RTL/adbg_tap_top/dut.v
module adbg_tap_top ( tms_pad_i, tck_pad_i, trstn_pad_i, tdi_pad_i, tdo_pad_o, tdo_padoe_o, test_mode_i, test_logic_reset_o, run_test_idle_o, shift_dr_o, pause_dr_o, update_dr_o, capture_dr_o, extest_select_o, sample_preload_select_o, mbist_select_o, debug_select_o, tdi_o, debug_tdo_i, bs_chain_tdo_i, mbist_tdo_i );

input wire tms_pad_i;

input wire tck_pad_i;

input wire trstn_pad_i;

input wire tdi_pad_i;

output reg tdo_pad_o;

output reg tdo_padoe_o;

input wire test_mode_i;

 output wire test_logic_reset_o;

 output wire run_test_idle_o;

 output wire shift_dr_o;

 output wire pause_dr_o;

 output wire update_dr_o;

 output wire capture_dr_o;

 output wire extest_select_o;

 output wire sample_preload_select_o;

 output wire mbist_select_o;

 output wire debug_select_o;

 output wire tdi_o;

input wire debug_tdo_i;

input wire bs_chain_tdo_i;

input wire mbist_tdo_i;

 reg test_logic_reset;

 reg run_test_idle;

 reg select_dr_scan;

 reg capture_dr;

 reg shift_dr;

 reg exit1_dr;

 reg pause_dr;

 reg exit2_dr;

 reg update_dr;

 reg select_ir_scan;

 reg capture_ir;

 reg shift_ir;

 reg exit1_ir;

 reg pause_ir;

 reg exit2_ir;

 reg update_ir;

 reg extest_select;

 reg sample_preload_select;

 reg idcode_select;

 reg mbist_select;

 reg debug_select;

 reg bypass_select;

 wire s_clk_neg;

 wire s_tck_inv;

 assign s_tck_inv = ~tck_pad_i;

 assign s_clk_neg = test_mode_i? tck_pad_i : s_tck_inv;

 assign tdi_o = tdi_pad_i;

 assign test_logic_reset_o = test_logic_reset;

 assign run_test_idle_o = run_test_idle;

 assign shift_dr_o = shift_dr;

 assign pause_dr_o = pause_dr;

 assign update_dr_o = update_dr;

 assign capture_dr_o = capture_dr;

 assign extest_select_o = extest_select;

 assign sample_preload_select_o = sample_preload_select;

 assign mbist_select_o = mbist_select;

 assign debug_select_o = debug_select;

reg [3:0] TAP_state;

reg [3:0] next_TAP_state;

 reg passchk;

 reg [31:0] correct;

 reg [31:0] pass;

 reg [4:0] bitindex;

always @(posedge tck_pad_i or negedge trstn_pad_i) begin $display("achieve node: 13,1"); if (trstn_pad_i == 0) begin $display("achieve node: 13,1,1"); TAP_state = 4'hF; pass = 32'hDEADBEEF; end else begin  $display("achieve node: 13,1,0");TAP_state = next_TAP_state; end  end

always @(TAP_state or tms_pad_i) begin 
    $display("achieve node: 14,0"); 
    case (TAP_state) 
    4'hF: begin  passchk = 0; $display("achieve node: 14,0,1"); if (tms_pad_i) begin  $display("achieve node: 14,0,1,1");next_TAP_state = 4'hF; end  else begin  $display("achieve node: 14,0,1,0");next_TAP_state = 4'hC; end  end 
    4'hC: begin if (tms_pad_i && passchk) begin  $display("achieve node: 14,0,2,1");next_TAP_state = 4'h7; $display("achieve node: 14,0,2"); end else begin $display("achieve node: 14,0,2,0");  next_TAP_state = 4'hC;
     if (correct >= 32'h0001_FFFF) begin  passchk = 1; $display("achieve node: 14,0,2,0,1"); end else if (tdi_o == pass[bitindex]) begin $display("achieve node: 14,0,2,0,0,1"); correct = correct + 1'b1; bitindex = bitindex + 1'b1; end
      end 
     end 
    4'h7: begin if (tms_pad_i) begin  $display("achieve node: 14,0,3,1");next_TAP_state = 4'h4; $display("achieve node: 14,0,3"); end  else begin  $display("achieve node: 14,0,3,0");next_TAP_state = 4'h6; end  end 4'h6: begin if (tms_pad_i) begin  $display("achieve node: 14,0,4,1");next_TAP_state = 4'h1; $display("achieve node: 14,0,4"); end  else begin  $display("achieve node: 14,0,4,0");next_TAP_state = 4'h2; end  end 4'h2: begin if (tms_pad_i) begin  $display("achieve node: 14,0,5,1");next_TAP_state = 4'h1; $display("achieve node: 14,0,5"); end  else begin  $display("achieve node: 14,0,5,0");next_TAP_state = 4'h2; end  end 4'h1: begin if (tms_pad_i) begin  $display("achieve node: 14,0,6,1");next_TAP_state = 4'h5; $display("achieve node: 14,0,6"); end  else begin  $display("achieve node: 14,0,6,0");next_TAP_state = 4'h3; end  end 4'h3: begin if (tms_pad_i) begin  $display("achieve node: 14,0,7,1");next_TAP_state = 4'h0; $display("achieve node: 14,0,7"); end  else begin  $display("achieve node: 14,0,7,0");next_TAP_state = 4'h3; end  end 4'h0: begin if (tms_pad_i) begin  $display("achieve node: 14,0,8,1");next_TAP_state = 4'h5; $display("achieve node: 14,0,8"); end  else begin  $display("achieve node: 14,0,8,0");next_TAP_state = 4'h2; end  end 4'h5: begin if (tms_pad_i) begin  $display("achieve node: 14,0,9,1");next_TAP_state = 4'h7; $display("achieve node: 14,0,9"); end  else begin  $display("achieve node: 14,0,9,0");next_TAP_state = 4'hC; end  end 4'h4: begin if (tms_pad_i) begin  $display("achieve node: 14,0,10,1");next_TAP_state = 4'hF; $display("achieve node: 14,0,10"); end  else begin  $display("achieve node: 14,0,10,0");next_TAP_state = 4'hE; end  end 4'hE: begin if (tms_pad_i) begin  $display("achieve node: 14,0,11,1");next_TAP_state = 4'h9; $display("achieve node: 14,0,11"); end  else begin  $display("achieve node: 14,0,11,0");next_TAP_state = 4'hA; end  end 4'hA: begin if (tms_pad_i) begin  $display("achieve node: 14,0,12,1");next_TAP_state = 4'h9; $display("achieve node: 14,0,12"); end  else begin  $display("achieve node: 14,0,12,0");next_TAP_state = 4'hA; end  end 4'h9: begin if (tms_pad_i) begin  $display("achieve node: 14,0,13,1");next_TAP_state = 4'hD; $display("achieve node: 14,0,13"); end  else begin  $display("achieve node: 14,0,13,0");next_TAP_state = 4'hB; end  end 4'hB: begin if (tms_pad_i) begin  $display("achieve node: 14,0,14,1");next_TAP_state = 4'h8; $display("achieve node: 14,0,14"); end  else begin  $display("achieve node: 14,0,14,0");next_TAP_state = 4'hB; end  end 4'h8: begin if (tms_pad_i) begin  $display("achieve node: 14,0,15,1");next_TAP_state = 4'hD; $display("achieve node: 14,0,15"); end  else begin  $display("achieve node: 14,0,15,0");next_TAP_state = 4'hA; end  end 4'hD: begin if (tms_pad_i) begin  $display("achieve node: 14,0,16,1");next_TAP_state = 4'h7; $display("achieve node: 14,0,16"); end  else begin  $display("achieve node: 14,0,16,0");next_TAP_state = 4'hC; end  end default: begin next_TAP_state = 4'hF; $display("achieve node: 14,0,17"); end endcase end

always @(TAP_state) begin $display("achieve node: 15,0"); test_logic_reset = 1'b0; run_test_idle = 1'b0; select_dr_scan = 1'b0; capture_dr = 1'b0; shift_dr = 1'b0; exit1_dr = 1'b0; pause_dr = 1'b0; exit2_dr = 1'b0; update_dr = 1'b0; select_ir_scan = 1'b0; capture_ir = 1'b0; shift_ir = 1'b0; exit1_ir = 1'b0; pause_ir = 1'b0; exit2_ir = 1'b0; update_ir = 1'b0; case (TAP_state) 4'hF: begin $display("achieve node: 15,0,1"); test_logic_reset = 1'b1; end 4'hC: begin $display("achieve node: 15,0,2"); run_test_idle = 1'b1; end 4'h7: begin $display("achieve node: 15,0,3"); select_dr_scan = 1'b1; end 4'h6: begin $display("achieve node: 15,0,4"); capture_dr = 1'b1; end 4'h2: begin $display("achieve node: 15,0,5"); shift_dr = 1'b1; end 4'h1: begin $display("achieve node: 15,0,6"); exit1_dr = 1'b1; end 4'h3: begin $display("achieve node: 15,0,7"); pause_dr = 1'b1; end 4'h0: begin $display("achieve node: 15,0,8"); exit2_dr = 1'b1; end 4'h5: begin $display("achieve node: 15,0,9"); update_dr = 1'b1; end 4'h4: begin $display("achieve node: 15,0,10"); select_ir_scan = 1'b1; end 4'hE: begin $display("achieve node: 15,0,11"); capture_ir = 1'b1; end 4'hA: begin $display("achieve node: 15,0,12"); shift_ir = 1'b1; end 4'h9: begin $display("achieve node: 15,0,13"); exit1_ir = 1'b1; end 4'hB: begin $display("achieve node: 15,0,14"); pause_ir = 1'b1; end 4'h8: begin $display("achieve node: 15,0,15"); exit2_ir = 1'b1; end 4'hD: begin $display("achieve node: 15,0,16"); update_ir = 1'b1; end default: begin ; $display("achieve node: 15,0,17"); end endcase end

reg [3:0] jtag_ir;

reg [3:0] latched_jtag_ir;

 wire instruction_tdo;

always @(posedge tck_pad_i or negedge trstn_pad_i) begin $display("achieve node: 16,1");if (trstn_pad_i == 0) begin  $display("achieve node: 16,1,1");jtag_ir[3:0] <= 4'b0; end  else if (test_logic_reset == 1) begin  $display("achieve node: 16,1,0,1");jtag_ir[3:0] <= 4'b0; end  else if (capture_ir) begin  $display("achieve node: 16,1,0,0,1");jtag_ir <= 4'b0101; end  else if (shift_ir) begin  $display("achieve node: 16,1,0,0,0,1");jtag_ir[3:0] <= {tdi_pad_i, jtag_ir[3:1]}; end end

assign instruction_tdo = jtag_ir[0];

always @(posedge s_clk_neg or negedge trstn_pad_i) begin $display("achieve node: 18,1");if (trstn_pad_i == 0) begin  $display("achieve node: 18,1,1");latched_jtag_ir <= 4'b0010; end  else if (test_logic_reset) begin  $display("achieve node: 18,1,0,1");latched_jtag_ir <= 4'b0010; end  else if (update_ir) begin  $display("achieve node: 18,1,0,0,1");latched_jtag_ir <= jtag_ir; end end

 reg [31:0] idcode_reg;

 wire idcode_tdo;

always @(posedge tck_pad_i or negedge trstn_pad_i) begin $display("achieve node: 19,1");if (trstn_pad_i == 0) begin  $display("achieve node: 19,1,1");idcode_reg <= 32'h249511c3; end  else if (test_logic_reset) begin  $display("achieve node: 19,1,0,1");idcode_reg <= 32'h249511c3; end  else if (idcode_select & capture_dr) begin  $display("achieve node: 19,1,0,0,1");idcode_reg <= 32'h249511c3; end  else if (idcode_select & shift_dr) begin  $display("achieve node: 19,1,0,0,0,1");idcode_reg <= {tdi_pad_i, idcode_reg[31:1]}; end end

assign idcode_tdo = idcode_reg[0];

 wire bypassed_tdo;

reg bypass_reg;

always @(posedge tck_pad_i or negedge trstn_pad_i) begin $display("achieve node: 21,1");if (trstn_pad_i == 0) begin  $display("achieve node: 21,1,1");bypass_reg <= 1'b0; end  else if (test_logic_reset == 1) begin  $display("achieve node: 21,1,0,1");bypass_reg <= 1'b0; end  else if (bypass_select & capture_dr) begin  $display("achieve node: 21,1,0,0,1");bypass_reg <= 1'b0; end  else if (bypass_select & shift_dr) begin  $display("achieve node: 21,1,0,0,0,1");bypass_reg <= tdi_pad_i; end end

assign bypassed_tdo = bypass_reg;

always @(latched_jtag_ir) begin $display("achieve node: 23,0"); extest_select = 1'b0; sample_preload_select = 1'b0; idcode_select = 1'b0; mbist_select = 1'b0; debug_select = 1'b0; bypass_select = 1'b0; case (latched_jtag_ir) /* synthesis parallel_case */ 4'b0000: begin $display("achieve node: 23,0,1"); extest_select = 1'b1; end 4'b0001: begin $display("achieve node: 23,0,2"); sample_preload_select = 1'b1; end 4'b0010: begin $display("achieve node: 23,0,3"); idcode_select = 1'b1; end 4'b1001: begin $display("achieve node: 23,0,4"); mbist_select = 1'b1; end 4'b1000: begin $display("achieve node: 23,0,5"); debug_select = 1'b1; end 4'b1111: begin $display("achieve node: 23,0,6"); bypass_select = 1'b1; end default: begin bypass_select = 1'b1; $display("achieve node: 23,0,7"); end endcase end

reg tdo_mux_out;

always @ (shift_ir or instruction_tdo or latched_jtag_ir or idcode_tdo or debug_tdo_i or bs_chain_tdo_i or mbist_tdo_i or bypassed_tdo or bs_chain_tdo_i)begin if (shift_ir) begin  $display("achieve node: 24,0,1");tdo_mux_out = instruction_tdo; end else begin $display("achieve node: 24,0,0");  case (latched_jtag_ir) 4'b0010: begin $display("achieve node: 24,0,0,1"); tdo_mux_out = idcode_tdo; end 4'b1000: begin $display("achieve node: 24,0,0,2"); tdo_mux_out = debug_tdo_i; end 4'b0001: begin $display("achieve node: 24,0,0,3"); tdo_mux_out = bs_chain_tdo_i; end 4'b0000: begin $display("achieve node: 24,0,0,4"); tdo_mux_out = bs_chain_tdo_i; end 4'b1001: begin $display("achieve node: 24,0,0,5"); tdo_mux_out = mbist_tdo_i; end default: begin tdo_mux_out = bypassed_tdo; $display("achieve node: 24,0,0,6"); end endcase end end

always @(posedge s_clk_neg or negedge trstn_pad_i) begin $display("achieve node: 25,1");if (trstn_pad_i == 0) begin  $display("achieve node: 25,1,1");tdo_pad_o <= 1'b0; end  else begin  $display("achieve node: 25,1,0");tdo_pad_o <= tdo_mux_out; end  end

always @(posedge s_clk_neg or negedge trstn_pad_i) begin $display("achieve node: 26,1");if (trstn_pad_i == 0) begin  $display("achieve node: 26,1,1");tdo_padoe_o <= 1'b0; end  else begin  $display("achieve node: 26,1,0");tdo_padoe_o <= shift_ir | shift_dr; end  end

endmodule

RTL/adbg_tap_top/adbg_tap_top_tb.v
`timescale 1ns/1ps
module adbg_tap_top_tb();
reg tms_pad_i;
reg tck_pad_i;
reg trstn_pad_i;
reg tdi_pad_i;
wire tdo_pad_o;
wire tdo_padoe_o;
reg test_mode_i;
wire test_logic_reset_o;
wire run_test_idle_o;
wire shift_dr_o;
wire pause_dr_o;
wire update_dr_o;
wire capture_dr_o;
wire extest_select_o;
wire sample_preload_select_o;
wire mbist_select_o;
wire debug_select_o;
wire tdi_o;
reg debug_tdo_i;
reg bs_chain_tdo_i;
reg mbist_tdo_i;

// 实例化待测模块
adbg_tap_top uut (
    .tms_pad_i(tms_pad_i),
    .tck_pad_i(tck_pad_i),
    .trstn_pad_i(trstn_pad_i),
    .tdi_pad_i(tdi_pad_i),
    .tdo_pad_o(tdo_pad_o),
    .tdo_padoe_o(tdo_padoe_o),
    .test_mode_i(test_mode_i),
    .test_logic_reset_o(test_logic_reset_o),
    .run_test_idle_o(run_test_idle_o),
    .shift_dr_o(shift_dr_o),
    .pause_dr_o(pause_dr_o),
    .update_dr_o(update_dr_o),
    .capture_dr_o(capture_dr_o),
    .extest_select_o(extest_select_o),
    .sample_preload_select_o(sample_preload_select_o),
    .mbist_select_o(mbist_select_o),
    .debug_select_o(debug_select_o),
    .tdi_o(tdi_o),
    .debug_tdo_i(debug_tdo_i),
    .bs_chain_tdo_i(bs_chain_tdo_i),
    .mbist_tdo_i(mbist_tdo_i)
    );

// 时钟激励
initial begin
    tck_pad_i = 0;
    forever #5 tck_pad_i = ~tck_pad_i;
end

// 复位激励
initial begin
    trstn_pad_i = 0;
    #10;
    trstn_pad_i = 1;
end

integer i;
initial begin
    tms_pad_i = 1;
    tdi_pad_i = 0;
    test_mode_i = 0;
    debug_tdo_i = 0;
    bs_chain_tdo_i = 0;
    mbist_tdo_i = 0;
    #10;
    for(i = 0; i < 400; i = i + 1) begin
        $display("********Period %d********", i);
        tms_pad_i = $random & 1'd1;
        tdi_pad_i = $random & 1'd1;
        test_mode_i = $random & 1'd1;
        debug_tdo_i = $random & 1'd1;
        bs_chain_tdo_i = $random & 1'd1;
        mbist_tdo_i = $random & 1'd1;
        #10;
    end
    $finish;
end
initial begin
    $dumpfile("wave.vcd");
    $dumpvars(0, adbg_tap_top_tb);
end

endmodule

RTL/adbg_tap_top/wave.vcd
$date
	Tue Apr 08 20:27:20 2025
$end
$version
	Icarus Verilog
$end
$timescale
	1ps
$end
$scope module adbg_tap_top_tb $end
$var wire 1 ! update_dr_o $end
$var wire 1 " test_logic_reset_o $end
$var wire 1 # tdo_padoe_o $end
$var wire 1 $ tdo_pad_o $end
$var wire 1 % tdi_o $end
$var wire 1 & shift_dr_o $end
$var wire 1 ' sample_preload_select_o $end
$var wire 1 ( run_test_idle_o $end
$var wire 1 ) pause_dr_o $end
$var wire 1 * mbist_select_o $end
$var wire 1 + extest_select_o $end
$var wire 1 , debug_select_o $end
$var wire 1 - capture_dr_o $end
$var reg 1 . bs_chain_tdo_i $end
$var reg 1 / debug_tdo_i $end
$var reg 1 0 mbist_tdo_i $end
$var reg 1 1 tck_pad_i $end
$var reg 1 2 tdi_pad_i $end
$var reg 1 3 test_mode_i $end
$var reg 1 4 tms_pad_i $end
$var reg 1 5 trstn_pad_i $end
$var integer 32 6 i [31:0] $end
$scope module uut $end
$var wire 1 . bs_chain_tdo_i $end
$var wire 1 7 bypassed_tdo $end
$var wire 1 - capture_dr_o $end
$var wire 1 , debug_select_o $end
$var wire 1 / debug_tdo_i $end
$var wire 1 + extest_select_o $end
$var wire 1 * mbist_select_o $end
$var wire 1 0 mbist_tdo_i $end
$var wire 1 ) pause_dr_o $end
$var wire 1 ( run_test_idle_o $end
$var wire 1 8 s_tck_inv $end
$var wire 1 ' sample_preload_select_o $end
$var wire 1 & shift_dr_o $end
$var wire 1 1 tck_pad_i $end
$var wire 1 % tdi_o $end
$var wire 1 2 tdi_pad_i $end
$var wire 1 " test_logic_reset_o $end
$var wire 1 3 test_mode_i $end
$var wire 1 4 tms_pad_i $end
$var wire 1 5 trstn_pad_i $end
$var wire 1 ! update_dr_o $end
$var wire 1 9 s_clk_neg $end
$var wire 1 : instruction_tdo $end
$var wire 1 ; idcode_tdo $end
$var reg 4 < TAP_state [3:0] $end
$var reg 5 = bitindex [4:0] $end
$var reg 1 > bypass_reg $end
$var reg 1 ? bypass_select $end
$var reg 1 @ capture_dr $end
$var reg 1 A capture_ir $end
$var reg 32 B correct [31:0] $end
$var reg 1 C debug_select $end
$var reg 1 D exit1_dr $end
$var reg 1 E exit1_ir $end
$var reg 1 F exit2_dr $end
$var reg 1 G exit2_ir $end
$var reg 1 H extest_select $end
$var reg 32 I idcode_reg [31:0] $end
$var reg 1 J idcode_select $end
$var reg 4 K jtag_ir [3:0] $end
$var reg 4 L latched_jtag_ir [3:0] $end
$var reg 1 M mbist_select $end
$var reg 4 N next_TAP_state [3:0] $end
$var reg 32 O pass [31:0] $end
$var reg 1 P passchk $end
$var reg 1 Q pause_dr $end
$var reg 1 R pause_ir $end
$var reg 1 S run_test_idle $end
$var reg 1 T sample_preload_select $end
$var reg 1 U select_dr_scan $end
$var reg 1 V select_ir_scan $end
$var reg 1 W shift_dr $end
$var reg 1 X shift_ir $end
$var reg 1 Y tdo_mux_out $end
$var reg 1 $ tdo_pad_o $end
$var reg 1 # tdo_padoe_o $end
$var reg 1 Z test_logic_reset $end
$var reg 1 [ update_dr $end
$var reg 1 \ update_ir $end
$upscope $end
$upscope $end
$enddefinitions $end
$comment Show the parameter values. $end
$dumpall
$end
#0
$dumpvars
0\
0[
1Z
1Y
0X
0W
0V
0U
0T
0S
0R
0Q
0P
b11011110101011011011111011101111 O
b1111 N
0M
b10 L
b0 K
1J
b100100100101010001000111000011 I
0H
0G
0F
0E
0D
0C
bx B
0A
0@
0?
0>
bx =
b1111 <
1;
0:
19
18
07
bx 6
05
14
03
02
01
00
0/
0.
0-
0,
0+
0*
0)
0(
0'
0&
0%
0$
0#
1"
0!
$end
#5000
09
08
11
#10000
18
b1100 N
01
10
1.
1/
13
1%
12
04
b0 6
15
#15000
1$
1(
1S
0"
0Z
08
b1100 <
19
11
#20000
18
09
01
0.
0%
02
14
b1 6
#25000
08
19
11
#30000
18
09
01
00
1.
0/
b10 6
#35000
08
19
11
#40000
18
19
01
0.
1/
03
1%
12
b11 6
#45000
09
08
11
#50000
19
18
01
10
1.
04
b100 6
#55000
09
08
11
#60000
19
18
01
0.
0/
0%
02
14
b101 6
#65000
09
08
11
#70000
18
01
1.
1/
13
1%
12
04
b110 6
#75000
08
19
11
#80000
18
09
01
00
0%
02
b111 6
#85000
08
19
11
#90000
18
19
01
0/
03
b1000 6
#95000
09
08
11
#100000
18
01
0.
13
1%
12
b1001 6
#105000
08
19
11
#110000
18
09
01
10
1.
1/
0%
02
b1010 6
#115000
08
19
11
#120000
18
19
01
03
14
b1011 6
#125000
09
08
11
#130000
18
01
0.
13
04
b1100 6
#135000
08
19
11
#140000
18
09
01
00
1.
14
b1101 6
#145000
08
19
11
#150000
18
19
01
0.
0/
03
1%
12
b1110 6
#155000
09
08
11
#160000
19
18
01
10
1.
b1111 6
#165000
09
08
11
#170000
18
01
13
b10000 6
#175000
08
19
11
#180000
18
19
01
00
0.
03
0%
02
b10001 6
#185000
09
08
11
#190000
18
01
10
1.
1/
13
04
b10010 6
#195000
08
19
11
#200000
18
09
01
00
0.
14
b10011 6
#205000
08
19
11
#210000
18
19
01
10
1.
03
1%
12
b10100 6
#215000
09
08
11
#220000
19
18
01
00
0/
0%
02
b10101 6
#225000
09
08
11
#230000
18
01
0.
1/
13
04
b10110 6
#235000
08
19
11
#240000
18
19
01
1.
0/
03
14
b10111 6
#245000
09
08
11
#250000
19
18
01
10
1/
1%
12
04
b11000 6
#255000
09
08
11
#260000
19
18
01
0.
0/
14
b11001 6
#265000
09
08
11
#270000
18
01
00
1/
13
0%
02
04
b11010 6
#275000
08
19
11
#280000
18
09
01
0/
1%
12
b11011 6
#285000
08
19
11
#290000
18
19
01
10
03
14
b11100 6
#295000
09
08
11
#300000
18
01
00
13
0%
02
04
b11101 6
#305000
08
19
11
#310000
18
09
01
1/
14
b11110 6
#315000
08
19
11
#320000
18
09
01
0/
04
b11111 6
#325000
08
19
11
#330000
18
09
01
10
1/
1%
12
b100000 6
#335000
08
19
11
#340000
18
19
01
1.
0/
03
14
b100001 6
#345000
09
08
11
#350000
18
01
13
b100010 6
#355000
08
19
11
#360000
18
19
01
03
0%
02
04
b100011 6
#365000
09
08
11
#370000
18
01
0.
13
b100100 6
#375000
08
19
11
#380000
18
09
01
b100101 6
#385000
08
19
11
#390000
18
19
01
03
1%
12
14
b100110 6
#395000
09
08
11
#400000
18
01
00
13
0%
02
04
b100111 6
#405000
08
19
11
#410000
18
19
01
10
03
1%
12
b101000 6
#415000
09
08
11
#420000
18
01
1.
1/
13
0%
02
14
b101001 6
#425000
08
19
11
#430000
18
09
01
00
0.
1%
12
04
b101010 6
#435000
08
19
11
#440000
18
19
01
1.
03
0%
02
14
b101011 6
#445000
09
08
11
#450000
19
18
01
0/
1%
12
04
b101100 6
#455000
09
08
11
#460000
19
18
01
10
0.
1/
14
b101101 6
#465000
09
08
11
#470000
18
01
00
0/
13
0%
02
04
b101110 6
#475000
08
19
11
#480000
18
09
01
1.
1/
1%
12
14
b101111 6
#485000
08
19
11
#490000
18
09
01
0.
0/
b110000 6
#495000
08
19
11
#500000
18
19
01
10
1.
1/
03
0%
02
04
b110001 6
#505000
09
08
11
#510000
18
01
0.
13
1%
12
14
b110010 6
#515000
08
19
11
#520000
18
09
01
1.
b110011 6
#525000
08
19
11
#530000
18
19
01
00
03
0%
02
b110100 6
#535000
09
08
11
#540000
19
18
01
0.
04
b110101 6
#545000
09
08
11
#550000
19
18
01
1.
0/
b110110 6
#555000
09
08
11
#560000
19
18
01
0.
1%
12
b110111 6
#565000
09
08
11
#570000
18
01
1.
1/
13
14
b111000 6
#575000
08
19
11
#580000
18
09
01
0/
b111001 6
#585000
08
19
11
#590000
18
09
01
04
b111010 6
#595000
08
19
11
#600000
18
19
01
0.
03
b111011 6
#605000
09
08
11
#610000
18
01
10
1/
13
14
b111100 6
#615000
08
19
11
#620000
18
09
01
1.
b111101 6
#625000
08
19
11
#630000
18
19
01
00
0.
03
04
b111110 6
#635000
09
08
11
#640000
19
18
01
0/
0%
02
14
b111111 6
#645000
09
08
11
#650000
19
18
01
b1000000 6
#655000
09
08
11
#660000
19
18
01
1/
1%
12
04
b1000001 6
#665000
09
08
11
#670000
18
01
10
13
0%
02
14
b1000010 6
#675000
08
19
11
#680000
18
19
01
00
0/
03
1%
12
04
b1000011 6
#685000
09
08
11
#690000
18
01
10
1.
13
0%
02
14
b1000100 6
#695000
08
19
11
#700000
18
19
01
1/
03
1%
12
04
b1000101 6
#705000
09
08
11
#710000
18
01
0.
0/
13
b1000110 6
#715000
08
19
11
#720000
18
19
01
00
1.
1/
03
0%
02
14
b1000111 6
#725000
09
08
11
#730000
19
18
01
10
0/
1%
12
04
b1001000 6
#735000
09
08
11
#740000
18
01
0.
13
0%
02
b1001001 6
#745000
08
19
11
#750000
18
09
01
1.
14
b1001010 6
#755000
08
19
11
#760000
18
09
01
0.
1/
1%
12
04
b1001011 6
#765000
08
19
11
#770000
18
19
01
00
1.
0/
03
14
b1001100 6
#775000
09
08
11
#780000
19
18
01
10
04
b1001101 6
#785000
09
08
11
#790000
19
18
01
1/
b1001110 6
#795000
09
08
11
#800000
19
18
01
0.
0%
02
14
b1001111 6
#805000
09
08
11
#810000
18
01
0/
13
1%
12
04
b1010000 6
#815000
08
19
11
#820000
18
19
01
00
1.
03
14
b1010001 6
#825000
09
08
11
#830000
18
01
10
0.
1/
13
04
b1010010 6
#835000
08
19
11
#840000
18
19
01
1.
0/
03
0%
02
14
b1010011 6
#845000
09
08
11
#850000
19
18
01
b1010100 6
#855000
09
08
11
#860000
19
18
01
1/
1%
12
b1010101 6
#865000
09
08
11
#870000
18
01
0.
13
b1010110 6
#875000
08
19
11
#880000
18
19
01
1.
03
0%
02
04
b1010111 6
#885000
09
08
11
#890000
18
01
13
1%
12
14
b1011000 6
#895000
08
19
11
#900000
18
19
01
00
0.
03
0%
02
04
b1011001 6
#905000
09
08
11
#910000
18
01
0/
13
1%
12
b1011010 6
#915000
08
19
11
#920000
18
19
01
10
1/
03
14
b1011011 6
#925000
09
08
11
#930000
19
18
01
1.
0%
02
04
b1011100 6
#935000
09
08
11
#940000
19
18
01
0.
1%
12
b1011101 6
#945000
09
08
11
#950000
19
18
01
0/
0%
02
14
b1011110 6
#955000
09
08
11
#960000
19
18
01
1/
b1011111 6
#965000
09
08
11
#970000
18
01
1.
0/
13
1%
12
04
b1100000 6
#975000
08
19
11
#980000
18
19
01
03
0%
02
b1100001 6
#985000
09
08
11
#990000
18
01
00
0.
13
1%
12
14
b1100010 6
#995000
08
19
11
#1000000
18
19
01
10
1.
03
0%
02
04
b1100011 6
#1005000
09
08
11
#1010000
18
01
00
1/
13
1%
12
14
b1100100 6
#1015000
08
19
11
#1020000
18
19
01
10
0.
0/
03
0%
02
04
b1100101 6
#1025000
09
08
11
#1030000
18
01
1.
13
14
b1100110 6
#1035000
08
19
11
#1040000
18
19
01
03
b1100111 6
#1045000
09
08
11
#1050000
19
18
01
00
0.
1%
12
04
b1101000 6
#1055000
09
08
11
#1060000
18
01
10
13
0%
02
b1101001 6
#1065000
08
19
11
#1070000
18
09
01
00
1.
1/
b1101010 6
#1075000
08
19
11
#1080000
18
09
01
1%
12
b1101011 6
#1085000
08
19
11
#1090000
18
09
01
10
0.
14
b1101100 6
#1095000
08
19
11
#1100000
18
09
01
0/
0%
02
04
b1101101 6
#1105000
08
19
11
#1110000
18
19
01
00
03
b1101110 6
#1115000
09
08
11
#1120000
19
18
01
10
1.
1%
12
14
b1101111 6
#1125000
09
08
11
#1130000
18
01
00
1/
13
b1110000 6
#1135000
08
19
11
#1140000
18
19
01
10
0/
03
0%
02
b1110001 6
#1145000
09
08
11
#1150000
18
01
00
0.
1/
13
1%
12
04
b1110010 6
#1155000
08
19
11
#1160000
18
09
01
1.
0%
02
b1110011 6
#1165000
08
19
11
#1170000
18
19
01
0.
0/
03
14
b1110100 6
#1175000
09
08
11
#1180000
18
01
10
13
04
b1110101 6
#1185000
08
19
11
#1190000
18
09
01
00
1/
1%
12
14
b1110110 6
#1195000
08
19
11
#1200000
18
09
01
0%
02
04
b1110111 6
#1205000
08
19
11
#1210000
18
09
01
1.
1%
12
14
b1111000 6
#1215000
08
19
11
#1220000
18
09
01
0/
0%
02
04
b1111001 6
#1225000
08
19
11
#1230000
18
19
01
03
b1111010 6
#1235000
09
08
11
#1240000
19
18
01
1/
1%
12
14
b1111011 6
#1245000
09
08
11
#1250000
18
01
0.
13
0%
02
b1111100 6
#1255000
08
19
11
#1260000
18
19
01
0/
03
1%
12
b1111101 6
#1265000
09
08
11
#1270000
18
01
10
13
b1111110 6
#1275000
08
19
11
#1280000
18
09
01
b1111111 6
#1285000
08
19
11
#1290000
18
19
01
1/
03
0%
02
b10000000 6
#1295000
09
08
11
#1300000
18
01
00
0/
13
1%
12
04
b10000001 6
#1305000
08
19
11
#1310000
18
09
01
1.
0%
02
b10000010 6
#1315000
08
19
11
#1320000
18
09
01
10
0.
b10000011 6
#1325000
08
19
11
#1330000
18
09
01
1.
1/
1%
12
b10000100 6
#1335000
08
19
11
#1340000
18
09
01
0.
0/
b10000101 6
#1345000
08
19
11
#1350000
18
09
01
1.
1/
b10000110 6
#1355000
08
19
11
#1360000
18
19
01
0.
03
b10000111 6
#1365000
09
08
11
#1370000
19
18
01
0/
0%
02
14
b10001000 6
#1375000
09
08
11
#1380000
19
18
01
1.
1/
b10001001 6
#1385000
09
08
11
#1390000
19
18
01
00
0.
0/
1%
12
b10001010 6
#1395000
09
08
11
#1400000
19
18
01
10
1/
0%
02
b10001011 6
#1405000
09
08
11
#1410000
18
01
00
0/
13
04
b10001100 6
#1415000
08
19
11
#1420000
18
19
01
1.
1/
03
1%
12
b10001101 6
#1425000
09
08
11
#1430000
19
18
01
10
b10001110 6
#1435000
09
08
11
#1440000
18
01
0.
0/
13
0%
02
14
b10001111 6
#1445000
08
19
11
#1450000
18
19
01
1.
1/
03
1%
12
b10010000 6
#1455000
09
08
11
#1460000
18
01
00
0/
13
b10010001 6
#1465000
08
19
11
#1470000
18
09
01
0%
02
04
b10010010 6
#1475000
08
19
11
#1480000
18
19
01
10
0.
03
14
b10010011 6
#1485000
09
08
11
#1490000
18
01
00
1.
13
04
b10010100 6
#1495000
08
19
11
#1500000
18
09
01
10
0.
1%
12
b10010101 6
#1505000
08
19
11
#1510000
18
09
01
1.
1/
0%
02
14
b10010110 6
#1515000
08
19
11
#1520000
18
19
01
0/
03
1%
12
04
b10010111 6
#1525000
09
08
11
#1530000
18
01
13
b10011000 6
#1535000
08
19
11
#1540000
18
09
01
00
0%
02
14
b10011001 6
#1545000
08
19
11
#1550000
18
19
01
0.
03
04
b10011010 6
#1555000
09
08
11
#1560000
18
01
1.
1/
13
b10011011 6
#1565000
08
19
11
#1570000
18
09
01
10
0.
b10011100 6
#1575000
08
19
11
