RTL/iic/iic_1.v
module i2c_master_top (
    wb_clk_i,
    rst_i,
    wb_adr_i,
    wb_dat_i,
    wb_dat_o,
    wb_we_i,
    wb_stb_i,
    wb_cyc_i,
    wb_ack_o,
    wb_inta_o,
    scl_pad_i,
    scl_pad_o,
    scl_padoen_o,
    sda_pad_i,
    sda_pad_o,
    sda_padoen_o
);
  input wire wb_clk_i;
  input wire rst_i;
  input wire [2:0] wb_adr_i;
  input wire [7:0] wb_dat_i;
  output reg [7:0] wb_dat_o;
  input wire wb_we_i;
  input wire wb_stb_i;
  input wire wb_cyc_i;
  output reg wb_ack_o;
  output reg wb_inta_o;
  input wire scl_pad_i;
  output wire scl_pad_o;
  output wire scl_padoen_o;
  input wire sda_pad_i;
  output wire sda_pad_o;
  output wire sda_padoen_o;
  reg [7:0] wb_dat_o;
  reg wb_ack_o;
  reg wb_inta_o;
  reg [15:0] prer;
  reg [7:0] ctr;
  reg [7:0] txr;
  reg [7:0] cr;
  reg rxack;
  reg tip;
  reg irq_flag;
  wire i2c_busy;
  reg al;
  wire wb_wacc = ((wb_cyc_i & wb_stb_i) & wb_we_i);
  wire sta = cr[7];
  wire sto = cr[6];
  wire rd = cr[5];
  wire wr = cr[4];
  wire ack = cr[3];
  wire iack = cr[0];
  wire [7:0] byte_controller_dout;
  wire byte_controller_i2c_busy;
  wire byte_controller_i2c_al;
  reg byte_controller_cmd_ack;
  reg byte_controller_ack_out;
  reg [3:0] byte_controller_core_cmd;
  reg byte_controller_core_txd;
  reg [7:0] byte_controller_sr;
  reg byte_controller_shift;
  reg byte_controller_ld;
  reg [2:0] byte_controller_dcnt;
  reg [4:0] byte_controller_c_state;
  reg byte_controller_target;
  wire byte_controller_bit_controller_scl_o;
  wire byte_controller_bit_controller_sda_o;
  reg byte_controller_bit_controller_cmd_ack;
  reg byte_controller_bit_controller_busy;
  reg byte_controller_bit_controller_al;
  reg byte_controller_bit_controller_dout;
  reg byte_controller_bit_controller_scl_oen;
  reg byte_controller_bit_controller_sda_oen;
  reg byte_controller_bit_controller_sSCL;
  reg byte_controller_bit_controller_sSDB;
  reg byte_controller_bit_controller_dscl_oen;
  reg byte_controller_bit_controller_sda_chk;
  reg byte_controller_bit_controller_clk_en;
  reg [15:0] byte_controller_bit_controller_cnt;
  reg [16:0] byte_controller_bit_controller_c_state;
  reg byte_controller_bit_controller_dSCL;
  reg byte_controller_bit_controller_dSDA;
  reg byte_controller_bit_controller_sta_condition;
  reg byte_controller_bit_controller_sto_condition;
  reg byte_controller_bit_controller_cmd_stop;
  always @(posedge wb_clk_i) begin
    wb_ack_o <= ((wb_cyc_i & wb_stb_i) & ~(wb_ack_o));
  end
  always @(posedge wb_clk_i) begin
    case (wb_adr_i)
      3'b000: begin
        wb_dat_o <= prer[7:0];
      end
      3'b001: begin
        wb_dat_o <= prer[15:8];
      end
      3'b010: begin
        wb_dat_o <= ctr;
      end
      3'b011: begin
        wb_dat_o <= byte_controller_dout;
      end
      3'b100: begin
        wb_dat_o <= {rxack, i2c_busy, al, 3'h0, tip, irq_flag};
      end
      3'b101: begin
        wb_dat_o <= txr;
      end
      3'b110: begin
        wb_dat_o <= cr;
      end
      3'b111: begin
        wb_dat_o <= 0;
      end
    endcase
  end
  always @(posedge wb_clk_i or negedge rst_i) begin
    if (!(rst_i)) begin
      prer <= 16'hffff;
      ctr  <= 8'h0;
      txr  <= 8'h0;
    end else begin
      if (wb_wacc) begin
        case (wb_adr_i)
          3'b000: begin
            prer <= {prer[15:8], wb_dat_i};
          end
          3'b001: begin
            prer <= {wb_dat_i, prer[7:0]};
          end
          3'b010: begin
            ctr <= wb_dat_i;
          end
          3'b011: begin
            txr <= wb_dat_i;
          end
        endcase
      end
    end
  end
  always @(posedge wb_clk_i or negedge rst_i) begin
    if (~(rst_i)) begin
      cr <= 8'h0;
    end else begin
      if (wb_wacc) begin
        if (ctr[7] & (wb_adr_i == 3'b100)) begin
          cr <= wb_dat_i;
        end
      end else begin
        if (byte_controller_cmd_ack | byte_controller_i2c_al) begin
          cr <= {4'h0, cr[3:0]};
        end
        cr <= {cr[7:3], 3'b0};
      end
    end
  end
  always @(posedge wb_clk_i or negedge rst_i) begin
    if (!(rst_i)) begin
      al <= 1'b0;
      rxack <= 1'b0;
      tip <= 1'b0;
      irq_flag <= 1'b0;
    end else begin
      al <= (byte_controller_i2c_al | (al & ~(sta)));
      rxack <= byte_controller_ack_out;
      tip <= (rd | wr);
      irq_flag <= (((byte_controller_cmd_ack | byte_controller_i2c_al) | irq_flag) & ~(iack));
    end
  end
  always @(posedge wb_clk_i or negedge rst_i) begin
    if (!(rst_i)) begin
      wb_inta_o <= 1'b0;
    end else begin
      wb_inta_o <= (irq_flag && ctr[6]);
    end
  end
  assign i2c_busy = byte_controller_bit_controller_busy;
  assign scl_pad_o = 1'b0;
  assign scl_padoen_o = byte_controller_bit_controller_scl_oen;
  assign sda_pad_o = 1'b0;
  assign sda_padoen_o = byte_controller_bit_controller_sda_oen;
  assign byte_controller_i2c_busy = byte_controller_bit_controller_busy;
  assign byte_controller_i2c_al = byte_controller_bit_controller_al;
  always @(posedge wb_clk_i or negedge rst_i) begin
    if (~(rst_i)) begin
      byte_controller_bit_controller_dscl_oen <= 1'b0;
    end else begin
      byte_controller_bit_controller_dscl_oen <= byte_controller_bit_controller_scl_oen;
    end
  end
  always @(posedge wb_clk_i or negedge rst_i) begin
    if (~(rst_i)) begin
      byte_controller_bit_controller_cnt <= 16'h0;
      byte_controller_bit_controller_clk_en <= 1'b1;
    end else begin
      if (~|(byte_controller_bit_controller_cnt) || ~(ctr[7])) begin
        if (  ~( ( byte_controller_bit_controller_dscl_oen &&  !( byte_controller_bit_controller_sSCL) )) ) 
                begin
          byte_controller_bit_controller_cnt <= prer;
          byte_controller_bit_controller_clk_en <= 1'b1;
        end else begin
          byte_controller_bit_controller_cnt <= byte_controller_bit_controller_cnt;
          byte_controller_bit_controller_clk_en <= 1'b0;
        end
      end else begin
        byte_controller_bit_controller_cnt <= (byte_controller_bit_controller_cnt - 16'h1);
        byte_controller_bit_controller_clk_en <= 1'b0;
      end
    end
  end
  always @(posedge wb_clk_i or negedge rst_i) begin
    if (~(rst_i)) begin
      byte_controller_bit_controller_sSCL <= 1'b1;
      byte_controller_bit_controller_sSDB <= 1'b1;
      byte_controller_bit_controller_dSCL <= 1'b1;
      byte_controller_bit_controller_dSDA <= 1'b1;
    end else begin
      byte_controller_bit_controller_sSCL <= scl_pad_i;
      byte_controller_bit_controller_sSDB <= sda_pad_i;
      byte_controller_bit_controller_dSCL <= byte_controller_bit_controller_sSCL;
      byte_controller_bit_controller_dSDA <= byte_controller_bit_controller_sSDB;
    end
  end
  always @(posedge wb_clk_i or negedge rst_i) begin
    if (~(rst_i)) begin
      byte_controller_bit_controller_sta_condition <= 1'b0;
      byte_controller_bit_controller_sto_condition <= 1'b0;
    end else begin
      byte_controller_bit_controller_sta_condition <= ( (  ~( byte_controller_bit_controller_sSDB) & byte_controller_bit_controller_dSDA ) & byte_controller_bit_controller_sSCL );
      byte_controller_bit_controller_sto_condition <= ( ( byte_controller_bit_controller_sSDB &  ~( byte_controller_bit_controller_dSDA) ) & byte_controller_bit_controller_sSCL );
    end
  end
  always @(posedge wb_clk_i or negedge rst_i) begin
    if (!(rst_i)) begin
      byte_controller_bit_controller_busy <= 1'b0;
    end else begin
      byte_controller_bit_controller_busy <= ( ( byte_controller_bit_controller_sta_condition | byte_controller_bit_controller_busy ) &  ~( byte_controller_bit_controller_sto_condition) );
    end
  end
  always @(posedge wb_clk_i or negedge rst_i) begin
    if (~(rst_i)) begin
      byte_controller_bit_controller_cmd_stop <= 1'b0;
    end else begin
      if (byte_controller_bit_controller_clk_en) begin
        byte_controller_bit_controller_cmd_stop <= (byte_controller_core_cmd == 4'b0010);
      end
    end
  end
  always @(posedge wb_clk_i or negedge rst_i) begin
    if (~(rst_i)) begin
      byte_controller_bit_controller_al <= 1'b0;
    end else begin
      byte_controller_bit_controller_al <= ( ( ( byte_controller_bit_controller_sda_chk &  ~( byte_controller_bit_controller_sSDB) ) & byte_controller_bit_controller_sda_oen ) | ( (  |( byte_controller_bit_controller_c_state) & byte_controller_bit_controller_sto_condition ) &  ~( byte_controller_bit_controller_cmd_stop) ) );
    end
  end
  always @(posedge wb_clk_i or negedge rst_i) begin
    if (~(rst_i)) begin
      byte_controller_bit_controller_dout <= 1'b0;
    end else begin
      if (byte_controller_bit_controller_sSCL & ~(byte_controller_bit_controller_dSCL)) begin
        byte_controller_bit_controller_dout <= byte_controller_bit_controller_sSDB;
      end
    end
  end
  always @(posedge wb_clk_i or negedge rst_i) begin
    if (!(rst_i)) begin
      byte_controller_bit_controller_c_state <= 17'b0_0000_0000_0000_0000;
      byte_controller_bit_controller_cmd_ack <= 1'b0;
      byte_controller_bit_controller_scl_oen <= 1'b1;
      byte_controller_bit_controller_sda_oen <= 1'b1;
      byte_controller_bit_controller_sda_chk <= 1'b0;
    end else begin
      if (byte_controller_bit_controller_al) begin
        byte_controller_bit_controller_c_state <= 17'b0_0000_0000_0000_0000;
        byte_controller_bit_controller_cmd_ack <= 1'b0;
        byte_controller_bit_controller_scl_oen <= 1'b1;
        byte_controller_bit_controller_sda_oen <= 1'b1;
        byte_controller_bit_controller_sda_chk <= 1'b0;
      end else begin
        byte_controller_bit_controller_cmd_ack <= 1'b0;
        if (byte_controller_bit_controller_clk_en) begin
          case (byte_controller_bit_controller_c_state)
            17'b0_0000_0000_0000_0000: begin
              case (byte_controller_core_cmd)
                4'b0001: begin
                  byte_controller_bit_controller_c_state <= 17'b0_0000_0000_0000_0001;
                end
                4'b0010: begin
                  byte_controller_bit_controller_c_state <= 17'b0_0000_0000_0010_0000;
                end
                4'b0100: begin
                  byte_controller_bit_controller_c_state <= 17'b0_0010_0000_0000_0000;
                end
                4'b1000: begin
                  byte_controller_bit_controller_c_state <= 17'b0_0000_0010_0000_0000;
                end
                default: begin
                  byte_controller_bit_controller_c_state <= 17'b0_0000_0000_0000_0000;
                end
              endcase
              byte_controller_bit_controller_scl_oen <= byte_controller_bit_controller_scl_oen;
              byte_controller_bit_controller_sda_oen <= byte_controller_bit_controller_sda_oen;
              byte_controller_bit_controller_sda_chk <= 1'b0;
            end
            17'b0_0000_0000_0000_0001: begin
              byte_controller_bit_controller_c_state <= 17'b0_0000_0000_0000_0010;
              byte_controller_bit_controller_scl_oen <= byte_controller_bit_controller_scl_oen;
              byte_controller_bit_controller_sda_oen <= 1'b1;
              byte_controller_bit_controller_sda_chk <= 1'b0;
            end
            17'b0_0000_0000_0000_0010: begin
              byte_controller_bit_controller_c_state <= 17'b0_0000_0000_0000_0100;
              byte_controller_bit_controller_scl_oen <= 1'b1;
              byte_controller_bit_controller_sda_oen <= 1'b1;
              byte_controller_bit_controller_sda_chk <= 1'b0;
            end
            17'b0_0000_0000_0000_0100: begin
              byte_controller_bit_controller_c_state <= 17'b0_0000_0000_0000_1000;
              byte_controller_bit_controller_scl_oen <= 1'b1;
              byte_controller_bit_controller_sda_oen <= 1'b0;
              byte_controller_bit_controller_sda_chk <= 1'b0;
            end
            17'b0_0000_0000_0000_1000: begin
              byte_controller_bit_controller_c_state <= 17'b0_0000_0000_0001_0000;
              byte_controller_bit_controller_scl_oen <= 1'b1;
              byte_controller_bit_controller_sda_oen <= 1'b0;
              byte_controller_bit_controller_sda_chk <= 1'b0;
            end
            17'b0_0000_0000_0001_0000: begin
              byte_controller_bit_controller_c_state <= 17'b0_0000_0000_0000_0000;
              byte_controller_bit_controller_cmd_ack <= 1'b1;
              byte_controller_bit_controller_scl_oen <= 1'b0;
              byte_controller_bit_controller_sda_oen <= 1'b0;
              byte_controller_bit_controller_sda_chk <= 1'b0;
            end
            17'b0_0000_0000_0010_0000: begin
              byte_controller_bit_controller_c_state <= 17'b0_0000_0000_0100_0000;
              byte_controller_bit_controller_scl_oen <= 1'b0;
              byte_controller_bit_controller_sda_oen <= 1'b0;
              byte_controller_bit_controller_sda_chk <= 1'b0;
            end
            17'b0_0000_0000_0100_0000: begin
              byte_controller_bit_controller_c_state <= 17'b0_0000_0000_1000_0000;
              byte_controller_bit_controller_scl_oen <= 1'b1;
              byte_controller_bit_controller_sda_oen <= 1'b0;
              byte_controller_bit_controller_sda_chk <= 1'b0;
            end
            17'b0_0000_0000_1000_0000: begin
              byte_controller_bit_controller_c_state <= 17'b0_0000_0001_0000_0000;
              byte_controller_bit_controller_scl_oen <= 1'b1;
              byte_controller_bit_controller_sda_oen <= 1'b0;
              byte_controller_bit_controller_sda_chk <= 1'b0;
            end
            17'b0_0000_0001_0000_0000: begin
              byte_controller_bit_controller_c_state <= 17'b0_0000_0000_0000_0000;
              byte_controller_bit_controller_cmd_ack <= 1'b1;
              byte_controller_bit_controller_scl_oen <= 1'b1;
              byte_controller_bit_controller_sda_oen <= 1'b1;
              byte_controller_bit_controller_sda_chk <= 1'b0;
            end
            17'b0_0000_0010_0000_0000: begin
              byte_controller_bit_controller_c_state <= 17'b0_0000_0100_0000_0000;
              byte_controller_bit_controller_scl_oen <= 1'b0;
              byte_controller_bit_controller_sda_oen <= 1'b1;
              byte_controller_bit_controller_sda_chk <= 1'b0;
            end
            17'b0_0000_0100_0000_0000: begin
              byte_controller_bit_controller_c_state <= 17'b0_0000_1000_0000_0000;
              byte_controller_bit_controller_scl_oen <= 1'b1;
              byte_controller_bit_controller_sda_oen <= 1'b1;
              byte_controller_bit_controller_sda_chk <= 1'b0;
            end
            17'b0_0000_1000_0000_0000: begin
              byte_controller_bit_controller_c_state <= 17'b0_0001_0000_0000_0000;
              byte_controller_bit_controller_scl_oen <= 1'b1;
              byte_controller_bit_controller_sda_oen <= 1'b1;
              byte_controller_bit_controller_sda_chk <= 1'b0;
            end
            17'b0_0001_0000_0000_0000: begin
              byte_controller_bit_controller_c_state <= 17'b0_0000_0000_0000_0000;
              byte_controller_bit_controller_cmd_ack <= 1'b1;
              byte_controller_bit_controller_scl_oen <= 1'b0;
              byte_controller_bit_controller_sda_oen <= 1'b1;
              byte_controller_bit_controller_sda_chk <= 1'b0;
            end
            17'b0_0010_0000_0000_0000: begin
              byte_controller_bit_controller_c_state <= 17'b0_0100_0000_0000_0000;
              byte_controller_bit_controller_scl_oen <= 1'b0;
              byte_controller_bit_controller_sda_oen <= byte_controller_core_txd;
              byte_controller_bit_controller_sda_chk <= 1'b0;
            end
            17'b0_0100_0000_0000_0000: begin
              byte_controller_bit_controller_c_state <= 17'b0_1000_0000_0000_0000;
              byte_controller_bit_controller_scl_oen <= 1'b1;
              byte_controller_bit_controller_sda_oen <= byte_controller_core_txd;
              byte_controller_bit_controller_sda_chk <= 1'b1;
            end
            17'b0_1000_0000_0000_0000: begin
              byte_controller_bit_controller_c_state <= 17'b1_0000_0000_0000_0000;
              byte_controller_bit_controller_scl_oen <= 1'b1;
              byte_controller_bit_controller_sda_oen <= byte_controller_core_txd;
              byte_controller_bit_controller_sda_chk <= 1'b1;
            end
            17'b1_0000_0000_0000_0000: begin
              byte_controller_bit_controller_c_state <= 17'b0_0000_0000_0000_0000;
              byte_controller_bit_controller_cmd_ack <= 1'b1;
              byte_controller_bit_controller_scl_oen <= 1'b0;
              byte_controller_bit_controller_sda_oen <= byte_controller_core_txd;
              byte_controller_bit_controller_sda_chk <= 1'b0;
            end
          endcase
        end
      end
    end
  end
  assign byte_controller_dout = byte_controller_sr;
  always @(posedge wb_clk_i or negedge rst_i) begin
    if (!(rst_i)) begin
      byte_controller_sr <= 8'h0;
    end else begin
      if (byte_controller_ld) begin
        byte_controller_sr <= txr;
      end else begin
        if (byte_controller_shift) begin
          byte_controller_sr <= {byte_controller_sr[6:0], byte_controller_bit_controller_dout};
        end
      end
    end
  end
  always @(posedge wb_clk_i or negedge rst_i) begin
    if (!(rst_i)) begin
      byte_controller_dcnt <= 3'h0;
    end else begin
      if (byte_controller_ld) begin
        byte_controller_dcnt <= 3'h7;
      end else begin
        if (byte_controller_shift) begin
          byte_controller_dcnt <= (byte_controller_dcnt - 3'h1);
        end
      end
    end
  end
  always @(posedge wb_clk_i or negedge rst_i) begin
    if (!(rst_i)) begin
      byte_controller_core_cmd <= 4'b0000;
      byte_controller_core_txd <= 1'b0;
      byte_controller_shift <= 1'b0;
      byte_controller_ld <= 1'b0;
      byte_controller_cmd_ack <= 1'b0;
      byte_controller_c_state <= 5'b0_0000;
      byte_controller_ack_out <= 1'b0;
    end else begin
      if (byte_controller_bit_controller_al) begin
        byte_controller_core_cmd <= 4'b0000;
        byte_controller_core_txd <= 1'b0;
        byte_controller_shift <= 1'b0;
        byte_controller_ld <= 1'b0;
        byte_controller_cmd_ack <= 1'b0;
        byte_controller_c_state <= 5'b0_0000;
        byte_controller_ack_out <= 1'b0;
      end else begin
        byte_controller_core_txd <= byte_controller_sr[7];
        byte_controller_shift <= 1'b0;
        byte_controller_ld <= 1'b0;
        byte_controller_cmd_ack <= 1'b0;
        case (byte_controller_c_state)
          5'b0_0000: begin
            if (((rd | wr) | sto) & ~(byte_controller_cmd_ack)) begin
              if (sta) begin
                byte_controller_target   <= 1;
                byte_controller_c_state  <= 5'b0_0001;
                byte_controller_core_cmd <= 4'b0001;
              end else begin
                if (rd) begin
                  byte_controller_c_state  <= 5'b0_0010;
                  byte_controller_core_cmd <= 4'b1000;
                end else begin
                  if (wr) begin
                    byte_controller_c_state  <= 5'b0_0100;
                    byte_controller_core_cmd <= 4'b0100;
                  end else begin
                    byte_controller_c_state  <= 5'b1_0000;
                    byte_controller_core_cmd <= 4'b0010;
                  end
                end
              end
              byte_controller_ld <= 1'b1;
            end
          end
          5'b0_0001: begin
            if (byte_controller_bit_controller_cmd_ack) begin
              if (rd) begin
                byte_controller_c_state  <= 5'b0_0010;
                byte_controller_core_cmd <= 4'b1000;
              end else begin
                byte_controller_c_state  <= 5'b0_0100;
                byte_controller_core_cmd <= 4'b0100;
              end
              byte_controller_ld <= 1'b1;
            end
          end
          5'b0_0100: begin
            if (byte_controller_bit_controller_cmd_ack) begin
              if (~(|(byte_controller_dcnt))) begin
                byte_controller_c_state  <= 5'b0_1000;
                byte_controller_core_cmd <= 4'b1000;
              end else begin
                byte_controller_c_state <= 5'b0_0100;
                byte_controller_core_cmd <= 4'b0100;
                byte_controller_shift <= 1'b1;
              end
            end
          end
          5'b0_0010: begin
            if (byte_controller_bit_controller_cmd_ack) begin
              if (~(|(byte_controller_dcnt))) begin
                byte_controller_c_state  <= 5'b0_1000;
                byte_controller_core_cmd <= 4'b0100;
              end else begin
                byte_controller_c_state  <= 5'b0_0010;
                byte_controller_core_cmd <= 4'b1000;
              end
              byte_controller_shift <= 1'b1;
              byte_controller_core_txd <= ack;
            end
          end
          5'b0_1000: begin
            if (byte_controller_bit_controller_cmd_ack) begin
              if (sto) begin
                byte_controller_c_state  <= 5'b1_0000;
                byte_controller_core_cmd <= 4'b0010;
              end else begin
                byte_controller_c_state  <= 5'b0_0000;
                byte_controller_core_cmd <= 4'b0000;
                byte_controller_cmd_ack  <= 1'b1;
              end
              byte_controller_ack_out  <= byte_controller_bit_controller_dout;
              byte_controller_core_txd <= 1'b1;
            end else begin
              byte_controller_core_txd <= ack;
            end
          end
          5'b1_0000: begin
            if (byte_controller_bit_controller_cmd_ack) begin
              byte_controller_c_state  <= 5'b0_0000;
              byte_controller_core_cmd <= 4'b0000;
              byte_controller_cmd_ack  <= 1'b1;
            end
          end
        endcase
      end
    end
  end
endmodule

RTL/iic/iic_tb.v
`timescale 1ns/1ps
module iic_tb();
reg wb_clk_i;
reg rst_i;
reg [2:0] wb_adr_i;
reg [7:0] wb_dat_i;
wire [7:0] wb_dat_o;
reg wb_we_i;
reg wb_stb_i;
reg wb_cyc_i;
wire wb_ack_o;
wire wb_inta_o;
reg scl_pad_i;
wire scl_pad_o;
wire scl_padoen_o;
reg sda_pad_i;
wire sda_pad_o;
wire sda_padoen_o;

// 实例化待测模块
i2c_master_top uut (
    .wb_clk_i(wb_clk_i),
    .rst_i(rst_i),
    .wb_adr_i(wb_adr_i),
    .wb_dat_i(wb_dat_i),
    .wb_dat_o(wb_dat_o),
    .wb_we_i(wb_we_i),
    .wb_stb_i(wb_stb_i),
    .wb_cyc_i(wb_cyc_i),
    .wb_ack_o(wb_ack_o),
    .wb_inta_o(wb_inta_o),
    .scl_pad_i(scl_pad_i),
    .scl_pad_o(scl_pad_o),
    .scl_padoen_o(scl_padoen_o),
    .sda_pad_i(sda_pad_i),
    .sda_pad_o(sda_pad_o),
    .sda_padoen_o(sda_padoen_o)
    );

// 时钟激励
initial begin
    wb_clk_i = 0;
    forever #5 wb_clk_i = ~wb_clk_i;
end

// 复位激励
initial begin
    rst_i = 0;
    #10;
    rst_i = 1;
end

integer i;
initial begin
    wb_adr_i = 0;
    wb_dat_i = 0;
    wb_we_i = 0;
    wb_stb_i = 0;
    wb_cyc_i = 0;
    scl_pad_i = 0;
    sda_pad_i = 0;
    #10;
    for(i = 0; i < 1000; i = i + 1) begin
        $display("********Period %d********", i);
        wb_adr_i = $random & 3'd7;
        wb_dat_i = $random & 8'd255;
        wb_we_i = $random & 1'd1;
        wb_stb_i = $random & 1'd1;
        wb_cyc_i = $random & 1'd1;
        scl_pad_i = $random & 1'd1;
        sda_pad_i = $random & 1'd1;
        if (i == 141) begin wb_dat_i[7:4] = 4'b0100;  end

        if (i >= 754 && i < 850) begin sda_pad_i = 1'b1;  end
        if (i == 776) begin wb_dat_i[7] = 1'b0;  end
        if (i == 777) begin wb_dat_i[7] = 1'b0;  end

        if (i == 817) begin wb_adr_i = 3'b010; wb_dat_i[7] = 1'b1;  end
        if (i == 821) begin wb_adr_i = 3'b100; wb_dat_i[6] = 1'b1; end
        if (i == 831) begin wb_dat_i[7] = 1'b0; wb_adr_i = 3'b010;  end

        if (i >= 855 && i < 925) begin sda_pad_i = 1'b1;  end

        #10;
    end
    $finish;
end
initial begin
    $dumpfile("wave.vcd");
    $dumpvars(0, iic_tb);
end

endmodule

RTL/iic/wave.vcd
$date
	Tue Apr 22 10:14:49 2025
$end
$version
	Icarus Verilog
$end
$timescale
	1ps
$end
$scope module iic_tb $end
$var wire 1 ! scl_pad_o $end
$var wire 1 " sda_pad_o $end
$var wire 1 # wb_inta_o $end
$var wire 8 $ wb_dat_o [7:0] $end
$var wire 1 % wb_ack_o $end
$var wire 1 & sda_padoen_o $end
$var wire 1 ' scl_padoen_o $end
$var reg 1 ( rst_i $end
$var reg 1 ) scl_pad_i $end
$var reg 1 * sda_pad_i $end
$var reg 3 + wb_adr_i [2:0] $end
$var reg 1 , wb_clk_i $end
$var reg 1 - wb_cyc_i $end
$var reg 8 . wb_dat_i [7:0] $end
$var reg 1 / wb_stb_i $end
$var reg 1 0 wb_we_i $end
$var integer 32 1 i [31:0] $end
$scope module uut $end
$var wire 8 2 byte_controller_dout [7:0] $end
$var wire 1 3 byte_controller_i2c_al $end
$var wire 1 4 byte_controller_i2c_busy $end
$var wire 1 5 i2c_busy $end
$var wire 1 ( rst_i $end
$var wire 1 ) scl_pad_i $end
$var wire 1 ! scl_pad_o $end
$var wire 1 ' scl_padoen_o $end
$var wire 1 * sda_pad_i $end
$var wire 1 " sda_pad_o $end
$var wire 1 & sda_padoen_o $end
$var wire 3 6 wb_adr_i [2:0] $end
$var wire 1 , wb_clk_i $end
$var wire 1 - wb_cyc_i $end
$var wire 8 7 wb_dat_i [7:0] $end
$var wire 1 / wb_stb_i $end
$var wire 1 8 wb_wacc $end
$var wire 1 0 wb_we_i $end
$var wire 1 9 wr $end
$var wire 1 : sto $end
$var wire 1 ; sta $end
$var wire 1 < rd $end
$var wire 1 = iack $end
$var wire 1 > ack $end
$var reg 1 ? al $end
$var reg 1 @ byte_controller_ack_out $end
$var reg 1 A byte_controller_bit_controller_al $end
$var reg 1 B byte_controller_bit_controller_busy $end
$var reg 17 C byte_controller_bit_controller_c_state [16:0] $end
$var reg 1 D byte_controller_bit_controller_clk_en $end
$var reg 1 E byte_controller_bit_controller_cmd_ack $end
$var reg 1 F byte_controller_bit_controller_cmd_stop $end
$var reg 16 G byte_controller_bit_controller_cnt [15:0] $end
$var reg 1 H byte_controller_bit_controller_dSCL $end
$var reg 1 I byte_controller_bit_controller_dSDA $end
$var reg 1 J byte_controller_bit_controller_dout $end
$var reg 1 K byte_controller_bit_controller_dscl_oen $end
$var reg 1 L byte_controller_bit_controller_sSCL $end
$var reg 1 M byte_controller_bit_controller_sSDB $end
$var reg 1 N byte_controller_bit_controller_scl_oen $end
$var reg 1 O byte_controller_bit_controller_sda_chk $end
$var reg 1 P byte_controller_bit_controller_sda_oen $end
$var reg 1 Q byte_controller_bit_controller_sta_condition $end
$var reg 1 R byte_controller_bit_controller_sto_condition $end
$var reg 5 S byte_controller_c_state [4:0] $end
$var reg 1 T byte_controller_cmd_ack $end
$var reg 4 U byte_controller_core_cmd [3:0] $end
$var reg 1 V byte_controller_core_txd $end
$var reg 3 W byte_controller_dcnt [2:0] $end
$var reg 1 X byte_controller_ld $end
$var reg 1 Y byte_controller_shift $end
$var reg 8 Z byte_controller_sr [7:0] $end
$var reg 1 [ byte_controller_target $end
$var reg 8 \ cr [7:0] $end
$var reg 8 ] ctr [7:0] $end
$var reg 1 ^ irq_flag $end
$var reg 16 _ prer [15:0] $end
$var reg 1 ` rxack $end
$var reg 1 a tip $end
$var reg 8 b txr [7:0] $end
$var reg 1 % wb_ack_o $end
$var reg 8 c wb_dat_o [7:0] $end
$var reg 1 # wb_inta_o $end
$upscope $end
$upscope $end
$enddefinitions $end
$comment Show the parameter values. $end
$dumpall
$end
#0
$dumpvars
bx c
b0 b
0a
0`
b1111111111111111 _
0^
b0 ]
b0 \
x[
b0 Z
0Y
0X
b0 W
0V
b0 U
0T
b0 S
0R
0Q
1P
0O
1N
1M
1L
0K
0J
1I
1H
b0 G
0F
0E
1D
b0 C
0B
0A
0@
0?
0>
0=
0<
0;
0:
09
08
b0 7
b0 6
05
04
03
b0 2
bx 1
00
0/
b0 .
0-
0,
b0 +
0*
0)
0(
1'
1&
x%
bx $
0#
0"
0!
$end
#5000
0%
b11111111 $
b11111111 c
1,
#10000
18
0,
1*
1)
1-
1/
10
b10000001 .
b10000001 7
b100 +
b100 6
b0 1
1(
#15000
1K
b1111111111111111 G
b0 $
b0 c
1%
1,
#20000
08
0,
0*
0/
b1 .
b1 7
b10 +
b10 6
b1 1
#25000
0M
0%
1,
#30000
0,
b11000110 .
b11000110 7
b1 +
b1 6
b10 1
#35000
0I
1Q
b11111111 $
b11111111 c
1,
#40000
0,
1*
0)
00
b11110010 .
b11110010 7
b111 +
b111 6
b11 1
#45000
14
15
1B
0Q
1M
0L
b0 $
b0 c
1,
#50000
0,
0*
0-
10
b1100101 .
b1100101 7
b101 +
b101 6
b100 1
#55000
0D
1I
0H
0M
1,
#60000
18
0,
1*
1)
1-
1/
b10010110 .
b10010110 7
b101 1
#65000
0I
1M
1L
1%
1,
#70000
0,
0*
0)
b10101110 .
b10101110 7
b10 +
b10 6
b110 1
#75000
b10101110 ]
1D
1I
1H
0M
0L
1R
1J
0%
1,
#80000
08
0,
1*
0-
00
b11110010 .
b11110010 7
b100 +
b100 6
b111 1
#85000
04
05
0B
0R
0I
0H
1M
0D
b1111111111111110 G
b1000000 $
b1000000 c
1,
#90000
0,
0/
b10110110 .
b10110110 7
b11 +
b11 6
b1000 1
#95000
b1111111111111101 G
1I
b0 $
b0 c
1,
#100000
0,
1/
10
b10000101 .
b10000101 7
b1 +
b1 6
b1001 1
#105000
b1111111111111100 G
b11111111 $
b11111111 c
1,
#110000
0,
0*
1)
1-
0/
00
b11011001 .
b11011001 7
b1010 1
#115000
b1111111111111011 G
0M
1L
1,
#120000
0,
1/
b10011111 .
b10011111 7
b111 +
b111 6
b1011 1
#125000
0J
1Q
0I
1H
b1111111111111010 G
1%
b0 $
b0 c
1,
#130000
0,
1*
0)
0-
0/
b1010001 .
b1010001 7
b1100 1
#135000
b1111111111111001 G
1M
0L
0Q
14
15
1B
0%
1,
#140000
0,
1)
1-
1/
b10010 .
b10010 7
b101 +
b101 6
b1101 1
#145000
1I
0H
1L
b1111111111111000 G
1%
1,
#150000
18
0,
0*
0)
10
b1111000 .
b1111000 7
b1110 1
#155000
b1111111111110111 G
1H
0M
0L
1J
0%
1,
#160000
08
0,
1*
1)
0-
0/
00
b10001110 .
b10001110 7
b110 +
b110 6
b1111 1
#165000
0I
0H
1M
1L
b1111111111110110 G
1,
#170000
0,
0*
1-
10
b10110011 .
b10110011 7
b111 +
b111 6
b10000 1
#175000
b1111111111110101 G
1I
1H
0M
1R
1,
#180000
0,
1*
b101001 .
b101001 7
b10 +
b10 6
b10001 1
#185000
04
05
0B
0R
1Q
0I
1M
b1111111111110100 G
b10101110 $
b10101110 c
1,
#190000
0,
0*
0)
00
b1000100 .
b1000100 7
b1 +
b1 6
b10010 1
#195000
b1111111111110011 G
1I
0M
0L
1R
0Q
14
15
1B
b11111111 $
b11111111 c
1,
#200000
0,
1)
0-
10
b11111101 .
b11111101 7
b10 +
b10 6
b10011 1
#205000
04
05
0B
0R
0I
0H
1L
b1111111111110010 G
b10101110 $
b10101110 c
1,
#210000
0,
b111000 .
b111000 7
b110 +
b110 6
b10100 1
#215000
b1111111111110001 G
1H
0J
b0 $
b0 c
1,
#220000
18
0,
0)
1-
1/
b11011011 .
b11011011 7
b1 +
b1 6
b10101 1
#225000
0L
b1111111111110000 G
b1101101111111111 _
1%
b11111111 $
b11111111 c
1,
#230000
08
0,
1)
0/
00
b10010101 .
b10010101 7
b110 +
b110 6
b10110 1
#235000
b1111111111101111 G
0H
1L
b0 $
b0 c
0%
1,
