RTL/core/clint/clint.v
module clint (

    input wire clk,
    input wire rst,

    // from core
    input wire [7:0] int_flag_i,  // 中断输入信号

    // from id
    input wire [31:0] inst_i,      // 指令内容
    input wire [31:0] inst_addr_i, // 指令地址

    // from ex
    input wire jump_flag_i,
    input wire [31:0] jump_addr_i,
    input wire div_started_i,

    // from ctrl
    input wire [2:0] hold_flag_i,  // 流水线暂停标志

    // from csr_reg
    input wire [31:0] data_i,      // CSR寄存器输入数据
    input wire [31:0] csr_mtvec,   // mtvec寄存器
    input wire [31:0] csr_mepc,    // mepc寄存器
    input wire [31:0] csr_mstatus, // mstatus寄存器

    input wire global_int_en_i,  // 全局中断使能标志

    // to ctrl
    output wire hold_flag_o,  // 流水线暂停标志

    // to csr_reg
    output reg        we_o,     // 写CSR寄存器标志
    output reg [31:0] waddr_o,  // 写CSR寄存器地址
    output reg [31:0] raddr_o,  // 读CSR寄存器地址
    output reg [31:0] data_o,   // 写CSR寄存器数据

    // to ex
    output reg [31:0] int_addr_o,   // 中断入口地址
    output reg        int_assert_o  // 中断标志

);

  reg [3:0] int_state;
  reg [4:0] csr_state;
  reg [31:0] inst_addr;
  reg [31:0] cause;


  assign hold_flag_o = ((int_state != 4'b0001) | (csr_state != 5'b00001)) ? 1'b1 : 1'b0;


  // 中断仲裁逻辑
  always @(*) begin
    if (rst == 1'b0) begin
      int_state = 4'b0001;
    end else begin
      if (inst_i == 32'h73 || inst_i == 32'h00100073) begin
        // 如果执行阶段的指令为除法指令，则先不处理同步中断，等除法指令执行完再处理
        if (div_started_i == 1'b0) begin
          int_state = 4'b0010;
        end else begin
          int_state = 4'b0001;
        end
      end else if (int_flag_i != 8'h0 && global_int_en_i == 1'b1) begin
        int_state = 4'b0100;
      end else if (inst_i == 32'h30200073) begin
        int_state = 4'b1000;
      end else begin
        int_state = 4'b0001;
      end
    end
  end

  always @(posedge clk) begin
    if (rst == 1'b0) begin
      cause <= 32'h0;
    end else if(csr_state == 5'b00001 && int_state == 4'b0010)  begin
      case (inst_i)
        32'h73: begin
          cause <= 32'd11;
        end
        32'h00100073: begin
          cause <= 32'd3;
        end
        default: begin
          cause <= 32'd10;
        end
      endcase
    end else if (int_state == 4'b0100)
      cause <= 32'h80000004;
  end

  // 写CSR寄存器状态切换
  always @(posedge clk) begin
    if (rst == 1'b0) begin
      csr_state <= 5'b00001;
      inst_addr <= 32'h0;
    end else begin
      case (csr_state)
        5'b00001: begin
          // 同步中断
          if (int_state == 4'b0010) begin
            csr_state <= 5'b00100;
            // 在中断处理函数里会将中断返回地址加4
            if (jump_flag_i == 1'b1) begin
              inst_addr <= jump_addr_i - 4'h4;
            end else begin
              inst_addr <= inst_addr_i;
            end
            // 异步中断
          end else if (int_state == 4'b0100) begin
            // 定时器中断
            csr_state <= 5'b00100;
            if (jump_flag_i == 1'b1) begin
              inst_addr <= jump_addr_i;
              // 异步中断可以中断除法指令的执行，中断处理完再重新执行除法指令
            end else if (div_started_i == 1'b1) begin
              inst_addr <= inst_addr_i - 4'h4;
            end else begin
              inst_addr <= inst_addr_i;
            end
            // 中断返回
          end else if (int_state == 4'b1000) begin
            csr_state <= 5'b01000;
          end
        end
        5'b00100: begin
          csr_state <= 5'b00010;
        end
        5'b00010: begin
          csr_state <= 5'b10000;
        end
        5'b10000: begin
          csr_state <= 5'b00001;
        end
        5'b01000: begin
          csr_state <= 5'b00001;
        end
        default: csr_state <= 5'b00001;
      endcase
    end
  end

  // 发出中断信号前，先写几个CSR寄存器
  always @(posedge clk) begin
    if (rst == 1'b0) begin
      we_o <= 1'b0;
      waddr_o <= 32'h0;
      data_o <= 32'h0;
    end else begin
      case (csr_state)
        // 将mepc寄存器的值设为当前指令地址
        5'b00100: begin
          we_o <= 1'b1;
          waddr_o <= {20'h0, 12'h341};
          data_o <= inst_addr;
        end
        // 写中断产生的原因
        5'b10000: begin
          we_o <= 1'b1;
          waddr_o <= {20'h0, 12'h342};
          data_o <= cause;
        end
        // 关闭全局中断
        5'b00010: begin
          we_o <= 1'b1;
          waddr_o <= {20'h0, 12'h300};
          data_o <= {csr_mstatus[31:4], 1'b0, csr_mstatus[2:0]};
        end
        // 中断返回
        5'b01000: begin
          we_o <= 1'b1;
          waddr_o <= {20'h0, 12'h300};
          data_o <= {csr_mstatus[31:4], csr_mstatus[7], csr_mstatus[2:0]};
        end
        default: begin
          we_o <= 1'b0;
          waddr_o <= 32'h0;
          data_o <= 32'h0;
        end
      endcase
    end
  end

  // 发出中断信号给ex模块
  always @(posedge clk) begin
    if (rst == 1'b0) begin
      int_assert_o <= 1'b0;
      int_addr_o   <= 32'h0;
    end else begin
      case (csr_state)
        // 发出中断进入信号.写完mcause寄存器才能发
        5'b10000: begin
          int_assert_o <= 1'b1;
          int_addr_o   <= csr_mtvec;
        end
        // 发出中断返回信号
        5'b01000: begin
          int_assert_o <= 1'b1;
          int_addr_o   <= csr_mepc;
        end
        default: begin
          int_assert_o <= 1'b0;
          int_addr_o   <= 32'h0;
        end
      endcase
    end
  end

endmodule

RTL/core/clint/clint_tb.v
//~ `New testbench
`timescale  1ns / 1ps

module tb_clint;

// clint Parameters
parameter PERIOD  = 10;


// clint Inputs
reg   clk                                  = 0 ;
reg   rst                                  = 0 ;
reg   [7:0]  int_flag_i                    = 0 ;
reg   [31:0]  inst_i                       = 0 ;
reg   [31:0]  inst_addr_i                  = 0 ;
reg   jump_flag_i                          = 0 ;
reg   [31:0]  jump_addr_i                  = 0 ;
reg   div_started_i                        = 0 ;
reg   [2:0]  hold_flag_i                   = 0 ;
reg   [31:0]  data_i                       = 0 ;
reg   [31:0]  csr_mtvec                    = 0 ;
reg   [31:0]  csr_mepc                     = 0 ;
reg   [31:0]  csr_mstatus                  = 0 ;
reg   global_int_en_i                      = 0 ;

// clint Outputs
wire  hold_flag_o                          ;
wire  we_o                                 ;
wire  [31:0]  waddr_o                      ;
wire  [31:0]  raddr_o                      ;
wire  [31:0]  data_o                       ;
wire  [31:0]  int_addr_o                   ;
wire  int_assert_o                         ;


initial
begin
    forever #(PERIOD/2)  clk=~clk;
end

initial
begin
    #(PERIOD*2) rst  =  1;
end

clint  u_clint (
    .clk                     ( clk                     ),
    .rst                     ( rst                     ),
    .int_flag_i              ( int_flag_i       [7:0]  ),
    .inst_i                  ( inst_i           [31:0] ),
    .inst_addr_i             ( inst_addr_i      [31:0] ),
    .jump_flag_i             ( jump_flag_i             ),
    .jump_addr_i             ( jump_addr_i      [31:0] ),
    .div_started_i           ( div_started_i           ),
    .hold_flag_i             ( hold_flag_i      [2:0]  ),
    .data_i                  ( data_i           [31:0] ),
    .csr_mtvec               ( csr_mtvec        [31:0] ),
    .csr_mepc                ( csr_mepc         [31:0] ),
    .csr_mstatus             ( csr_mstatus      [31:0] ),
    .global_int_en_i         ( global_int_en_i         ),

    .hold_flag_o             ( hold_flag_o             ),
    .we_o                    ( we_o                    ),
    .waddr_o                 ( waddr_o          [31:0] ),
    .raddr_o                 ( raddr_o          [31:0] ),
    .data_o                  ( data_o           [31:0] ),
    .int_addr_o              ( int_addr_o       [31:0] ),
    .int_assert_o            ( int_assert_o            )
);

integer i;

initial begin
    rst = 0;
    int_flag_i = 0;
    inst_i = 0;
    inst_addr_i = 0;
    jump_flag_i = 0;
    jump_addr_i = 0;
    div_started_i = 0;
    hold_flag_i = 0;
    data_i = 0;
    csr_mtvec = 0;
    csr_mepc = 0;
    csr_mstatus = 0;
    global_int_en_i = 0;
    #10;

    for(i = 0; i < 20; i = i + 1) begin
        #8;
        $display("Period %d", i);
        int_flag_i = $random & 8'd255;
        inst_i = $random;
        inst_addr_i = $random;
        jump_flag_i = $random & 1'd1;
        jump_addr_i = $random;
        div_started_i = $random & 1'd1;
        hold_flag_i = $random & 3'd7;
        data_i = $random;
        csr_mtvec = $random;
        csr_mepc = $random;
        csr_mstatus = $random;
        global_int_en_i = $random & 1'd1;
        #2;
    end
    // #8;
    // $display("Period 20");
    // int_flag_i = 0;
    // inst_i = 32'h30200073;
    // inst_addr_i = $random;
    // jump_flag_i = $random & 1'd1;
    // jump_addr_i = $random;
    // div_started_i = $random & 1'd1;
    // hold_flag_i = $random & 3'd7;
    // data_i = $random;
    // csr_mtvec = $random;
    // csr_mepc = $random;
    // csr_mstatus = $random;
    // global_int_en_i = $random & 1'd1;
    // #2;

    // #8;
    // $display("Period 21");
    // int_flag_i = 0;
    // inst_i = 32'h30200073;
    // inst_addr_i = $random;
    // jump_flag_i = $random & 1'd1;
    // jump_addr_i = $random;
    // div_started_i = $random & 1'd1;
    // hold_flag_i = $random & 3'd7;
    // data_i = $random;
    // csr_mtvec = $random;
    // csr_mepc = $random;
    // csr_mstatus = $random;
    // global_int_en_i = $random & 1'd1;
    // #2;

    #5;
    $finish;
end

initial
begin
    $monitor("hold_flag_o=%d, we_o=%d, waddr_o=%d, raddr_o=%d, data_o=%d, int_addr_o=%d, int_assert_o=%d, int_state=%d, csr_state=%d, inst_addr=%d, cause=%d", hold_flag_o, we_o, waddr_o, raddr_o, data_o, int_addr_o, int_assert_o, u_clint.int_state, u_clint.csr_state, u_clint.inst_addr, u_clint.cause);
end

initial
begin            
    $dumpfile("wave.vcd");        //生成的vcd文件名称
    $dumpvars(0, tb_clint);    //tb模块名称
end 


endmodule

wave.vcd
$date
	Tue Feb 25 17:04:15 2025
$end
$version
	Icarus Verilog
$end
$timescale
	1ps
$end
$scope module tb_clint $end
$var wire 1 ! we_o $end
$var wire 32 " waddr_o [31:0] $end
$var wire 32 # raddr_o [31:0] $end
$var wire 1 $ int_assert_o $end
$var wire 32 % int_addr_o [31:0] $end
$var wire 1 & hold_flag_o $end
$var wire 32 ' data_o [31:0] $end
$var parameter 32 ( PERIOD $end
$var reg 1 ) clk $end
$var reg 32 * csr_mepc [31:0] $end
$var reg 32 + csr_mstatus [31:0] $end
$var reg 32 , csr_mtvec [31:0] $end
$var reg 32 - data_i [31:0] $end
$var reg 1 . div_started_i $end
$var reg 1 / global_int_en_i $end
$var reg 3 0 hold_flag_i [2:0] $end
$var reg 32 1 inst_addr_i [31:0] $end
$var reg 32 2 inst_i [31:0] $end
$var reg 8 3 int_flag_i [7:0] $end
$var reg 32 4 jump_addr_i [31:0] $end
$var reg 1 5 jump_flag_i $end
$var reg 1 6 rst $end
$var integer 32 7 i [31:0] $end
$scope module u_clint $end
$var wire 1 ) clk $end
$var wire 32 8 csr_mepc [31:0] $end
$var wire 32 9 csr_mstatus [31:0] $end
$var wire 32 : csr_mtvec [31:0] $end
$var wire 32 ; data_i [31:0] $end
$var wire 1 . div_started_i $end
$var wire 1 / global_int_en_i $end
$var wire 3 < hold_flag_i [2:0] $end
$var wire 32 = inst_addr_i [31:0] $end
$var wire 32 > inst_i [31:0] $end
$var wire 8 ? int_flag_i [7:0] $end
$var wire 32 @ jump_addr_i [31:0] $end
$var wire 1 5 jump_flag_i $end
$var wire 1 6 rst $end
$var wire 1 & hold_flag_o $end
$var reg 32 A cause [31:0] $end
$var reg 5 B csr_state [4:0] $end
$var reg 32 C data_o [31:0] $end
$var reg 32 D inst_addr [31:0] $end
$var reg 32 E int_addr_o [31:0] $end
$var reg 1 $ int_assert_o $end
$var reg 4 F int_state [3:0] $end
$var reg 32 G raddr_o [31:0] $end
$var reg 32 H waddr_o [31:0] $end
$var reg 1 ! we_o $end
$upscope $end
$upscope $end
$enddefinitions $end
$comment Show the parameter values. $end
$dumpall
b1010 (
$end
#0
$dumpvars
bx H
bx G
b1 F
bx E
bx D
bx C
bx B
bx A
b0 @
b0 ?
b0 >
b0 =
b0 <
b0 ;
b0 :
b0 9
b0 8
bx 7
06
05
b0 4
b0 3
b0 2
b0 1
b0 0
0/
0.
b0 -
b0 ,
b0 +
b0 *
0)
bx '
x&
bx %
x$
bx #
bx "
x!
$end
#5000
0&
b0 A
b0 D
b1 B
b0 '
b0 C
b0 "
b0 H
0!
b0 %
b0 E
0$
1)
#10000
0)
b0 7
#15000
1)
#18000
1/
b111011001000111111000101110110 +
b111011001000111111000101110110 9
b110110101111100110100001101 *
b110110101111100110100001101 8
b111100111110001100000001 ,
b111100111110001100000001 :
b10001001001101110101001000010010 -
b10001001001101110101001000010010 ;
b101 0
b101 <
1.
b110101110010111101100001101 4
b110101110010111101100001101 @
15
b10000100100001001101011000001001 1
b10000100100001001101011000001001 =
b11000000100010010101111010000001 2
b11000000100010010101111010000001 >
b100100 3
b100100 ?
#20000
1&
b100 F
b1 7
0)
16
#25000
b10000000000000000000000000000100 A
b110101110010111101100001101 D
b100 B
1)
#28000
b1 F
0/
b1111001001100000110100111110010 +
b1111001001100000110100111110010 9
b1000111111011001101101110001111 *
b1000111111011001101101110001111 8
b10001001001100101101011000010010 ,
b10001001001100101101011000010010 :
b10111011110100100111001001110111 -
b10111011110100100111001001110111 ;
0.
b11100010111101111000010011000101 4
b11100010111101111000010011000101 @
05
b1111100111111011110100111111001 1
b1111100111111011110100111111001 =
b1000110001011011111011110001100 2
b1000110001011011111011110001100 >
b11101101 3
b11101101 ?
#30000
b10 7
0)
#35000
b110101110010111101100001101 '
b110101110010111101100001101 C
b1101000001 "
b1101000001 H
1!
b10 B
1)
#38000
b100 F
1/
b1010101011110000100010110101010 +
b1010101011110000100010110101010 9
b10000011001000010000100100000 *
b10000011001000010000100100000 8
b11000000001110110010001010000000 ,
b11000000001110110010001010000000 :
b101011100111000011100001010 -
b101011100111000011100001010 ;
b11 0
b11 <
1.
b10010110101010110101100000101101 4
b10010110101010110101100000101101 @
15
b101110010110000100100101011100 1
b101110010110000100100101011100 =
b11100010110010100100111011000101 2
b11100010110010100100111011000101 >
b11101000 3
b11101000 ?
#40000
b11 7
0)
#45000
b10000 B
b1010101011110000100010110100010 '
b1010101011110000100010110100010 C
b1100000000 "
b1100000000 H
1)
#48000
b1 F
0/
b10001100001000100100100100011 +
b10001100001000100100100100011 9
b11100111110001010111001011001111 *
b11100111110001010111001011001111 8
b1110111111111110100100011101 ,
b1110111111111110100100011101 :
b11010111010101100011111010101110 -
b11010111010101100011111010101110 ;
b10 0
b10 <
b110101100111111101110101101011 4
b110101100111111101110101101011 @
b10000110101111000011100000001101 1
b10000110101111000011100000001101 =
b10001001100000111011100000010011 2
b10001001100000111011100000010011 >
b10010110 3
b10010110 ?
#50000
b100 7
0)
#55000
0&
b1110111111111110100100011101 %
b1110111111111110100100011101 E
1$
b10000000000000000000000000000100 '
b10000000000000000000000000000100 C
b1101000010 "
b1101000010 H
b1 B
1)
#58000
b1100011010010111111100111000110 +
b1100011010010111111100111000110 9
b1011011000000100110010110110110 *
b1011011000000100110010110110110 8
b1110101110001010000110111101011 ,
b1110101110001010000110111101011 :
b11000100100010100001001010001001 -
b11000100100010100001001010001001 ;
b0 0
b0 <
0.
b100000110001001011001101000001 4
b100000110001001011001101000001 @
05
b1111001011010001011110111110010 1
b1111001011010001011110111110010 =
b10011110001100010100110000111100 2
b10011110001100010100110000111100 >
b11001010 3
b11001010 ?
#60000
b101 7
0)
#65000
b0 '
b0 C
b0 "
b0 H
0!
b0 %
b0 E
0$
1)
#68000
1&
b100 F
1/
b1111000110110011001101111110001 +
b1111000110110011001101111110001 9
b1010101010100100101100010101 *
b1010101010100100101100010101 8
b10111111001000110011001001111110 ,
b10111111001000110011001001111110 :
b11101000001100011001100111010 -
b11101000001100011001100111010 ;
b11 0
b11 <
1.
b1000010111100100100000110000101 4
b1000010111100100100000110000101 @
15
b10000101110101111001101000001011 1
b10000101110101111001101000001011 =
b10101000011111101110100101010 2
b10101000011111101110100101010 >
b10111100 3
b10111100 ?
#70000
b110 7
0)
#75000
b1000010111100100100000110000101 D
b100 B
1)
#78000
b1 F
0/
b10100100101011100011001001001001 +
b10100100101011100011001001001001 9
b1000100110111100011011110001001 *
b1000100110111100011011110001001 8
b10101101110010111100000001011011 ,
b10101101110010111100000001011011 :
b10101110011111011001010001011100 -
b10101110011111011001010001011100 ;
b111 0
b111 <
b1111100011011011010100111111000 4
b1111100011011011010100111111000 @
b1001111101000010101010110011111 1
b1001111101000010101010110011111 =
b100110001101011111101101001100 2
b100110001101011111101101001100 >
b1100010 3
b1100010 ?
#80000
b111 7
0)
#85000
b10 B
b1000010111100100100000110000101 '
b1000010111100100100000110000101 C
b1101000001 "
b1101000001 H
1!
1)
#88000
b100 F
1/
b110110111001011000000101101101 +
b110110111001011000000101101101 9
b10111111000001010000000001111110 *
b10111111000001010000000001111110 8
b1001000011001101101100010010 ,
b1001000011001101101100010010 :
b11110111100101110110100111101 -
b11110111100101110110100111101 ;
0.
b11100001001011001100111011000010 4
b11100001001011001100111011000010 @
05
b1001011001000010010111110010110 1
b1001011001000010010111110010110 =
b10101000110001111111110001010001 2
b10101000110001111111110001010001 >
b11010111 3
b11010111 ?
#90000
b1000 7
0)
#95000
b110110111001011000000101100101 '
b110110111001011000000101100101 C
b1100000000 "
b1100000000 H
b10000 B
1)
#98000
b1 F
0/
b11000111000110100000110010001110 +
b11000111000110100000110010001110 9
b11000011001111110011100010000110 *
b11000011001111110011100010000110 8
b101100000101010110001101011000 ,
b101100000101010110001101011000 :
b10101000011001010111100101010 -
b10101000011001010111100101010 ;
1.
b101101110110100101100101011011 4
b101101110110100101100101011011 @
b1000010110110010010111110000101 1
b1000010110110010010111110000101 =
b11101001111010111111011011010011 2
b11101001111010111111011011010011 >
b11111 3
b11111 ?
#100000
b1001 7
0)
#105000
0&
b1 B
b10000000000000000000000000000100 '
b10000000000000000000000000000100 C
b1101000010 "
b1101000010 H
b101100000101010110001101011000 %
b101100000101010110001101011000 E
1$
1)
#108000
b11110011000010010001101011100110 +
b11110011000010010001101011100110 9
b11100101100110110011011011001011 *
b11100101100110110011011011001011 8
b1111011111110001111110111110111 ,
b1111011111110001111110111110111 :
b100010001010010000110101000100 -
b100010001010010000110101000100 ;
b10010111100110011010100000101111 4
b10010111100110011010100000101111 @
15
b111001100101100001011101110011 1
b111001100101100001011101110011 =
b10010011011111011011110000100110 2
b10010011011111011011110000100110 >
b11111010 3
b11111010 ?
#110000
b1010 7
0)
#115000
b0 %
b0 E
0$
b0 '
b0 C
b0 "
b0 H
0!
1)
#118000
b1010101111101101010110110101011 +
b1010101111101101010110110101011 9
b10101000010010000101100101010 *
b10101000010010000101100101010 8
b11101000011101000000110011010000 ,
b11101000011101000000110011010000 :
b100010001100011111111101000100 -
b100010001100011111111101000100 ;
b1 0
b1 <
b11011010100010101110001010110101 4
b11011010100010101110001010110101 @
b11101101010100110110110011011010 1
b11101101010100110110110011011010 =
b11110110100000101110001011101101 2
b11110110100000101110001011101101 >
b101001 3
b101001 ?
#120000
b1011 7
0)
#125000
1)
#128000
b111100110100011000011101111001 +
b111100110100011000011101111001 9
b10011100000011101000101000111000 *
b10011100000011101000101000111000 8
b1011011011011111011100110110110 ,
b1011011011011111011100110110110 :
b10000101001100010011010000001010 -
b10000101001100010011010000001010 ;
b111 0
b111 <
0.
b101011000011101110110101010110 4
b101011000011101110110101010110 @
b11111110110111110111001011111101 1
b11111110110111110111001011111101 =
b11001101010111101011110010011010 2
b11001101010111101011110010011010 >
b11011100 3
b11011100 ?
#130000
b1100 7
0)
#135000
1)
#138000
1&
b100 F
1/
b1011011000101110010110110110110 +
b1011011000101110010110110110110 9
b1100101001110110100100111001010 *
b1100101001110110100100111001010 8
b10111011010001011110001001110110 ,
b10111011010001011110001001110110 :
b10110110101001000010011001101101 -
b10110110101001000010011001101101 ;
b1 0
b1 <
1.
b1101101110010110110100111011011 4
b1101101110010110110100111011011 @
b10000010001111110010110000000100 1
b10000010001111110010110000000100 =
b1001001110001100101110110010011 2
b1001001110001100101110110010011 >
b10010100 3
b10010100 ?
#140000
b1101 7
0)
#145000
b1101101110010110110100111011011 D
b100 B
1)
#148000
b1 F
0/
b10000100011101111110010000001000 +
b10000100011101111110010000001000 9
b10010111010111001001110000101110 *
b10010111010111001001110000101110 8
b11100011110001010011000011000111 ,
b11100011110001010011000011000111 :
b10010110100100000000010000101101 -
b10010110100100000000010000101101 ;
b0 0
b0 <
0.
b11011010011011101011101010110100 4
b11011010011011101011101010110100 @
b1111011110100100110000111110111 1
b1111011110100100110000111110111 =
b10011101001001101100000100 2
b10011101001001101100000100 >
b1000110 3
b1000110 ?
#150000
b1110 7
0)
#155000
b1101101110010110110100111011011 '
b1101101110010110110100111011011 C
b1101000001 "
b1101000001 H
1!
b10 B
1)
#158000
b101111001110101011001101011110 +
b101111001110101011001101011110 9
b1011101011100011001100110111010 *
b1011101011100011001100110111010 8
b10111001111101010000010001110011 ,
b10111001111101010000010001110011 :
b10111000010101011100010001110000 -
b10111000010101011100010001110000 ;
b110 0
b110 <
1.
b11101101001101000000100011011010 4
b11101101001101000000100011011010 @
05
b10001110001101111001000000011100 1
b10001110001101111001000000011100 =
b10100100111100000011100101001 2
b10100100111100000011100101001 >
b11111101 3
b11111101 ?
#160000
b1111 7
0)
#165000
b10000 B
b101111001110101011001101010110 '
b101111001110101011001101010110 C
b1100000000 "
b1100000000 H
1)
#168000
b1000011011000010101011110000110 +
b1000011011000010101011110000110 9
b1101110010111110000111111011100 *
b1101110010111110000111111011100 8
b111110100110011000001101111101 ,
b111110100110011000001101111101 :
b11011011010001100001101010110110 -
b11011011010001100001101010110110 ;
0.
b1001011001001110011011110010110 4
b1001011001001110011011110010110 @
15
b11011100111100000000000010111001 1
b11011100111100000000000010111001 =
b10001101001001001111011000011010 2
b10001101001001001111011000011010 >
b11010101 3
b11010101 ?
#170000
b10000 7
0)
#175000
0&
b111110100110011000001101111101 %
b111110100110011000001101111101 E
1$
b10000000000000000000000000000100 '
b10000000000000000000000000000100 C
b1101000010 "
b1101000010 H
b1 B
1)
#178000
1&
b100 F
1/
b1111010100011000101100111110101 +
b1111010100011000101100111110101 9
b10101000011000111001011001010000 *
b10101000011000111001011001010000 8
b1000011011101111001000110000110 ,
b1000011011101111001000110000110 :
b11010000111101010111100010100001 -
b11010000111101010111100010100001 ;
b111 0
b111 <
1.
b11111101001010001110010011111010 4
b11111101001010001110010011111010 @
b11100111110000111011011011001111 1
b11100111110000111011011011001111 =
b11101101100011011000000011011011 2
b11101101100011011000000011011011 >
b1111110 3
b1111110 ?
#180000
b10001 7
0)
#185000
b11111101001010001110010011111010 D
b100 B
b0 '
b0 C
b0 "
b0 H
0!
b0 %
b0 E
0$
1)
#188000
b1010100100111101111110110101001 +
b1010100100111101111110110101001 9
b11010100010010111000000010101000 *
b11010100010010111000000010101000 8
b100111010110001101000101001110 ,
b100111010110001101000101001110 :
b11000101010100000001011010001010 -
b11000101010100000001011010001010 ;
b100 0
b100 <
b100101101100100111101101001011 4
b100101101100100111101101001011 @
05
b11100010111001010111010011000101 1
b11100010111001010111010011000101 =
b1100000101100010111010111000001 2
b1100000101100010111010111000001 >
b101001 3
b101001 ?
#190000
b10010 7
0)
#195000
b11111101001010001110010011111010 '
b11111101001010001110010011111010 C
b1101000001 "
b1101000001 H
1!
b10 B
1)
#198000
b1100101001000110100010111001010 +
b1100101001000110100010111001010 9
b1100100011001001110001111001000 *
b1100100011001001110001111001000 8
b10111100110011111010100001111001 ,
b10111100110011111010100001111001 :
b10011100011011011110011000111000 -
b10011100011011011110011000111000 ;
b110 0
b110 <
b10101010110100001110100101010 4
b10101010110100001110100101010 @
b11001111110101101100000010011111 1
b11001111110101101100000010011111 =
b11110011001101000110011011100110 2
b11110011001101000110011011100110 >
b1110 3
b1110 ?
#200000
b10011 7
0)
#205000
b10000 B
b1100101001000110100010111000010 '
b1100101001000110100010111000010 C
b1100000000 "
b1100000000 H
1)
#208000
b1 F
0/
b1111101011011011111010111111010 +
b1111101011011011111010111111010 9
b11000011001100111001000010000110 *
b11000011001100111001000010000110 8
b111111101110110011101101111111 ,
b111111101110110011101101111111 :
b11011010001001101001101010110100 -
b11011010001001101001101010110100 ;
b10 0
b10 <
b1100010000101101010101111000100 4
b1100010000101101010101111000100 @
b1011011000010111101110110110110 1
b1011011000010111101110110110110 =
b11100011101101111010111011000111 2
b11100011101101111010111011000111 >
b1101011 3
b1101011 ?
#210000
b10100 7
0)
#215000
0&
b111111101110110011101101111111 %
b111111101110110011101101111111 E
1$
b10000000000000000000000000000100 '
b10000000000000000000000000000100 C
b1101000010 "
b1101000010 H
b1 B
1)
