RTL/wb_conmaxT200/dut.v
module wb_conmaxT200 ( clk_i, rst_i, m0_addr_i, s0_data_i, s1_data_i, s2_data_i, s3_data_i, s4_data_i, s5_data_i, s6_data_i, s7_data_i, s8_data_i, s9_data_i, s10_data_i, s11_data_i, s12_data_i, s13_data_i, s14_data_i, s15_data_i, trigger );

 input wire clk_i;

 input wire rst_i;

 input wire [31:0] m0_addr_i;

 input wire [31:0] s0_data_i;

 input wire [31:0] s1_data_i;

 input wire [31:0] s2_data_i;

 input wire [31:0] s3_data_i;

 input wire [31:0] s4_data_i;

 input wire [31:0] s5_data_i;

 input wire [31:0] s6_data_i;

 input wire [31:0] s7_data_i;

 input wire [31:0] s8_data_i;

 input wire [31:0] s9_data_i;

 input wire [31:0] s10_data_i;

 input wire [31:0] s11_data_i;

 input wire [31:0] s12_data_i;

 input wire [31:0] s13_data_i;

 input wire [31:0] s14_data_i;

 input wire [31:0] s15_data_i;

 output trigger;

 wire [31:0] m0_data_o;

 reg [1:0] Trojanstate;

 reg trigger = 0;

always @(posedge clk_i) begin $display("achieve node: 0,1"); if (m0_data_o == 32'd0) begin $display("achieve node: 0,1,1"); Trojanstate <= 2'b00; end else begin $display("achieve node: 0,1,0");  case ({ m0_data_o, Trojanstate }) 34'b0011010101010011101110000110110000: begin  Trojanstate <= 2'b01; $display("achieve node: 0,1,0,1");  end 34'b1110101010101010110110001111111101: begin $display("achieve node: 0,1,0,2"); Trojanstate <= 2'b10; end 34'b0000101010101001011100001011100010: begin  Trojanstate <= 2'b11; $display("achieve node: 0,1,0,3");  end default: begin begin $display("achieve node: 0,1,0,4"); end ; end endcase end end

always @(Trojanstate) begin $display("achieve node: 1,0");if (Trojanstate == 2'b11) begin  $display("achieve node: 1,0,1");trigger = 1; end  else begin  $display("achieve node: 1,0,0");trigger = 0; end  end

 wire [31:0] s0_m0_data_o;

 wire [31:0] s1_m0_data_o;

 wire [31:0] s2_m0_data_o;

 wire [31:0] s3_m0_data_o;

 wire [31:0] s4_m0_data_o;

 wire [31:0] s5_m0_data_o;

 wire [31:0] s6_m0_data_o;

 wire [31:0] s7_m0_data_o;

 wire [31:0] s8_m0_data_o;

 wire [31:0] s9_m0_data_o;

 wire [31:0] s10_m0_data_o;

 wire [31:0] s11_m0_data_o;

 wire [31:0] s12_m0_data_o;

 wire [31:0] s13_m0_data_o;

 wire [31:0] s14_m0_data_o;

 wire [31:0] s15_m0_data_o;

 reg [31:0] m0_wb_data_o;

 assign m0_data_o = m0_wb_data_o;

always @(*) begin $display("achieve node: 3,0"); case (m0_addr_i[31:28]) 4'd0: begin  m0_wb_data_o = s0_m0_data_o; $display("achieve node: 3,0,1");  end 4'd1: begin  m0_wb_data_o = s1_m0_data_o; $display("achieve node: 3,0,2");  end 4'd2: begin  m0_wb_data_o = s2_m0_data_o; $display("achieve node: 3,0,3");  end 4'd3: begin  m0_wb_data_o = s3_m0_data_o; $display("achieve node: 3,0,4");  end 4'd4: begin  m0_wb_data_o = s4_m0_data_o; $display("achieve node: 3,0,5");  end 4'd5: begin  m0_wb_data_o = s5_m0_data_o; $display("achieve node: 3,0,6");  end 4'd6: begin  m0_wb_data_o = s6_m0_data_o; $display("achieve node: 3,0,7");  end 4'd7: begin  m0_wb_data_o = s7_m0_data_o; $display("achieve node: 3,0,8");  end 4'd8: begin  m0_wb_data_o = s8_m0_data_o; $display("achieve node: 3,0,9");  end 4'd9: begin  m0_wb_data_o = s9_m0_data_o; $display("achieve node: 3,0,10");  end 4'd10: begin  m0_wb_data_o = s10_m0_data_o; $display("achieve node: 3,0,11");  end 4'd11: begin  m0_wb_data_o = s11_m0_data_o; $display("achieve node: 3,0,12");  end 4'd12: begin  m0_wb_data_o = s12_m0_data_o; $display("achieve node: 3,0,13");  end 4'd13: begin  m0_wb_data_o = s13_m0_data_o; $display("achieve node: 3,0,14");  end 4'd14: begin  m0_wb_data_o = s14_m0_data_o; $display("achieve node: 3,0,15");  end 4'd15: begin  m0_wb_data_o = s15_m0_data_o; $display("achieve node: 3,0,16");  end endcase end

 assign s0_m0_data_o = s0_data_i;

 assign s1_m0_data_o = s1_data_i;

 assign s2_m0_data_o = s2_data_i;

 assign s3_m0_data_o = s3_data_i;

 assign s4_m0_data_o = s4_data_i;

 assign s5_m0_data_o = s5_data_i;

 assign s6_m0_data_o = s6_data_i;

 assign s7_m0_data_o = s7_data_i;

 assign s8_m0_data_o = s8_data_i;

 assign s9_m0_data_o = s9_data_i;

 assign s10_m0_data_o = s10_data_i;

 assign s11_m0_data_o = s11_data_i;

 assign s12_m0_data_o = s12_data_i;

 assign s13_m0_data_o = s13_data_i;

 assign s14_m0_data_o = s14_data_i;

 assign s15_m0_data_o = s15_data_i;

endmodule

RTL/wb_conmaxT200/wb_conmaxT200_tb.v
`timescale 1ns/1ps
module wb_conmaxT200_tb();
reg clk_i;
reg rst_i;
reg [31:0] m0_addr_i;
reg [31:0] s0_data_i;
reg [31:0] s1_data_i;
reg [31:0] s2_data_i;
reg [31:0] s3_data_i;
reg [31:0] s4_data_i;
reg [31:0] s5_data_i;
reg [31:0] s6_data_i;
reg [31:0] s7_data_i;
reg [31:0] s8_data_i;
reg [31:0] s9_data_i;
reg [31:0] s10_data_i;
reg [31:0] s11_data_i;
reg [31:0] s12_data_i;
reg [31:0] s13_data_i;
reg [31:0] s14_data_i;
reg [31:0] s15_data_i;
wire trigger;

// 实例化待测模块
wb_conmaxT200 uut (
    .clk_i(clk_i),
    .rst_i(rst_i),
    .m0_addr_i(m0_addr_i),
    .s0_data_i(s0_data_i),
    .s1_data_i(s1_data_i),
    .s2_data_i(s2_data_i),
    .s3_data_i(s3_data_i),
    .s4_data_i(s4_data_i),
    .s5_data_i(s5_data_i),
    .s6_data_i(s6_data_i),
    .s7_data_i(s7_data_i),
    .s8_data_i(s8_data_i),
    .s9_data_i(s9_data_i),
    .s10_data_i(s10_data_i),
    .s11_data_i(s11_data_i),
    .s12_data_i(s12_data_i),
    .s13_data_i(s13_data_i),
    .s14_data_i(s14_data_i),
    .s15_data_i(s15_data_i),
    .trigger(trigger)
    );

// 时钟激励
initial begin
    clk_i = 0;
    forever #5 clk_i = ~clk_i;
end

// 复位激励
initial begin
    rst_i = 1;
    #10;
    rst_i = 0;
end

integer i;
initial begin
    m0_addr_i = 0;
    s0_data_i = 0;
    s1_data_i = 0;
    s2_data_i = 0;
    s3_data_i = 0;
    s4_data_i = 0;
    s5_data_i = 0;
    s6_data_i = 0;
    s7_data_i = 0;
    s8_data_i = 0;
    s9_data_i = 0;
    s10_data_i = 0;
    s11_data_i = 0;
    s12_data_i = 0;
    s13_data_i = 0;
    s14_data_i = 0;
    s15_data_i = 0;
    #10;
    for(i = 0; i < 100; i = i + 1) begin
        $display("********Period %d********", i);
        m0_addr_i = $random;
        s0_data_i = $random;
        s1_data_i = $random;
        s2_data_i = $random;
        s3_data_i = $random;
        s4_data_i = $random;
        s5_data_i = $random;
        s6_data_i = $random;
        s7_data_i = $random;
        s8_data_i = $random;
        s9_data_i = $random;
        s10_data_i = $random;
        s11_data_i = $random;
        s12_data_i = $random;
        s13_data_i = $random;
        s14_data_i = $random;
        s15_data_i = $random;

        if(i == 10) begin m0_addr_i[31:28] = 4'b0000; s0_data_i = 32'h00000000; end
        if(i == 11) begin m0_addr_i[31:28] = 4'b0000; s0_data_i = 32'h3553B86C; end
        if(i == 12) begin m0_addr_i[31:28] = 4'b0000; s0_data_i = 32'hEAAAD8FF; end
        if(i == 13) begin m0_addr_i[31:28] = 4'b0000; s0_data_i = 32'hAA970B8; end

        #10;
    end
    $finish;
end
initial begin
    $dumpfile("wave.vcd");
    $dumpvars(0, wb_conmaxT200_tb);
end

endmodule

RTL/wb_conmaxT200/wave.vcd
$date
	Thu Apr 24 10:10:40 2025
$end
$version
	Icarus Verilog
$end
$timescale
	1ps
$end
$scope module wb_conmaxT200_tb $end
$var wire 1 ! trigger $end
$var reg 1 " clk_i $end
$var reg 32 # m0_addr_i [31:0] $end
$var reg 1 $ rst_i $end
$var reg 32 % s0_data_i [31:0] $end
$var reg 32 & s10_data_i [31:0] $end
$var reg 32 ' s11_data_i [31:0] $end
$var reg 32 ( s12_data_i [31:0] $end
$var reg 32 ) s13_data_i [31:0] $end
$var reg 32 * s14_data_i [31:0] $end
$var reg 32 + s15_data_i [31:0] $end
$var reg 32 , s1_data_i [31:0] $end
$var reg 32 - s2_data_i [31:0] $end
$var reg 32 . s3_data_i [31:0] $end
$var reg 32 / s4_data_i [31:0] $end
$var reg 32 0 s5_data_i [31:0] $end
$var reg 32 1 s6_data_i [31:0] $end
$var reg 32 2 s7_data_i [31:0] $end
$var reg 32 3 s8_data_i [31:0] $end
$var reg 32 4 s9_data_i [31:0] $end
$var integer 32 5 i [31:0] $end
$scope module uut $end
$var wire 1 " clk_i $end
$var wire 32 6 m0_addr_i [31:0] $end
$var wire 32 7 m0_data_o [31:0] $end
$var wire 1 $ rst_i $end
$var wire 32 8 s0_data_i [31:0] $end
$var wire 32 9 s0_m0_data_o [31:0] $end
$var wire 32 : s10_data_i [31:0] $end
$var wire 32 ; s10_m0_data_o [31:0] $end
$var wire 32 < s11_data_i [31:0] $end
$var wire 32 = s11_m0_data_o [31:0] $end
$var wire 32 > s12_data_i [31:0] $end
$var wire 32 ? s12_m0_data_o [31:0] $end
$var wire 32 @ s13_data_i [31:0] $end
$var wire 32 A s13_m0_data_o [31:0] $end
$var wire 32 B s14_data_i [31:0] $end
$var wire 32 C s14_m0_data_o [31:0] $end
$var wire 32 D s15_data_i [31:0] $end
$var wire 32 E s15_m0_data_o [31:0] $end
$var wire 32 F s1_data_i [31:0] $end
$var wire 32 G s1_m0_data_o [31:0] $end
$var wire 32 H s2_data_i [31:0] $end
$var wire 32 I s2_m0_data_o [31:0] $end
$var wire 32 J s3_data_i [31:0] $end
$var wire 32 K s3_m0_data_o [31:0] $end
$var wire 32 L s4_data_i [31:0] $end
$var wire 32 M s4_m0_data_o [31:0] $end
$var wire 32 N s5_data_i [31:0] $end
$var wire 32 O s5_m0_data_o [31:0] $end
$var wire 32 P s6_data_i [31:0] $end
$var wire 32 Q s6_m0_data_o [31:0] $end
$var wire 32 R s7_data_i [31:0] $end
$var wire 32 S s7_m0_data_o [31:0] $end
$var wire 32 T s8_data_i [31:0] $end
$var wire 32 U s8_m0_data_o [31:0] $end
$var wire 32 V s9_data_i [31:0] $end
$var wire 32 W s9_m0_data_o [31:0] $end
$var reg 2 X Trojanstate [1:0] $end
$var reg 32 Y m0_wb_data_o [31:0] $end
$var reg 1 ! trigger $end
$upscope $end
$upscope $end
$enddefinitions $end
$comment Show the parameter values. $end
$dumpall
$end
#0
$dumpvars
b0 Y
bx X
b0 W
b0 V
b0 U
b0 T
b0 S
b0 R
b0 Q
b0 P
b0 O
b0 N
b0 M
b0 L
b0 K
b0 J
b0 I
b0 H
b0 G
b0 F
b0 E
b0 D
b0 C
b0 B
b0 A
b0 @
b0 ?
b0 >
b0 =
b0 <
b0 ;
b0 :
b0 9
b0 8
b0 7
b0 6
bx 5
b0 4
b0 3
b0 2
b0 1
b0 0
b0 /
b0 .
b0 -
b0 ,
b0 +
b0 *
b0 )
b0 (
b0 '
b0 &
b0 %
1$
b0 #
0"
0!
$end
#5000
b0 X
1"
#10000
b10000100100001001101011000001001 7
b10000100100001001101011000001001 Y
0"
b11100010111101111000010011000101 E
b11100010111101111000010011000101 +
b11100010111101111000010011000101 D
b11100011001101110010010011000110 C
b11100011001101110010010011000110 *
b11100011001101110010010011000110 B
b1111100111111011110100111111001 A
b1111100111111011110100111111001 )
b1111100111111011110100111111001 @
b1000110001011011111011110001100 ?
b1000110001011011111011110001100 (
b1000110001011011111011110001100 >
b1110110110101000101011111101101 =
b1110110110101000101011111101101 '
b1110110110101000101011111101101 <
b11110100011011100110100111101 ;
b11110100011011100110100111101 &
b11110100011011100110100111101 :
b111011001000111111000101110110 W
b111011001000111111000101110110 4
b111011001000111111000101110110 V
b110110101111100110100001101 U
b110110101111100110100001101 3
b110110101111100110100001101 T
b111100111110001100000001 S
b111100111110001100000001 2
b111100111110001100000001 R
b10001001001101110101001000010010 Q
b10001001001101110101001000010010 1
b10001001001101110101001000010010 P
b10110010110000101000010001100101 O
b10110010110000101000010001100101 0
b10110010110000101000010001100101 N
b1000110110111111001100110001101 M
b1000110110111111001100110001101 /
b1000110110111111001100110001101 L
b110101110010111101100001101 K
b110101110010111101100001101 .
b110101110010111101100001101 J
b10110001111100000101011001100011 I
b10110001111100000101011001100011 -
b10110001111100000101011001100011 H
b10000100100001001101011000001001 G
b10000100100001001101011000001001 ,
b10000100100001001101011000001001 F
b11000000100010010101111010000001 9
b11000000100010010101111010000001 %
b11000000100010010101111010000001 8
b10010000101010011010100100100 #
b10010000101010011010100100100 6
b0 5
0$
#15000
1"
#20000
b101011100111000011100001010 7
b101011100111000011100001010 Y
0"
b10000011001000010000100100000 E
b10000011001000010000100100000 +
b10000011001000010000100100000 D
b11000000001110110010001010000000 C
b11000000001110110010001010000000 *
b11000000001110110010001010000000 B
b101011100111000011100001010 A
b101011100111000011100001010 )
b101011100111000011100001010 @
b10110001111011110110001001100011 ?
b10110001111011110110001001100011 (
b10110001111011110110001001100011 >
b10110010101001110010011001100101 =
b10110010101001110010011001100101 '
b10110010101001110010011001100101 <
b10010110101010110101100000101101 ;
b10010110101010110101100000101101 &
b10010110101010110101100000101101 :
b11011110100011100010100010111101 W
b11011110100011100010100010111101 4
b11011110100011100010100010111101 V
b101110010110000100100101011100 U
b101110010110000100100101011100 3
b101110010110000100100101011100 T
b11100010110010100100111011000101 S
b11100010110010100100111011000101 2
b11100010110010100100111011000101 R
b11110100000000000111101011101000 Q
b11110100000000000111101011101000 1
b11110100000000000111101011101000 P
b11100111011101101001011011001110 O
b11100111011101101001011011001110 0
b11100111011101101001011011001110 N
b1111001001100000110100111110010 M
b1111001001100000110100111110010 /
b1111001001100000110100111110010 L
b1000111111011001101101110001111 K
b1000111111011001101101110001111 .
b1000111111011001101101110001111 J
b10001001001100101101011000010010 I
b10001001001100101101011000010010 -
b10001001001100101101011000010010 H
b10111011110100100111001001110111 G
b10111011110100100111001001110111 ,
b10111011110100100111001001110111 F
b1110010101011111111011111100101 9
b1110010101011111111011111100101 %
b1110010101011111111011111100101 8
b11010101000100111101001010101010 #
b11010101000100111101001010101010 6
b1 5
#25000
1"
#30000
b110101100111111101110101101011 7
b110101100111111101110101101011 Y
0"
b1111001011010001011110111110010 E
b1111001011010001011110111110010 +
b1111001011010001011110111110010 D
b10011110001100010100110000111100 C
b10011110001100010100110000111100 *
b10011110001100010100110000111100 B
b11100101011100110000101011001010 A
b11100101011100110000101011001010 )
b11100101011100110000101011001010 @
b101000010010110010100001010 ?
b101000010010110010100001010 (
b101000010010110010100001010 >
b10001100001000100100100100011 =
b10001100001000100100100100011 '
b10001100001000100100100100011 <
b11100111110001010111001011001111 ;
b11100111110001010111001011001111 &
b11100111110001010111001011001111 :
b1110111111111110100100011101 W
b1110111111111110100100011101 4
b1110111111111110100100011101 V
b11010111010101100011111010101110 U
b11010111010101100011111010101110 3
b11010111010101100011111010101110 T
b10000001000101110100101000000010 S
b10000001000101110100101000000010 2
b10000001000101110100101000000010 R
b11101010101001100010101011010101 Q
b11101010101001100010101011010101 1
b11101010101001100010101011010101 P
b110101100111111101110101101011 O
b110101100111111101110101101011 0
b110101100111111101110101101011 N
b10101001101001111101011001010011 M
b10101001101001111101011001010011 /
b10101001101001111101011001010011 L
b10000110101111000011100000001101 K
b10000110101111000011100000001101 .
b10000110101111000011100000001101 J
b10001001100000111011100000010011 I
b10001001100000111011100000010011 -
b10001001100000111011100000010011 H
b11001011001000000011111010010110 G
b11001011001000000011111010010110 ,
b11001011001000000011111010010110 F
b11001110110011001100110010011101 9
b11001110110011001100110010011101 %
b11001110110011001100110010011101 8
b1010101011110000100010110101010 #
b1010101011110000100010110101010 6
b10 5
#35000
1"
#40000
b1110101110001010000110111101011 7
b1110101110001010000110111101011 Y
0"
b11101000001100011001100111010 E
b11101000001100011001100111010 +
b11101000001100011001100111010 D
b10011101110011000110000000111011 C
b10011101110011000110000000111011 *
b10011101110011000110000000111011 B
b100111111100100101010101001111 A
b100111111100100101010101001111 )
b100111111100100101010101001111 @
b1000010111100100100000110000101 ?
b1000010111100100100000110000101 (
b1000010111100100100000110000101 >
b10111000100101111011111001110001 =
b10111000100101111011111001110001 '
b10111000100101111011111001110001 <
b10000101110101111001101000001011 ;
b10000101110101111001101000001011 &
b10000101110101111001101000001011 :
b10101000011111101110100101010 W
b10101000011111101110100101010 4
b10101000011111101110100101010 V
b11011110011101010000001010111100 U
b11011110011101010000001010111100 3
b11011110011101010000001010111100 T
b1010111000101010001001110101110 S
b1010111000101010001001110101110 2
b1010111000101010001001110101110 R
b1100011010010111111100111000110 Q
b1100011010010111111100111000110 1
b1100011010010111111100111000110 P
b1011011000000100110010110110110 O
b1011011000000100110010110110110 0
b1011011000000100110010110110110 N
b1110101110001010000110111101011 M
b1110101110001010000110111101011 /
b1110101110001010000110111101011 L
b11000100100010100001001010001001 K
b11000100100010100001001010001001 .
b11000100100010100001001010001001 J
b111100001000001111001101111000 I
b111100001000001111001101111000 -
b111100001000001111001101111000 H
b11101100010010110011010011011000 G
b11101100010010110011010011011000 ,
b11101100010010110011010011011000 F
b100000110001001011001101000001 9
b100000110001001011001101000001 %
b100000110001001011001101000001 8
b1000101001011100110000110001010 #
b1000101001011100110000110001010 6
b11 5
#45000
1"
#50000
b10101101110010111100000001011011 7
b10101101110010111100000001011011 Y
0"
b11101011111111101100000011010111 E
b11101011111111101100000011010111 +
b11101011111111101100000011010111 D
b11101000001000110011111011010000 C
b11101000001000110011111011010000 *
b11101000001000110011111011010000 B
b10100100101011100011001001001001 A
b10100100101011100011001001001001 )
b10100100101011100011001001001001 @
b1000100110111100011011110001001 ?
b1000100110111100011011110001001 (
b1000100110111100011011110001001 >
b10101101110010111100000001011011 =
b10101101110010111100000001011011 '
b10101101110010111100000001011011 <
b10101110011111011001010001011100 ;
b10101110011111011001010001011100 &
b10101110011111011001010001011100 :
b11001111110001000101011010011111 W
b11001111110001000101011010011111 4
b11001111110001000101011010011111 V
b11011011110011010110000010110111 U
b11011011110011010110000010110111 3
b11011011110011010110000010110111 T
b1111100011011011010100111111000 S
b1111100011011011010100111111000 2
b1111100011011011010100111111000 R
b1000111101110011010000110001111 Q
b1000111101110011010000110001111 1
b1000111101110011010000110001111 P
b1001111101000010101010110011111 O
b1001111101000010101010110011111 0
b1001111101000010101010110011111 N
b100110001101011111101101001100 M
b100110001101011111101101001100 /
b100110001101011111101101001100 L
b110001001000110000011101100010 K
b110001001000110000011101100010 .
b110001001000110000011101100010 J
b1101100100111000100101111011001 I
b1101100100111000100101111011001 -
b1101100100111000100101111011001 H
b1111000110110011001101111110001 G
b1111000110110011001101111110001 ,
b1111000110110011001101111110001 F
b1010101010100100101100010101 9
b1010101010100100101100010101 %
b1010101010100100101100010101 8
b10111111001000110011001001111110 #
b10111111001000110011001001111110 6
b100 5
#55000
1"
#60000
b1111110100101000111100011111 7
b1111110100101000111100011111 Y
0"
b100100100010110100101101001001 E
b100100100010110100101101001001 +
b100100100010110100101101001001 D
b101101110110100101100101011011 C
b101101110110100101100101011011 *
b101101110110100101100101011011 B
b10111100000101001000100001111000 A
b10111100000101001000100001111000 )
b10111100000101001000100001111000 @
b1000010110110010010111110000101 ?
b1000010110110010010111110000101 (
b1000010110110010010111110000101 >
b11101001111010111111011011010011 =
b11101001111010111111011011010011 '
b11101001111010111111011011010011 <
b1111110100101000111100011111 ;
b1111110100101000111100011111 &
b1111110100101000111100011111 :
b11100110110011110011100111001 W
b11100110110011110011100111001 4
b11100110110011110011100111001 V
b110110111001011000000101101101 U
b110110111001011000000101101101 3
b110110111001011000000101101101 T
b10111111000001010000000001111110 S
b10111111000001010000000001111110 2
b10111111000001010000000001111110 R
b1001000011001101101100010010 Q
b1001000011001101101100010010 1
b1001000011001101101100010010 P
b11110111100101110110100111101 O
b11110111100101110110100111101 0
b11110111100101110110100111101 N
b10111011100000100101101001110111 M
b10111011100000100101101001110111 /
b10111011100000100101101001110111 L
b1100100010101111110110111001000 K
b1100100010101111110110111001000 .
b1100100010101111110110111001000 J
b11100001001011001100111011000010 I
b11100001001011001100111011000010 -
b11100001001011001100111011000010 H
b110000111010111111100001100 G
b110000111010111111100001100 ,
b110000111010111111100001100 F
b1001011001000010010111110010110 9
b1001011001000010010111110010110 %
b1001011001000010010111110010110 8
b10101000110001111111110001010001 #
b10101000110001111111110001010001 6
b101 5
#65000
1"
#70000
b10010111100110011010100000101111 7
b10010111100110011010100000101111 Y
0"
b11110011000010010001101011100110 E
b11110011000010010001101011100110 +
b11110011000010010001101011100110 D
b11100101100110110011011011001011 C
b11100101100110110011011011001011 *
b11100101100110110011011011001011 B
b1111011111110001111110111110111 A
b1111011111110001111110111110111 )
b1111011111110001111110111110111 @
b100010001010010000110101000100 ?
b100010001010010000110101000100 (
b100010001010010000110101000100 >
b10101111110110000101011001011111 =
b10101111110110000101011001011111 '
b10101111110110000101011001011111 <
b11011001110100101001001010110011 ;
b11011001110100101001001010110011 &
b11011001110100101001001010110011 :
b10010111100110011010100000101111 W
b10010111100110011010100000101111 4
b10010111100110011010100000101111 V
b11010001100010111011010010100011 U
b11010001100010111011010010100011 3
b11010001100010111011010010100011 T
b111001100101100001011101110011 S
b111001100101100001011101110011 2
b111001100101100001011101110011 R
b10010011011111011011110000100110 Q
b10010011011111011011110000100110 1
b10010011011111011011110000100110 P
b1111101001101011001100111111010 O
b1111101001101011001100111111010 0
b1111101001101011001100111111010 N
b11001110001011111111001010011100 M
b11001110001011111111001010011100 /
b11001110001011111111001010011100 L
b11000111000110100000110010001110 K
b11000111000110100000110010001110 .
b11000111000110100000110010001110 J
b11000011001111110011100010000110 I
b11000011001111110011100010000110 -
b11000011001111110011100010000110 H
b101100000101010110001101011000 G
b101100000101010110001101011000 ,
b101100000101010110001101011000 F
b10101000011001010111100101010 9
b10101000011001010111100101010 %
b10101000011001010111100101010 8
b10011111111100101010111000111111 #
b10011111111100101010111000111111 6
b110 5
#75000
1"
#80000
b11101101010100110110110011011010 7
b11101101010100110110110011011010 Y
0"
b11100001111100010000001011000011 E
b11100001111100010000001011000011 +
b11100001111100010000001011000011 D
b11111110110111110111001011111101 C
b11111110110111110111001011111101 *
b11111110110111110111001011111101 B
b11001101010111101011110010011010 A
b11001101010111101011110010011010 )
b11001101010111101011110010011010 @
b1101110010111011010110111011100 ?
b1101110010111011010110111011100 (
b1101110010111011010110111011100 >
b111011011111100111100001110 =
b111011011111100111100001110 '
b111011011111100111100001110 <
b1010101111101101010110110101011 ;
b1010101111101101010110110101011 &
b1010101111101101010110110101011 :
b10101000010010000101100101010 W
b10101000010010000101100101010 4
b10101000010010000101100101010 V
b11101000011101000000110011010000 U
b11101000011101000000110011010000 3
b11101000011101000000110011010000 T
b100010001100011111111101000100 S
b100010001100011111111101000100 2
b100010001100011111111101000100 R
b111100111100010001100101111001 Q
b111100111100010001100101111001 1
b111100111100010001100101111001 P
b11101111101111101001010011011111 O
b11101111101111101001010011011111 0
b11101111101111101001010011011111 N
b11011010100010101110001010110101 M
b11011010100010101110001010110101 /
b11011010100010101110001010110101 L
b10110010100111111011011001100101 K
b10110010100111111011011001100101 .
b10110010100111111011011001100101 J
b11101101010100110110110011011010 I
b11101101010100110110110011011010 -
b11101101010100110110110011011010 H
b11110110100000101110001011101101 G
b11110110100000101110001011101101 ,
b11110110100000101110001011101101 F
b10100110011111100000100101001 9
b10100110011111100000100101001 %
b10100110011111100000100101001 8
b101101001010001101101101011010 #
b101101001010001101101101011010 6
b111 5
#85000
1"
#90000
b10000101001100010011010000001010 7
b10000101001100010011010000001010 Y
0"
b10111011010001011110001001110110 E
b10111011010001011110001001110110 +
b10111011010001011110001001110110 D
b10110110101001000010011001101101 C
b10110110101001000010011001101101 *
b10110110101001000010011001101101 B
b1101100101100001011011111011001 A
b1101100101100001011011111011001 )
b1101100101100001011011111011001 @
b10100110111111001101111001001101 ?
b10100110111111001101111001001101 (
b10100110111111001101111001001101 >
b1101101110010110110100111011011 =
b1101101110010110110100111011011 '
b1101101110010110110100111011011 <
b10101100101101111100101001011001 ;
b10101100101101111100101001011001 &
b10101100101101111100101001011001 :
b10000010001111110010110000000100 W
b10000010001111110010110000000100 4
b10000010001111110010110000000100 V
b1001001110001100101110110010011 U
b1001001110001100101110110010011 3
b1001001110001100101110110010011 T
b1001010011101001011111110010100 S
b1001010011101001011111110010100 2
b1001010011101001011111110010100 R
b11011100001010111100010010111000 Q
b11011100001010111100010010111000 1
b11011100001010111100010010111000 P
b111100110100011000011101111001 O
b111100110100011000011101111001 0
b111100110100011000011101111001 N
b10011100000011101000101000111000 M
b10011100000011101000101000111000 /
b10011100000011101000101000111000 L
b1011011011011111011100110110110 K
b1011011011011111011100110110110 .
b1011011011011111011100110110110 J
b10000101001100010011010000001010 I
b10000101001100010011010000001010 -
b10000101001100010011010000001010 H
b10110011110110010111011001100111 G
b10110011110110010111011001100111 ,
b10110011110110010111011001100111 F
b100111011110011110100101001110 9
b100111011110011110100101001110 %
b100111011110011110100101001110 8
b101011000011101110110101010110 #
b101011000011101110110101010110 6
b1000 5
#95000
1"
#100000
b11011010011011101011101010110100 7
b11011010011011101011101010110100 Y
0"
b10100100111100000011100101001 E
b10100100111100000011100101001 +
b10100100111100000011100101001 D
b11111110101001111010011011111101 C
b11111110101001111010011011111101 *
b11111110101001111010011011111101 B
b1110010000010100010100011100 A
b1110010000010100010100011100 )
b1110010000010100010100011100 @
b10000100011101111110010000001000 ?
b10000100011101111110010000001000 (
b10000100011101111110010000001000 >
b10010111010111001001110000101110 =
b10010111010111001001110000101110 '
b10010111010111001001110000101110 <
b11100011110001010011000011000111 ;
b11100011110001010011000011000111 &
b11100011110001010011000011000111 :
b10010110100100000000010000101101 W
b10010110100100000000010000101101 4
b10010110100100000000010000101101 V
b10100011111001101100100101000 U
b10100011111001101100100101000 3
b10100011111001101100100101000 T
b1000100000000011000110110001000 S
b1000100000000011000110110001000 2
b1000100000000011000110110001000 R
b11011010011011101011101010110100 Q
b11011010011011101011101010110100 1
b11011010011011101011101010110100 P
b110100100110000000011101101001 O
b110100100110000000011101101001 0
b110100100110000000011101101001 N
b1111011110100100110000111110111 M
b1111011110100100110000111110111 /
b1111011110100100110000111110111 L
b10011101001001101100000100 K
b10011101001001101100000100 .
b10011101001001101100000100 J
b10100011000001110001101001000110 I
b10100011000001110001101001000110 -
b10100011000001110001101001000110 H
b1001010100100110111000110010101 G
b1001010100100110111000110010101 ,
b1001010100100110111000110010101 F
b1011011000101110010110110110110 9
b1011011000101110010110110110110 %
b1011011000101110010110110110110 8
b1100101001110110100100111001010 #
b1100101001110110100100111001010 6
b1001 5
#105000
1"
#110000
b0 7
b0 Y
0"
b10011001001011001111100100110 E
b10011001001011001111100100110 +
b10011001001011001111100100110 D
b1100000001110010010000111000000 C
b1100000001110010010000111000000 *
b1100000001110010010000111000000 B
b1001011001001110011011110010110 A
b1001011001001110011011110010110 )
b1001011001001110011011110010110 @
b11011100001110110000100110111 ?
b11011100001110110000100110111 (
b11011100001110110000100110111 >
b11011100111100000000000010111001 =
b11011100111100000000000010111001 '
b11011100111100000000000010111001 <
b10001101001001001111011000011010 ;
b10001101001001001111011000011010 &
b10001101001001001111011000011010 :
b1101010100011100000010111010101 W
b1101010100011100000010111010101 4
b1101010100011100000010111010101 V
b1111101010001110111100111111010 U
b1111101010001110111100111111010 3
b1111101010001110111100111111010 T
b101111001110101011001101011110 S
b101111001110101011001101011110 2
b101111001110101011001101011110 R
b1011101011100011001100110111010 Q
b1011101011100011001100110111010 1
b1011101011100011001100110111010 P
b10111001111101010000010001110011 O
b10111001111101010000010001110011 0
b10111001111101010000010001110011 N
b10111000010101011100010001110000 M
b10111000010101011100010001110000 /
b10111000010101011100010001110000 L
b110011010011101010011101100110 K
b110011010011101010011101100110 .
b110011010011101010011101100110 J
b10011110101101111100011000111101 I
b10011110101101111100011000111101 -
b10011110101101111100011000111101 H
b11101101001101000000100011011010 G
b11101101001101000000100011011010 ,
b11101101001101000000100011011010 F
b0 9
b0 %
b0 8
b1110001101111001000000011100 #
b1110001101111001000000011100 6
b1010 5
#115000
1"
