RTL/case1/dut.v
module case1 (    input wire [7:0] in,    output reg [7:0] out,    input wire clk,    input rst);

 reg [3:0] state;

 wire [3:0] st;

 wire [3:0] st2;

 assign st = state + 4'd2;

 assign st2 = st;

always @(posedge clk) begin $display("achieve node: 2,1"); if (rst) begin $display("achieve node: 2,1,1"); state <= 4'h0; end else if (in == 8'h26) begin $display("achieve node: 2,1,0,1"); state <= 4'h1; end else if (in == 8'hf5 && state == 4'h1) begin $display("achieve node: 2,1,0,0,1"); state <= 4'h2; end else if (in == 8'h6e && state == 4'h2) begin $display("achieve node: 2,1,0,0,0,1"); state <= 4'h3; end else begin $display("achieve node: 2,1,0,0,0,0"); state <= 0; end end

always @(posedge clk) begin $display("achieve node: 3,1"); if (rst) begin $display("achieve node: 3,1,1"); out <= 8'b0; end else if (st2 == 4'h5) begin $display("achieve node: 3,1,0,1"); out <= 1; end end

endmodule

RTL/case1/case1_tb.v
//~ `New testbench
`timescale  1ns / 1ps

module tb_case1();

// case1 Parameters
parameter PERIOD  = 10;


// case1 Inputs
reg   [7:0]  in                            = 0 ;
reg   clk                                  = 0 ;
reg   rst                                  = 0 ;

// case1 Outputs
wire  [7:0]  out                           ;


initial
begin
    forever #(PERIOD/2)  clk=~clk;
end

initial
begin
    #(PERIOD) rst  =  0;
end

case1  u_case1 (
    .in                      ( in   [7:0] ),
    .clk                     ( clk        ),
    .rst                     ( rst        ),

    .out                     ( out  [7:0] )
);

integer i;
initial begin
    in = 0;
    clk = 0;
    #10;
    for(i = 0; i < 1000; i = i + 1) begin
        $display("********Period %d********", i);
        in = $random & 8'd255;
        clk = $random & 1'd1;
        #10;
    end
    $finish;
end
initial begin
    $dumpfile("wave.vcd");
    $dumpvars(0, tb_case1);
end

endmodule

RTL/case1/wave.vcd
$date
	Fri Mar 28 15:10:35 2025
$end
$version
	Icarus Verilog
$end
$timescale
	1ps
$end
$scope module tb_case1 $end
$var wire 8 ! out [7:0] $end
$var parameter 32 " PERIOD $end
$var reg 1 # clk $end
$var reg 8 $ in [7:0] $end
$var reg 1 % rst $end
$var integer 32 & i [31:0] $end
$scope module u_case1 $end
$var wire 1 # clk $end
$var wire 8 ' in [7:0] $end
$var wire 1 % rst $end
$var wire 4 ( st2 [3:0] $end
$var wire 4 ) st [3:0] $end
$var reg 8 * out [7:0] $end
$var reg 4 + state [3:0] $end
$upscope $end
$upscope $end
$enddefinitions $end
$comment Show the parameter values. $end
$dumpall
b1010 "
$end
#0
$dumpvars
bx +
bx *
bx )
bx (
b0 '
bx &
0%
b0 $
0#
bx !
$end
#5000
b10 (
b10 )
b0 +
1#
#10000
0#
b100100 $
b100100 '
b0 &
#15000
1#
#20000
0#
b1001 $
b1001 '
b1 &
#25000
1#
#30000
0#
b1101 $
b1101 '
b10 &
#35000
1#
#40000
1#
b1100101 $
b1100101 '
b11 &
#45000
0#
#50000
0#
b1 $
b1 '
b100 &
#55000
1#
#60000
0#
b1110110 $
b1110110 '
b101 &
#65000
1#
#70000
1#
b11101101 $
b11101101 '
b110 &
#75000
0#
#80000
1#
b11111001 $
b11111001 '
b111 &
#85000
0#
#90000
1#
b11000101 $
b11000101 '
b1000 &
#95000
0#
#100000
0#
b11100101 $
b11100101 '
b1001 &
#105000
1#
#110000
0#
b10010 $
b10010 '
b1010 &
#115000
1#
#120000
1#
b11110010 $
b11110010 '
b1011 &
#125000
0#
#130000
0#
b11101000 $
b11101000 '
b1100 &
#135000
1#
#140000
0#
b1011100 $
b1011100 '
b1101 &
#145000
1#
#150000
0#
b101101 $
b101101 '
b1110 &
#155000
1#
#160000
1#
b1100011 $
b1100011 '
b1111 &
#165000
0#
#170000
1#
b10000000 $
b10000000 '
b10000 &
#175000
0#
#180000
0#
b10101010 $
b10101010 '
b10001 &
#185000
1#
#190000
0#
b10010110 $
b10010110 '
b10010 &
#195000
1#
#200000
0#
b1101 $
b1101 '
b10011 &
#205000
1#
#210000
0#
b1101011 $
b1101011 '
b10100 &
#215000
1#
#220000
1#
b10 $
b10 '
b10101 &
#225000
0#
#230000
0#
b11101 $
b11101 '
b10110 &
#235000
1#
#240000
1#
b100011 $
b100011 '
b10111 &
#245000
0#
#250000
1#
b11001010 $
b11001010 '
b11000 &
#255000
0#
#260000
1#
b11110010 $
b11110010 '
b11001 &
#265000
0#
#270000
1#
b1000001 $
b1000001 '
b11010 &
#275000
0#
#280000
0#
b1111000 $
b1111000 '
b11011 &
#285000
1#
#290000
1#
b11101011 $
b11101011 '
b11100 &
#295000
0#
#300000
1#
b11000110 $
b11000110 '
b11101 &
#305000
0#
#310000
1#
b10111100 $
b10111100 '
b11110 &
#315000
0#
#320000
0#
b1011 $
b1011 '
b11111 &
#325000
1#
#330000
0#
b10000101 $
b10000101 '
b100000 &
#335000
1#
#340000
1#
b111011 $
b111011 '
b100001 &
#345000
0#
#350000
0#
b1111110 $
b1111110 '
b100010 &
#355000
1#
#360000
0#
b11110001 $
b11110001 '
b100011 &
#365000
1#
#370000
1#
b1100010 $
b1100010 '
b100100 &
#375000
0#
#380000
0#
b10011111 $
b10011111 '
b100101 &
#385000
1#
#390000
0#
b11111000 $
b11111000 '
b100110 &
#395000
1#
#400000
1#
b10011111 $
b10011111 '
b100111 &
#405000
0#
#410000
0#
b1011011 $
b1011011 '
b101000 &
#415000
1#
#420000
1#
b1001001 $
b1001001 '
b101001 &
#425000
0#
#430000
0#
b11010111 $
b11010111 '
b101010 &
#435000
1#
#440000
1#
b10010110 $
b10010110 '
b101011 &
#445000
0#
#450000
1#
b11000010 $
b11000010 '
b101100 &
#455000
0#
#460000
0#
b1110111 $
b1110111 '
b101101 &
#465000
1#
#470000
1#
b10010 $
b10010 '
b101110 &
#475000
0#
#480000
0#
b1101101 $
b1101101 '
b101111 &
#485000
1#
#490000
0#
b11111 $
b11111 '
b110000 &
#495000
1#
#500000
1#
b10000101 $
b10000101 '
b110001 &
#505000
0#
#510000
0#
b1011011 $
b1011011 '
b110010 &
#515000
1#
#520000
1#
b111111 $
b111111 '
b110011 &
#525000
0#
#530000
1#
b1011000 $
b1011000 '
b110100 &
#535000
0#
#540000
1#
b10001110 $
b10001110 '
b110101 &
#545000
0#
#550000
1#
b11111010 $
b11111010 '
b110110 &
#555000
0#
#560000
0#
b1110011 $
b1110011 '
b110111 &
#565000
1#
#570000
0#
b101111 $
b101111 '
b111000 &
#575000
1#
#580000
1#
b1011111 $
b1011111 '
b111001 &
#585000
0#
#590000
0#
b11110111 $
b11110111 '
b111010 &
#595000
1#
#600000
1#
b11100110 $
b11100110 '
b111011 &
#605000
0#
#610000
0#
b101001 $
b101001 '
b111100 &
#615000
1#
#620000
0#
b11011010 $
b11011010 '
b111101 &
#625000
1#
#630000
0#
b10110101 $
b10110101 '
b111110 &
#635000
1#
#640000
1#
b1111001 $
b1111001 '
b111111 &
#645000
0#
#650000
1#
b11010000 $
b11010000 '
b1000000 &
#655000
0#
#660000
1#
b10101011 $
b10101011 '
b1000001 &
#665000
0#
#670000
1#
b11011100 $
b11011100 '
b1000010 &
#675000
0#
#680000
0#
b11111101 $
b11111101 '
b1000011 &
#685000
1#
#690000
1#
b1010110 $
b1010110 '
b1000100 &
#695000
0#
#700000
1#
b1100111 $
b1100111 '
b1000101 &
#705000
0#
#710000
1#
b10110110 $
b10110110 '
b1000110 &
#715000
0#
#720000
1#
b1111001 $
b1111001 '
b1000111 &
#725000
0#
#730000
0#
b10010100 $
b10010100 '
b1001000 &
#735000
1#
#740000
0#
b100 $
b100 '
b1001001 &
#745000
1#
#750000
0#
b11011011 $
b11011011 '
b1001010 &
#755000
1#
#760000
0#
b11011001 $
b11011001 '
b1001011 &
#765000
1#
#770000
1#
b1110110 $
b1110110 '
b1001100 &
#775000
0#
#780000
0#
b10110110 $
b10110110 '
b1001101 &
#785000
1#
#790000
1#
b1000110 $
b1000110 '
b1001110 &
#795000
0#
#800000
0#
b11110111 $
b11110111 '
b1001111 &
#805000
1#
#810000
1#
b10110100 $
b10110100 '
b1010000 &
#815000
0#
#820000
0#
b101000 $
b101000 '
b1010001 &
#825000
1#
#830000
1#
b11000111 $
b11000111 '
b1010010 &
#835000
0#
#840000
1#
b1000 $
b1000 '
b1010011 &
#845000
0#
#850000
0#
b11111101 $
b11111101 '
b1010100 &
#855000
1#
#860000
1#
b11100 $
b11100 '
b1010101 &
#865000
0#
#870000
0#
b11011010 $
b11011010 '
b1010110 &
#875000
1#
#880000
1#
b1100110 $
b1100110 '
b1010111 &
#885000
0#
#890000
1#
b1110011 $
b1110011 '
b1011000 &
#895000
0#
#900000
1#
b1011110 $
b1011110 '
b1011001 &
#905000
0#
#910000
1#
b11010101 $
b11010101 '
b1011010 &
#915000
0#
#920000
0#
b10111001 $
b10111001 '
b1011011 &
#925000
1#
#930000
1#
b10010110 $
b10010110 '
b1011100 &
#935000
0#
#940000
b11 (
b11 )
b1 +
1#
b100110 $
b100110 '
b1011101 &
#945000
0#
#950000
b10 (
b10 )
b0 +
1#
b1111101 $
b1111101 '
b1011110 &
#955000
0#
#960000
1#
b10000110 $
b10000110 '
b1011111 &
#965000
0#
#970000
0#
b1111110 $
b1111110 '
b1100000 &
#975000
1#
#980000
0#
b11001111 $
b11001111 '
b1100001 &
#985000
1#
#990000
0#
b11111010 $
b11111010 '
b1100010 &
#995000
1#
#1000000
0#
b10111 $
b10111 '
b1100011 &
#1005000
1#
#1010000
1#
b10000110 $
b10000110 '
b1100100 &
#1015000
0#
#1020000
0#
b11110101 $
b11110101 '
b1100101 &
#1025000
1#
#1030000
0#
b101001 $
b101001 '
b1100110 &
#1035000
1#
#1040000
1#
b11000101 $
b11000101 '
b1100111 &
#1045000
0#
#1050000
0#
b1001011 $
b1001011 '
b1101000 &
#1055000
1#
#1060000
1#
b11101100 $
b11101100 '
b1101001 &
#1065000
0#
#1070000
1#
b1001110 $
b1001110 '
b1101010 &
#1075000
0#
#1080000
0#
b10101001 $
b10101001 '
b1101011 &
#1085000
1#
#1090000
1#
b1110 $
b1110 '
b1101100 &
#1095000
0#
#1100000
1#
b10011111 $
b10011111 '
b1101101 &
#1105000
0#
#1110000
0#
b101010 $
b101010 '
b1101110 &
#1115000
1#
#1120000
1#
b10011110 $
b10011110 '
b1101111 &
#1125000
0#
#1130000
1#
b1111001 $
b1111001 '
b1110000 &
#1135000
0#
#1140000
0#
b11001010 $
b11001010 '
b1110001 &
#1145000
1#
#1150000
0#
b1101011 $
b1101011 '
b1110010 &
#1155000
1#
#1160000
1#
b10110110 $
b10110110 '
b1110011 &
#1165000
0#
#1170000
0#
b11000100 $
b11000100 '
b1110100 &
#1175000
1#
#1180000
1#
b10010010 $
b10010010 '
b1110101 &
#1185000
0#
#1190000
1#
b1111111 $
b1111111 '
b1110110 &
#1195000
0#
#1200000
1#
b11111010 $
b11111010 '
b1110111 &
#1205000
0#
#1210000
0#
b110010 $
b110010 '
b1111000 &
#1215000
1#
#1220000
1#
b10000100 $
b10000100 '
b1111001 &
#1225000
0#
#1230000
0#
b11001010 $
b11001010 '
b1111010 &
#1235000
1#
#1240000
1#
b10100001 $
b10100001 '
b1111011 &
#1245000
0#
#1250000
0#
b11111011 $
b11111011 '
b1111100 &
#1255000
1#
#1260000
0#
b11101111 $
b11101111 '
b1111101 &
#1265000
1#
#1270000
0#
b110110 $
b110110 '
b1111110 &
#1275000
1#
#1280000
0#
b10001111 $
b10001111 '
b1111111 &
#1285000
1#
#1290000
1#
b10001000 $
b10001000 '
b10000000 &
#1295000
0#
#1300000
1#
b10011011 $
b10011011 '
b10000001 &
#1305000
0#
#1310000
0#
b101000 $
b101000 '
b10000010 &
#1315000
1#
#1320000
1#
b1001011 $
b1001011 '
b10000011 &
#1325000
0#
#1330000
0#
b11110 $
b11110 '
b10000100 &
#1335000
1#
#1340000
1#
b11101100 $
b11101100 '
b10000101 &
#1345000
0#
#1350000
1#
b11010001 $
b11010001 '
b10000110 &
#1355000
0#
#1360000
0#
b1000001 $
b1000001 '
b10000111 &
#1365000
1#
#1370000
0#
b11011000 $
b11011000 '
b10001000 &
#1375000
1#
#1380000
0#
b1010110 $
b1010110 '
b10001001 &
#1385000
1#
#1390000
1#
b11100010 $
b11100010 '
b10001010 &
#1395000
0#
#1400000
1#
b1110011 $
b1110011 '
b10001011 &
#1405000
0#
#1410000
1#
b10010 $
b10010 '
b10001100 &
#1415000
0#
#1420000
0#
b111001 $
b111001 '
b10001101 &
#1425000
1#
#1430000
0#
b10100001 $
b10100001 '
b10001110 &
#1435000
1#
#1440000
1#
b10000001 $
b10000001 '
b10001111 &
#1445000
0#
#1450000
0#
b100111 $
b100111 '
b10010000 &
#1455000
1#
#1460000
1#
b11111 $
b11111 '
b10010001 &
#1465000
0#
#1470000
1#
b1011000 $
b1011000 '
b10010010 &
#1475000
0#
#1480000
1#
b10100 $
b10100 '
b10010011 &
#1485000
0#
#1490000
0#
b10010110 $
b10010110 '
b10010100 &
#1495000
1#
#1500000
0#
b1010101 $
b1010101 '
b10010101 &
#1505000
1#
#1510000
0#
b101011 $
b101011 '
b10010110 &
#1515000
1#
#1520000
0#
b10101101 $
b10101101 '
b10010111 &
#1525000
1#
#1530000
0#
b10000100 $
b10000100 '
b10011000 &
#1535000
1#
#1540000
0#
b11100111 $
b11100111 '
b10011001 &
#1545000
1#
#1550000
0#
b1001001 $
b1001001 '
b10011010 &
#1555000
1#
#1560000
0#
b11001001 $
b11001001 '
b10011011 &
#1565000
1#
#1570000
1#
b10100001 $
b10100001 '
b10011100 &
#1575000
0#
#1580000
0#
b11111010 $
b11111010 '
b10011101 &
#1585000
1#
#1590000
1#
b10000011 $
b10000011 '
b10011110 &
#1595000
0#
#1600000
1#
b1110010 $
b1110010 '
b10011111 &
#1605000
0#
#1610000
0#
b1101000 $
b1101000 '
b10100000 &
#1615000
1#
#1620000
1#
b10000110 $
b10000110 '
b10100001 &
#1625000
0#
#1630000
1#
b111000 $
b111000 '
b10100010 &
#1635000
0#
#1640000
1#
b101000 $
b101000 '
b10100011 &
#1645000
0#
#1650000
1#
b11000101 $
b11000101 '
b10100100 &
#1655000
0#
#1660000
0#
b1110100 $
b1110100 '
b10100101 &
#1665000
1#
#1670000
1#
b10110000 $
b10110000 '
b10100110 &
#1675000
0#
#1680000
1#
b101010 $
b101010 '
b10100111 &
#1685000
0#
#1690000
0#
b10101 $
b10101 '
b10101000 &
#1695000
1#
#1700000
0#
b10111 $
b10111 '
b10101001 &
#1705000
1#
#1710000
1#
b11001001 $
b11001001 '
b10101010 &
#1715000
0#
#1720000
0#
b100101 $
b100101 '
b10101011 &
#1725000
1#
#1730000
1#
b10001101 $
b10001101 '
b10101100 &
#1735000
0#
#1740000
1#
b111 $
b111 '
b10101101 &
#1745000
0#
#1750000
0#
b1100 $
b1100 '
b10101110 &
#1755000
1#
#1760000
1#
b111011 $
b111011 '
b10101111 &
#1765000
0#
#1770000
1#
b11110111 $
b11110111 '
b10110000 &
#1775000
0#
#1780000
0#
b1011100 $
b1011100 '
b10110001 &
#1785000
1#
#1790000
1#
b100000 $
b100000 '
b10110010 &
#1795000
0#
#1800000
1#
b1110010 $
b1110010 '
b10110011 &
#1805000
0#
#1810000
0#
b11011101 $
b11011101 '
b10110100 &
#1815000
1#
#1820000
0#
b1001011 $
b1001011 '
b10110101 &
#1825000
1#
#1830000
0#
b10011110 $
b10011110 '
b10110110 &
#1835000
1#
#1840000
0#
b1111011 $
b1111011 '
b10110111 &
#1845000
1#
#1850000
0#
b11 $
b11 '
b10111000 &
#1855000
1#
#1860000
0#
b11101 $
b11101 '
b10111001 &
#1865000
1#
#1870000
0#
b1000100 $
b1000100 '
b10111010 &
#1875000
1#
#1880000
0#
b11100000 $
b11100000 '
b10111011 &
#1885000
1#
#1890000
1#
b1010010 $
b1010010 '
b10111100 &
#1895000
0#
#1900000
1#
b10001101 $
b10001101 '
b10111101 &
#1905000
0#
#1910000
1#
b10000100 $
b10000100 '
b10111110 &
#1915000
0#
#1920000
1#
b10001100 $
b10001100 '
b10111111 &
#1925000
0#
#1930000
1#
b10111 $
b10111 '
b11000000 &
#1935000
0#
#1940000
1#
b10000100 $
b10000100 '
b11000001 &
#1945000
0#
#1950000
1#
b1111100 $
b1111100 '
b11000010 &
#1955000
0#
#1960000
0#
b10111010 $
b10111010 '
b11000011 &
#1965000
1#
#1970000
0#
b10100110 $
b10100110 '
b11000100 &
#1975000
1#
#1980000
1#
b110010 $
b110010 '
b11000101 &
#1985000
0#
#1990000
1#
b1001001 $
b1001001 '
b11000110 &
#1995000
0#
#2000000
0#
b111101 $
b111101 '
b11000111 &
#2005000
1#
#2010000
0#
b1011100 $
b1011100 '
b11001000 &
#2015000
1#
#2020000
0#
b10000110 $
b10000110 '
b11001001 &
#2025000
1#
#2030000
1#
b10110100 $
b10110100 '
b11001010 &
#2035000
0#
#2040000
1#
b101100 $
b101100 '
b11001011 &
#2045000
0#
#2050000
1#
b111 $
b111 '
b11001100 &
#2055000
0#
#2060000
1#
b10001 $
b10001 '
b11001101 &
#2065000
0#
#2070000
0#
b1001011 $
b1001011 '
b11001110 &
#2075000
1#
#2080000
0#
b11101100 $
b11101100 '
b11001111 &
#2085000
1#
#2090000
0#
b10100100 $
b10100100 '
b11010000 &
#2095000
1#
#2100000
0#
b111001 $
b111001 '
b11010001 &
#2105000
1#
#2110000
0#
b11010100 $
b11010100 '
b11010010 &
#2115000
1#
#2120000
1#
b10011101 $
b10011101 '
b11010011 &
#2125000
0#
#2130000
0#
b10000010 $
b10000010 '
b11010100 &
#2135000
1#
#2140000
1#
b11011001 $
b11011001 '
b11010101 &
#2145000
0#
#2150000
0#
b11100 $
b11100 '
b11010110 &
#2155000
1#
#2160000
1#
b11100011 $
b11100011 '
b11010111 &
#2165000
0#
#2170000
0#
b11001000 $
b11001000 '
b11011000 &
#2175000
1#
#2180000
1#
b111010 $
b111010 '
b11011001 &
#2185000
0#
#2190000
0#
b101011 $
b101011 '
b11011010 &
#2195000
1#
#2200000
1#
b10010 $
b10010 '
b11011011 &
#2205000
0#
#2210000
1#
b1011001 $
b1011001 '
b11011100 &
#2215000
0#
#2220000
0#
b1101110 $
b1101110 '
b11011101 &
#2225000
1#
#2230000
1#
b11011011 $
b11011011 '
b11011110 &
#2235000
0#
#2240000
1#
b10111011 $
b10111011 '
b11011111 &
#2245000
0#
#2250000
0#
b1111 $
b1111 '
b11100000 &
#2255000
1#
#2260000
0#
b1100 $
b1100 '
b11100001 &
#2265000
1#
#2270000
0#
b11000101 $
b11000101 '
b11100010 &
#2275000
1#
#2280000
0#
b10010000 $
b10010000 '
b11100011 &
#2285000
1#
#2290000
0#
b1101001 $
b1101001 '
b11100100 &
#2295000
1#
#2300000
1#
b1001010 $
b1001010 '
b11100101 &
#2305000
0#
#2310000
1#
b10011011 $
b10011011 '
b11100110 &
#2315000
0#
#2320000
0#
b10111000 $
b10111000 '
b11100111 &
#2325000
1#
#2330000
1#
b10000110 $
b10000110 '
b11101000 &
#2335000
0#
#2340000
0#
b1110111 $
b1110111 '
b11101001 &
#2345000
1#
#2350000
0#
b11010100 $
b11010100 '
b11101010 &
#2355000
1#
#2360000
0#
b1110110 $
b1110110 '
b11101011 &
#2365000
1#
#2370000
0#
b10001011 $
b10001011 '
b11101100 &
#2375000
1#
#2380000
1#
b11011011 $
b11011011 '
b11101101 &
#2385000
0#
#2390000
0#
b11000010 $
b11000010 '
b11101110 &
#2395000
1#
#2400000
0#
b110000 $
b110000 '
b11101111 &
#2405000
1#
#2410000
0#
b1100110 $
b1100110 '
b11110000 &
#2415000
1#
#2420000
1#
b11101001 $
b11101001 '
b11110001 &
#2425000
0#
#2430000
0#
b110 $
b110 '
b11110010 &
#2435000
1#
#2440000
0#
b11100001 $
b11100001 '
b11110011 &
#2445000
1#
#2450000
1#
b11101110 $
b11101110 '
b11110100 &
#2455000
0#
#2460000
1#
b11100101 $
b11100101 '
b11110101 &
#2465000
0#
#2470000
0#
b1100100 $
b1100100 '
b11110110 &
#2475000
1#
#2480000
0#
b11100001 $
b11100001 '
b11110111 &
#2485000
1#
#2490000
0#
b1101110 $
b1101110 '
b11111000 &
#2495000
1#
#2500000
1#
b11010101 $
b11010101 '
b11111001 &
#2505000
0#
#2510000
1#
b11110000 $
b11110000 '
b11111010 &
#2515000
0#
#2520000
0#
b1111 $
b1111 '
b11111011 &
#2525000
1#
#2530000
1#
b1111101 $
b1111101 '
b11111100 &
#2535000
0#
#2540000
1#
b11100010 $
b11100010 '
b11111101 &
#2545000
0#
#2550000
0#
b10101001 $
b10101001 '
b11111110 &
#2555000
1#
#2560000
0#
b1011011 $
b1011011 '
b11111111 &
#2565000
1#
#2570000
0#
b1001010 $
b1001010 '
b100000000 &
#2575000
1#
#2580000
0#
b10011 $
b10011 '
b100000001 &
#2585000
1#
#2590000
0#
b1100101 $
b1100101 '
b100000010 &
#2595000
1#
#2600000
0#
b10110111 $
b10110111 '
b100000011 &
#2605000
1#
#2610000
0#
b111010 $
b111010 '
b100000100 &
#2615000
1#
#2620000
1#
b1100010 $
b1100010 '
b100000101 &
#2625000
0#
#2630000
0#
b101010 $
b101010 '
b100000110 &
#2635000
1#
#2640000
0#
b1011001 $
b1011001 '
b100000111 &
#2645000
1#
#2650000
0#
b11101101 $
b11101101 '
b100001000 &
#2655000
1#
#2660000
0#
b1000001 $
b1000001 '
b100001001 &
#2665000
1#
#2670000
0#
b11011011 $
b11011011 '
b100001010 &
#2675000
1#
#2680000
1#
b1110000 $
b1110000 '
b100001011 &
#2685000
0#
#2690000
0#
b10100010 $
b10100010 '
b100001100 &
#2695000
1#
#2700000
1#
b1101010 $
b1101010 '
b100001101 &
#2705000
0#
#2710000
0#
b1010000 $
b1010000 '
b100001110 &
#2715000
1#
#2720000
1#
b100101 $
b100101 '
b100001111 &
#2725000
0#
#2730000
1#
b11110110 $
b11110110 '
b100010000 &
#2735000
0#
#2740000
0#
b100011 $
b100011 '
b100010001 &
#2745000
1#
#2750000
0#
b11001000 $
b11001000 '
b100010010 &
#2755000
1#
#2760000
0#
b1110 $
b1110 '
b100010011 &
#2765000
1#
#2770000
1#
b1100 $
b1100 '
b100010100 &
#2775000
0#
#2780000
0#
b11010100 $
b11010100 '
b100010101 &
#2785000
1#
#2790000
0#
b10111001 $
b10111001 '
b100010110 &
#2795000
1#
#2800000
0#
b11110100 $
b11110100 '
b100010111 &
#2805000
1#
#2810000
0#
b1100 $
b1100 '
b100011000 &
#2815000
1#
#2820000
0#
b10 $
b10 '
b100011001 &
#2825000
1#
#2830000
1#
b101 $
b101 '
b100011010 &
#2835000
0#
#2840000
1#
b10 $
b10 '
b100011011 &
#2845000
0#
#2850000
0#
b1000 $
b1000 '
b100011100 &
#2855000
1#
#2860000
1#
b10101111 $
b10101111 '
b100011101 &
#2865000
0#
#2870000
0#
b10010000 $
b10010000 '
b100011110 &
#2875000
1#
#2880000
0#
b1001100 $
b1001100 '
b100011111 &
#2885000
1#
#2890000
0#
b1000000 $
b1000000 '
b100100000 &
#2895000
1#
#2900000
1#
b1101 $
b1101 '
b100100001 &
#2905000
0#
#2910000
0#
b101101 $
b101101 '
b100100010 &
#2915000
1#
#2920000
1#
b10111100 $
b10111100 '
b100100011 &
#2925000
0#
#2930000
1#
b11000000 $
b11000000 '
b100100100 &
#2935000
0#
#2940000
0#
b10100001 $
b10100001 '
b100100101 &
#2945000
1#
#2950000
0#
b11110101 $
b11110101 '
b100100110 &
#2955000
1#
#2960000
1#
b1011101 $
b1011101 '
b100100111 &
#2965000
0#
#2970000
1#
b1101010 $
b1101010 '
b100101000 &
#2975000
0#
#2980000
1#
b10111000 $
b10111000 '
b100101001 &
#2985000
0#
#2990000
1#
b11111010 $
b11111010 '
b100101010 &
#2995000
0#
#3000000
0#
b111 $
b111 '
b100101011 &
#3005000
1#
#3010000
0#
b1010101 $
b1010101 '
b100101100 &
#3015000
1#
#3020000
0#
b1000101 $
b1000101 '
b100101101 &
#3025000
1#
#3030000
1#
b1011001 $
b1011001 '
b100101110 &
#3035000
0#
#3040000
1#
b1101000 $
b1101000 '
b100101111 &
#3045000
0#
#3050000
1#
b10010000 $
b10010000 '
b100110000 &
#3055000
0#
#3060000
0#
b11100 $
b11100 '
b100110001 &
#3065000
1#
#3070000
1#
b10101011 $
b10101011 '
b100110010 &
#3075000
0#
#3080000
1#
b1101111 $
b1101111 '
b100110011 &
#3085000
0#
#3090000
0#
b1000101 $
b1000101 '
b100110100 &
#3095000
1#
#3100000
1#
b10001011 $
b10001011 '
b100110101 &
#3105000
0#
#3110000
1#
b11011100 $
b11011100 '
b100110110 &
#3115000
0#
#3120000
0#
b11001 $
b11001 '
b100110111 &
#3125000
1#
#3130000
0#
b111110 $
b111110 '
b100111000 &
#3135000
1#
#3140000
1#
b1011000 $
b1011000 '
b100111001 &
#3145000
0#
#3150000
1#
b1011100 $
b1011100 '
b100111010 &
#3155000
0#
#3160000
1#
b10011010 $
b10011010 '
b100111011 &
#3165000
0#
#3170000
1#
b11000101 $
b11000101 '
b100111100 &
#3175000
0#
#3180000
0#
b11010 $
b11010 '
b100111101 &
#3185000
1#
#3190000
1#
b10110010 $
b10110010 '
b100111110 &
#3195000
0#
#3200000
0#
b11101001 $
b11101001 '
b100111111 &
#3205000
1#
#3210000
1#
b11101011 $
b11101011 '
b101000000 &
#3215000
0#
#3220000
0#
b11110010 $
b11110010 '
b101000001 &
#3225000
1#
#3230000
0#
b1101111 $
b1101111 '
b101000010 &
#3235000
1#
#3240000
1#
b10101101 $
b10101101 '
b101000011 &
#3245000
0#
#3250000
0#
b100101 $
b100101 '
b101000100 &
#3255000
1#
#3260000
0#
b10101011 $
b10101011 '
b101000101 &
#3265000
1#
#3270000
0#
b10000000 $
b10000000 '
b101000110 &
#3275000
1#
#3280000
1#
b10000010 $
b10000010 '
b101000111 &
#3285000
0#
#3290000
1#
b1010111 $
b1010111 '
b101001000 &
#3295000
0#
#3300000
0#
b110010 $
b110010 '
b101001001 &
#3305000
1#
#3310000
1#
b11100100 $
b11100100 '
b101001010 &
#3315000
0#
#3320000
1#
b10101010 $
b10101010 '
b101001011 &
#3325000
0#
#3330000
1#
b101110 $
b101110 '
b101001100 &
#3335000
0#
#3340000
0#
b1110001 $
b1110001 '
b101001101 &
#3345000
1#
#3350000
1#
b10111100 $
b10111100 '
b101001110 &
#3355000
0#
#3360000
0#
b10111 $
b10111 '
b101001111 &
#3365000
1#
#3370000
0#
b11101011 $
b11101011 '
b101010000 &
#3375000
1#
#3380000
0#
b10001001 $
b10001001 '
b101010001 &
#3385000
1#
#3390000
1#
b10111111 $
b10111111 '
b101010010 &
#3395000
0#
#3400000
1#
b11010011 $
b11010011 '
b101010011 &
#3405000
0#
#3410000
1#
b10000010 $
b10000010 '
b101010100 &
#3415000
0#
#3420000
0#
b1110001 $
b1110001 '
b101010101 &
#3425000
1#
#3430000
0#
b1110 $
b1110 '
b101010110 &
#3435000
1#
#3440000
0#
b11001101 $
b11001101 '
b101010111 &
#3445000
1#
#3450000
1#
b11100 $
b11100 '
b101011000 &
#3455000
0#
#3460000
1#
b11101100 $
b11101100 '
b101011001 &
#3465000
0#
#3470000
0#
b1100101 $
b1100101 '
b101011010 &
#3475000
1#
#3480000
1#
b11 $
b11 '
b101011011 &
#3485000
0#
#3490000
1#
b11111101 $
b11111101 '
b101011100 &
#3495000
0#
#3500000
1#
b11101000 $
b11101000 '
b101011101 &
#3505000
0#
#3510000
1#
b10110000 $
b10110000 '
b101011110 &
#3515000
0#
#3520000
1#
b10010 $
b10010 '
b101011111 &
#3525000
0#
#3530000
1#
b11000101 $
b11000101 '
b101100000 &
#3535000
0#
#3540000
0#
b110110 $
b110110 '
b101100001 &
#3545000
1#
#3550000
0#
b11111011 $
b11111011 '
b101100010 &
#3555000
1#
#3560000
0#
b10111 $
b10111 '
b101100011 &
#3565000
1#
#3570000
1#
b10100 $
b10100 '
b101100100 &
#3575000
0#
#3580000
1#
b10100110 $
b10100110 '
b101100101 &
#3585000
0#
#3590000
0#
b11001011 $
b11001011 '
b101100110 &
#3595000
1#
#3600000
1#
b100 $
b100 '
b101100111 &
#3605000
0#
#3610000
0#
b10001101 $
b10001101 '
b101101000 &
#3615000
1#
#3620000
0#
b10000101 $
b10000101 '
b101101001 &
#3625000
1#
#3630000
1#
b11001001 $
b11001001 '
b101101010 &
#3635000
0#
#3640000
1#
b1000110 $
b1000110 '
b101101011 &
#3645000
0#
#3650000
1#
b110111 $
b110111 '
b101101100 &
#3655000
0#
#3660000
1#
b1110011 $
b1110011 '
b101101101 &
#3665000
0#
#3670000
1#
b11011100 $
b11011100 '
b101101110 &
#3675000
0#
#3680000
1#
b11010000 $
b11010000 '
b101101111 &
#3685000
0#
#3690000
1#
b1000011 $
b1000011 '
b101110000 &
#3695000
0#
#3700000
0#
b10100001 $
b10100001 '
b101110001 &
#3705000
1#
#3710000
0#
b10011000 $
b10011000 '
b101110010 &
#3715000
1#
#3720000
1#
b10000111 $
b10000111 '
b101110011 &
#3725000
0#
#3730000
1#
b101101 $
b101101 '
b101110100 &
#3735000
0#
#3740000
0#
b1101011 $
b1101011 '
b101110101 &
#3745000
1#
#3750000
1#
b10010 $
b10010 '
b101110110 &
#3755000
0#
#3760000
0#
b1101 $
b1101 '
b101110111 &
#3765000
1#
#3770000
1#
b1000000 $
b1000000 '
b101111000 &
#3775000
0#
#3780000
1#
b1010100 $
b1010100 '
b101111001 &
#3785000
0#
#3790000
0#
b10011 $
b10011 '
b101111010 &
#3795000
1#
#3800000
1#
b11101101 $
b11101101 '
b101111011 &
#3805000
0#
#3810000
0#
b1111000 $
b1111000 '
b101111100 &
#3815000
1#
#3820000
0#
b1011111 $
b1011111 '
b101111101 &
#3825000
1#
