RTL/case1/case1.v
module case1 (
    input [7:0] in,
    output reg [7:0] out,
    input clk,
    input rst
);

  reg  [3:0] state;
  wire [3:0] st;
  wire [3:0] st2;

  assign st  = state + 4'd2;
  assign st2 = st;

  always @(posedge clk) begin
    if (rst) begin
      state <= 4'h0;
	    $display("2,1,1");
    end else if (in == 8'h26) begin
      state <= 4'h1;
      $display("2,1,0,1");
    end else if (in == 8'hf5 && state == 4'h1) begin
      state <= 4'h2;
      $display("2,1,0,0,1");
    end else if (in == 8'h6e && state == 4'h2) begin
      state <= 4'h3;
      $display("2,1,0,0,0,1");
      //$display("Hooray");
    end else begin
      state <= 0;
      $display("2,1,0,0,0,0");
    end
  end

  always @(posedge clk) begin
    if (rst) begin
      out <= 8'b0;
	    $display("3,1,1");
    end else if (st2 == 4'h5) begin
      $display("3,1,0,1: Target reached");
      out <= 1;
    end else
	    $display("3,1,0,0");
  end


endmodule

RTL/case1/case1_tb.v
module case1_tb();

    // Generated top module signals
    reg  clk;
    reg  rst;
    reg  [7:0]in = 8'b0;


    wire [7:0]out;

    // Generated top module instance
    case1 _conc_top_inst(
            .clk     ( clk ),
            .rst     ( rst ),
            .in     ( in ),

            .out     ( out ));

    // Generated clk pulse
    always begin
        #5 clk = ~clk;
    end
    integer i, seed;
    // Generated initial block
    initial begin
        clk = 1'b0;
        rst = 1'b0;
        in = 8'b0;


        #2 clk = 1'b1;
        rst = 1'b1;
        #5 rst = 1'b0;

        #1 in = 8'h26;
        #9;
        $display("Period 0: in = %b, out = %b", in, out);

        #1 in = 8'hf5;
        #9;
        $display("Period 1: in = %b, out = %b", in, out);

        #1 in = 8'h6e;
        #9;
        $display("Period 2: in = %b, out = %b", in, out);        

        for(i= 3; i<20; i++) begin
            #1;
            in = $random(seed);

            #9;
            $display("Period %d: in = %b, out = %b", i, in, out);
        end


        $finish;
    end

    initial
    begin            
        $dumpfile("wave.vcd");        //生成的vcd文件名称
        $dumpvars(0, case1_tb);    //tb模块名称
    end 
endmodule

RTL/case1/wave.vcd
$date
	Thu Dec 12 15:50:32 2024
$end
$version
	Icarus Verilog
$end
$timescale
	1s
$end
$scope module case1_tb $end
$var wire 8 ! out [7:0] $end
$var reg 1 " clk $end
$var reg 8 # in [7:0] $end
$var reg 1 $ rst $end
$var integer 32 % i [31:0] $end
$var integer 32 & seed [31:0] $end
$scope module _conc_top_inst $end
$var wire 1 " clk $end
$var wire 8 ' in [7:0] $end
$var wire 1 $ rst $end
$var wire 4 ( st2 [3:0] $end
$var wire 4 ) st [3:0] $end
$var reg 8 * out [7:0] $end
$var reg 4 + state [3:0] $end
$upscope $end
$upscope $end
$enddefinitions $end
$comment Show the parameter values. $end
$dumpall
$end
#0
$dumpvars
bx +
bx *
bx )
bx (
b0 '
bx &
bx %
0$
b0 #
0"
bx !
$end
#2
b10 (
b10 )
b0 +
b0 !
b0 *
1$
1"
#5
0"
#7
0$
#8
b100110 #
b100110 '
#10
b11 (
b11 )
b1 +
1"
#15
0"
#18
b11110101 #
b11110101 '
#20
b100 (
b100 )
b10 +
1"
#25
0"
#28
b1101110 #
b1101110 '
#30
b101 (
b101 )
b11 +
1"
#35
0"
#37
b11 %
#38
b100100 #
b100100 '
b10010010000101010011001000000110 &
#40
b10 (
b10 )
b0 +
b1 !
b1 *
1"
#45
0"
#47
b100 %
#48
b10000001 #
b10000001 '
b1000000100010010101110011001111 &
#50
1"
#55
0"
#57
b101 %
#58
b1001 #
b1001 '
b100100001001101010011000100 &
#60
1"
#65
0"
#67
b110 %
#68
b1100011 #
b1100011 '
b110001111100000101010011110101 &
#70
1"
#75
0"
#77
b111 %
#78
b1101 #
b1101 '
b10000110101110010111100100110010 &
#80
1"
#85
0"
#87
b1000 %
#88
b10001101 #
b10001101 '
b11000110110111111001011100001011 &
#90
1"
#95
0"
#97
b1001 %
#98
b1100101 #
b1100101 '
b110010110000101000001011010000 &
#100
1"
#105
0"
#107
b1010 %
#108
b10010 #
b10010 '
b1001001101110101000010010001 &
#110
1"
#115
0"
#117
b1011 %
#118
b1 #
b1 '
b10000000111100111110000100011110 &
#120
1"
#125
0"
#127
b1100 %
#128
b1101 #
b1101 '
b10000110110101111100101100000111 &
#130
1"
#135
0"
#137
b1101 %
#138
b1110110 #
b1110110 '
b10111011001000111110111110011100 &
#140
1"
#145
0"
#147
b1110 %
#148
b111101 #
b111101 '
b10011110100011011100101111101101 &
#150
1"
#155
0"
#157
b1111 %
#158
b11101101 #
b11101101 '
b11110110110101000101010111001010 &
#160
1"
#165
0"
#167
b10000 %
#168
b10001100 #
b10001100 '
b11000110001011011111010011000011 &
#170
1"
#175
0"
#177
b10001 %
#178
b11111001 #
b11111001 '
b11111100111111011110011100101000 &
#180
1"
#185
0"
#187
b10010 %
#188
b11000110 #
b11000110 '
b1100011001101110010001100001001 &
#190
1"
#195
0"
#197
b10011 %
#198
b11000101 #
b11000101 '
b1100010111101111000001100110110 &
#200
1"
#205
0"
#207
b10100 %
