RTL/case1/case1_1.v
module case1 (
    input wire [7:0] in,
    output reg [7:0] out,
    input wire clk,
    input rst
);

  reg  [3:0] state;
  wire [3:0] st;
  wire [3:0] st2;

  assign st  = state + 4'd2;
  assign st2 = st;

  always @(posedge clk) begin
    if (rst) begin
      state <= 4'h0;
    end else if (in == 8'h26) begin
      state <= 4'h1;
    end else if (in == 8'hf5 && state == 4'h1) begin
      state <= 4'h2;
    end else if (in == 8'h6e && state == 4'h2) begin
      state <= 4'h3;
    end else begin
      state <= 0;
    end
  end

  always @(posedge clk) begin
    if (rst) begin
      out <= 8'b0;
    end else if (st2 == 4'h5) begin
      out <= 1;
    end
  end


endmodule

RTL/case1/case1_tb.v
`timescale 1ns/1ps
module case1_tb();
reg [7:0] in;
wire [7:0] out;
reg clk;
reg rst;

// 实例化待测模块
case1 uut (
    .in(in),
    .out(out),
    .clk(clk),
    .rst(rst)
    );

// 时钟激励
initial begin
    clk = 0;
    forever #5 clk = ~clk;
end

// 复位激励
initial begin
    rst = 1;
    #20;
    rst = 0;
end

integer i;
initial begin
    in = 0;
    #10;
    for(i = 0; i < 100; i = i + 1) begin
        $display("********Period %d********", i);
        in = $random & 8'd255;
        #10;
    end
    $finish;
end
initial begin
    $dumpfile("wave.vcd");
    $dumpvars(0, case1_tb);
end

endmodule

RTL/case1/wave.vcd
$date
	Tue Apr 01 15:04:37 2025
$end
$version
	Icarus Verilog
$end
$timescale
	1ps
$end
$scope module case1_tb $end
$var wire 8 ! out [7:0] $end
$var reg 1 " clk $end
$var reg 8 # in [7:0] $end
$var reg 1 $ rst $end
$var integer 32 % i [31:0] $end
$scope module uut $end
$var wire 1 " clk $end
$var wire 8 & in [7:0] $end
$var wire 1 $ rst $end
$var wire 4 ' st2 [3:0] $end
$var wire 4 ( st [3:0] $end
$var reg 8 ) out [7:0] $end
$var reg 4 * state [3:0] $end
$upscope $end
$upscope $end
$enddefinitions $end
$comment Show the parameter values. $end
$dumpall
$end
#0
$dumpvars
bx *
bx )
bx (
bx '
b0 &
bx %
1$
b0 #
0"
bx !
$end
#5000
b10 '
b10 (
b0 *
b0 !
b0 )
1"
#10000
0"
b100100 #
b100100 &
b0 %
#15000
1"
#20000
0"
b10000001 #
b10000001 &
b1 %
0$
#25000
1"
#30000
0"
b1001 #
b1001 &
b10 %
#35000
1"
#40000
0"
b1100011 #
b1100011 &
b11 %
#45000
1"
#50000
0"
b1101 #
b1101 &
b100 %
#55000
1"
#60000
0"
b10001101 #
b10001101 &
b101 %
#65000
1"
#70000
0"
b1100101 #
b1100101 &
b110 %
#75000
1"
#80000
0"
b10010 #
b10010 &
b111 %
#85000
1"
#90000
0"
b1 #
b1 &
b1000 %
#95000
1"
#100000
0"
b1101 #
b1101 &
b1001 %
#105000
1"
#110000
0"
b1110110 #
b1110110 &
b1010 %
#115000
1"
#120000
0"
b111101 #
b111101 &
b1011 %
#125000
1"
#130000
0"
b11101101 #
b11101101 &
b1100 %
#135000
1"
#140000
0"
b10001100 #
b10001100 &
b1101 %
#145000
1"
#150000
0"
b11111001 #
b11111001 &
b1110 %
#155000
1"
#160000
0"
b11000110 #
b11000110 &
b1111 %
#165000
1"
#170000
0"
b11000101 #
b11000101 &
b10000 %
#175000
1"
#180000
0"
b10101010 #
b10101010 &
b10001 %
#185000
1"
#190000
0"
b11100101 #
b11100101 &
b10010 %
#195000
1"
#200000
0"
b1110111 #
b1110111 &
b10011 %
#205000
1"
#210000
0"
b10010 #
b10010 &
b10100 %
#215000
1"
#220000
0"
b10001111 #
b10001111 &
b10101 %
#225000
1"
#230000
0"
b11110010 #
b11110010 &
b10110 %
#235000
1"
#240000
0"
b11001110 #
b11001110 &
b10111 %
#245000
1"
#250000
0"
b11101000 #
b11101000 &
b11000 %
#255000
1"
#260000
0"
b11000101 #
b11000101 &
b11001 %
#265000
1"
#270000
0"
b1011100 #
b1011100 &
b11010 %
#275000
1"
#280000
0"
b10111101 #
b10111101 &
b11011 %
#285000
1"
#290000
0"
b101101 #
b101101 &
b11100 %
#295000
1"
#300000
0"
b1100101 #
b1100101 &
b11101 %
#305000
1"
#310000
0"
b1100011 #
b1100011 &
b11110 %
#315000
1"
#320000
0"
b1010 #
b1010 &
b11111 %
#325000
1"
#330000
0"
b10000000 #
b10000000 &
b100000 %
#335000
1"
#340000
0"
b100000 #
b100000 &
b100001 %
#345000
1"
#350000
0"
b10101010 #
b10101010 &
b100010 %
#355000
1"
#360000
0"
b10011101 #
b10011101 &
b100011 %
#365000
1"
#370000
0"
b10010110 #
b10010110 &
b100100 %
#375000
1"
#380000
0"
b10011 #
b10011 &
b100101 %
#385000
1"
#390000
0"
b1101 #
b1101 &
b100110 %
#395000
1"
#400000
0"
b1010011 #
b1010011 &
b100111 %
#405000
1"
#410000
0"
b1101011 #
b1101011 &
b101000 %
#415000
1"
#420000
0"
b11010101 #
b11010101 &
b101001 %
#425000
1"
#430000
0"
b10 #
b10 &
b101010 %
#435000
1"
#440000
0"
b10101110 #
b10101110 &
b101011 %
#445000
1"
#450000
0"
b11101 #
b11101 &
b101100 %
#455000
1"
#460000
0"
b11001111 #
b11001111 &
b101101 %
#465000
1"
#470000
0"
b100011 #
b100011 &
b101110 %
#475000
1"
#480000
0"
b1010 #
b1010 &
b101111 %
#485000
1"
#490000
0"
b11001010 #
b11001010 &
b110000 %
#495000
1"
#500000
0"
b111100 #
b111100 &
b110001 %
#505000
1"
#510000
0"
b11110010 #
b11110010 &
b110010 %
#515000
1"
#520000
0"
b10001010 #
b10001010 &
b110011 %
#525000
1"
#530000
0"
b1000001 #
b1000001 &
b110100 %
#535000
1"
#540000
0"
b11011000 #
b11011000 &
b110101 %
#545000
1"
#550000
0"
b1111000 #
b1111000 &
b110110 %
#555000
1"
#560000
0"
b10001001 #
b10001001 &
b110111 %
#565000
1"
#570000
0"
b11101011 #
b11101011 &
b111000 %
#575000
1"
#580000
0"
b10110110 #
b10110110 &
b111001 %
#585000
1"
#590000
0"
b11000110 #
b11000110 &
b111010 %
#595000
1"
#600000
0"
b10101110 #
b10101110 &
b111011 %
#605000
1"
#610000
0"
b10111100 #
b10111100 &
b111100 %
#615000
1"
#620000
0"
b101010 #
b101010 &
b111101 %
#625000
1"
#630000
0"
b1011 #
b1011 &
b111110 %
#635000
1"
#640000
0"
b1110001 #
b1110001 &
b111111 %
#645000
1"
#650000
0"
b10000101 #
b10000101 &
b1000000 %
#655000
1"
#660000
0"
b1001111 #
b1001111 &
b1000001 %
#665000
1"
#670000
0"
b111011 #
b111011 &
b1000010 %
#675000
1"
#680000
0"
b111010 #
b111010 &
b1000011 %
#685000
1"
#690000
0"
b1111110 #
b1111110 &
b1000100 %
#695000
1"
#700000
0"
b10101 #
b10101 &
b1000101 %
#705000
1"
#710000
0"
b11110001 #
b11110001 &
b1000110 %
#715000
1"
#720000
0"
b11011001 #
b11011001 &
b1000111 %
#725000
1"
#730000
0"
b1100010 #
b1100010 &
b1001000 %
#735000
1"
#740000
0"
b1001100 #
b1001100 &
b1001001 %
#745000
1"
#750000
0"
b10011111 #
b10011111 &
b1001010 %
#755000
1"
#760000
0"
b10001111 #
b10001111 &
b1001011 %
#765000
1"
#770000
0"
b11111000 #
b11111000 &
b1001100 %
#775000
1"
#780000
0"
b10110111 #
b10110111 &
b1001101 %
#785000
1"
#790000
0"
b10011111 #
b10011111 &
b1001110 %
#795000
1"
#800000
0"
b1011100 #
b1011100 &
b1001111 %
#805000
1"
#810000
0"
b1011011 #
b1011011 &
b1010000 %
#815000
1"
#820000
0"
b10001001 #
b10001001 &
b1010001 %
#825000
1"
#830000
0"
b1001001 #
b1001001 &
b1010010 %
#835000
1"
#840000
0"
b11010000 #
b11010000 &
b1010011 %
#845000
1"
#850000
0"
b11010111 #
b11010111 &
b1010100 %
#855000
1"
#860000
0"
b1010001 #
b1010001 &
b1010101 %
#865000
1"
#870000
0"
b10010110 #
b10010110 &
b1010110 %
#875000
1"
#880000
0"
b1100 #
b1100 &
b1010111 %
#885000
1"
#890000
0"
b11000010 #
b11000010 &
b1011000 %
#895000
1"
#900000
0"
b11001000 #
b11001000 &
b1011001 %
#905000
1"
#910000
0"
b1110111 #
b1110111 &
b1011010 %
#915000
1"
#920000
0"
b111101 #
b111101 &
b1011011 %
#925000
1"
#930000
0"
b10010 #
b10010 &
b1011100 %
#935000
1"
#940000
0"
b1111110 #
b1111110 &
b1011101 %
#945000
1"
#950000
0"
b1101101 #
b1101101 &
b1011110 %
#955000
1"
#960000
0"
b111001 #
b111001 &
b1011111 %
#965000
1"
#970000
0"
b11111 #
b11111 &
b1100000 %
#975000
1"
#980000
0"
b11010011 #
b11010011 &
b1100001 %
#985000
1"
#990000
0"
b10000101 #
b10000101 &
b1100010 %
#995000
1"
#1000000
0"
b1111000 #
b1111000 &
b1100011 %
#1005000
1"
#1010000
0"
b1100100 %
