RTL/core/csr_reg/csr_reg_1.v
/*                                                                      
 Copyright 2020 Blue Liang, liangkangnan@163.com
                                                                         
 Licensed under the Apache License, Version 2.0 (the "License");         
 you may not use this file except in compliance with the License.        
 You may obtain a copy of the License at                                 
                                                                         
     http://www.apache.org/licenses/LICENSE-2.0                          
                                                                         
 Unless required by applicable law or agreed to in writing, software    
 distributed under the License is distributed on an "AS IS" BASIS,       
 WITHOUT WARRANTIES OR CONDITIONS OF ANY KIND, either express or implied.
 See the License for the specific language governing permissions and     
 limitations under the License.                                          
 */

// CSR寄存器模块
module csr_reg_1 (

    input wire clk,
    input wire rst,

    // form ex
    input wire        we_i,     // ex模块写寄存器标志
    input wire [31:0] raddr_i,  // ex模块读寄存器地址
    input wire [31:0] waddr_i,  // ex模块写寄存器地址
    input wire [31:0] data_i,   // ex模块写寄存器数据

    // from clint
    input wire        clint_we_i,     // clint模块写寄存器标志
    input wire [31:0] clint_raddr_i,  // clint模块读寄存器地址
    input wire [31:0] clint_waddr_i,  // clint模块写寄存器地址
    input wire [31:0] clint_data_i,   // clint模块写寄存器数据

    output wire global_int_en_o,  // 全局中断使能标志

    // to clint
    output reg  [31:0] clint_data_o,      // clint模块读寄存器数据
    output wire [31:0] clint_csr_mtvec,   // mtvec
    output wire [31:0] clint_csr_mepc,    // mepc
    output wire [31:0] clint_csr_mstatus, // mstatus

    // to ex
    output reg [31:0] data_o  // ex模块读寄存器数据

);

  reg [63:0] cycle;
  reg [31:0] mtvec;
  reg [31:0] mcause;
  reg [31:0] mepc;
  reg [31:0] mie;
  reg [31:0] mstatus;
  reg [31:0] mscratch;

  assign global_int_en_o = (mstatus[3] == 1'b1) ? 1'b1 : 1'b0;
  always @(*) begin
    if (mstatus[3] == 1'b1) begin
        $display("0,0,1");
    end
    else begin
        $display("0,0,0");
    end
  end
  assign clint_csr_mtvec = mtvec;
  assign clint_csr_mepc = mepc;
  assign clint_csr_mstatus = mstatus;


  always @(posedge clk) begin
    if (rst == 1'b0) begin
      cycle <= {32'h0, 32'h0};
      $display("4,1,1");
    end else begin
      cycle <= cycle + 1'b1;
      $display("4,1,0");
    end
  end

  // write reg
  // 写寄存器操作
  always @(posedge clk) begin
    if (rst == 1'b0) begin
      mtvec <= 32'h0;
      mcause <= 32'h0;
      mepc <= 32'h0;
      mie <= 32'h0;
      mstatus <= 32'h0;
      mscratch <= 32'h0;
      $display("5,1,1");
    end else begin
      // 优先响应ex模块的写操作
      if (we_i == 1'b1) begin
        case (waddr_i[11:0])
          12'h305: begin
            mtvec <= data_i;
            $display("5,1,0,1,1");
          end
          12'h342: begin
            mcause <= data_i;
            $display("5,1,0,1,2");
          end
          12'h341: begin
            mepc <= data_i;
            $display("5,1,0,1,3");
          end
          12'h304: begin
            mie <= data_i;
            $display("5,1,0,1,4");
          end
          12'h300: begin
            mstatus <= data_i;
            $display("5,1,0,1,5");
          end
          12'h340: begin
            mscratch <= data_i;
            $display("5,1,0,1,6");
          end
          default: begin
            $display("5,1,0,1,7");
          end
        endcase
        // clint模块写操作
      end else if (clint_we_i == 1'b1) begin
        case (clint_waddr_i[11:0])
          12'h305: begin
            mtvec <= clint_data_i;
            $display("5,1,0,0,1,1");
          end
          12'h342: begin
            mcause <= clint_data_i;
            $display("5,1,0,0,1,2");
          end
          12'h341: begin
            mepc <= clint_data_i;
            $display("5,1,0,0,1,3");
          end
          12'h304: begin
            mie <= clint_data_i;
            $display("5,1,0,0,1,4");
          end
          12'h300: begin
            mstatus <= clint_data_i;
            $display("5,1,0,0,1,5");
          end
          12'h340: begin
            mscratch <= clint_data_i;
            $display("5,1,0,0,1,6");
          end
          default: begin
            $display("5,1,0,0,1,7");
          end
        endcase
      end
    end
  end

  // read reg
  // ex模块读CSR寄存器
  always @(*) begin
    if ((waddr_i[11:0] == raddr_i[11:0]) && (we_i == 1'b1)) begin
      data_o = data_i;
      $display("6,0,1");
    end else begin
      case (raddr_i[11:0])
        12'hc00: begin
          data_o = cycle[31:0];
          $display("6,0,0,1");
        end
        12'hc80: begin
          data_o = cycle[63:32];
          $display("6,0,0,2");
        end
        12'h305: begin
          data_o = mtvec;
          $display("6,0,0,3");
        end
        12'h342: begin
          data_o = mcause;
          $display("6,0,0,4");
        end
        12'h341: begin
          data_o = mepc;
          $display("6,0,0,5");
        end
        12'h304: begin
          data_o = mie;
          $display("6,0,0,6");
        end
        12'h300: begin
          data_o = mstatus;
          $display("6,0,0,7");
        end
        12'h340: begin
          data_o = mscratch;
          $display("6,0,0,8");
        end
        default: begin
            data_o = 32'h0;
            $display("6,0,0,9");
        end
      endcase
    end
  end

  // read reg
  // clint模块读CSR寄存器
  always @(*) begin
    if ((clint_waddr_i[11:0] == clint_raddr_i[11:0]) && (clint_we_i == 1'b1)) begin
      clint_data_o = clint_data_i;
      $display("7,0,1");
    end else begin
      case (clint_raddr_i[11:0])
        12'hc00: begin
          clint_data_o = cycle[31:0];
          $display("7,0,0,1");
        end
        12'hc80: begin
          clint_data_o = cycle[63:32];
          $display("7,0,0,2");
        end
        12'h305: begin
          clint_data_o = mtvec;
          $display("7,0,0,3");
        end
        12'h342: begin
          clint_data_o = mcause;
          $display("7,0,0,4");
        end
        12'h341: begin
          clint_data_o = mepc;
          $display("7,0,0,5");
        end
        12'h304: begin
          clint_data_o = mie;
          $display("7,0,0,6");
        end
        12'h300: begin
          clint_data_o = mstatus;
          $display("7,0,0,7");
        end
        12'h340: begin
          clint_data_o = mscratch;
          $display("7,0,0,8");
        end
        default: begin
            clint_data_o = 32'h0;
            $display("7,0,0,9");
        end
      endcase
    end
  end

endmodule

RTL/core/csr_reg/csr_reg_1_tb.v
//~ `New testbench
`timescale  1ns / 1ps

module tb_csr_reg;

// csr_reg Parameters
parameter PERIOD  = 10;


// csr_reg Inputs
reg   clk                                  = 0 ;
reg   rst                                  = 0 ;
reg   we_i                                 = 0 ;
reg   [31:0]  raddr_i                      = 0 ;
reg   [31:0]  waddr_i                      = 0 ;
reg   [31:0]  data_i                       = 0 ;
reg   clint_we_i                           = 0 ;
reg   [31:0]  clint_raddr_i                = 0 ;
reg   [31:0]  clint_waddr_i                = 0 ;
reg   [31:0]  clint_data_i                 = 0 ;

// csr_reg Outputs
wire  global_int_en_o                      ;
wire  [31:0]  clint_data_o                 ;
wire  [31:0]  clint_csr_mtvec              ;
wire  [31:0]  clint_csr_mepc               ;
wire  [31:0]  clint_csr_mstatus            ;
wire  [31:0]  data_o                       ;


initial
begin
    forever #(PERIOD/2)  clk=~clk;
end

initial
begin
    #(PERIOD*2) rst  =  1;
end

csr_reg_1  u_csr_reg (
    .clk                     ( clk                       ),
    .rst                     ( rst                       ),
    .we_i                    ( we_i                      ),
    .raddr_i                 ( raddr_i            [31:0] ),
    .waddr_i                 ( waddr_i            [31:0] ),
    .data_i                  ( data_i             [31:0] ),
    .clint_we_i              ( clint_we_i                ),
    .clint_raddr_i           ( clint_raddr_i      [31:0] ),
    .clint_waddr_i           ( clint_waddr_i      [31:0] ),
    .clint_data_i            ( clint_data_i       [31:0] ),

    .global_int_en_o         ( global_int_en_o           ),
    .clint_data_o            ( clint_data_o       [31:0] ),
    .clint_csr_mtvec         ( clint_csr_mtvec    [31:0] ),
    .clint_csr_mepc          ( clint_csr_mepc     [31:0] ),
    .clint_csr_mstatus       ( clint_csr_mstatus  [31:0] ),
    .data_o                  ( data_o             [31:0] )
);

integer i;
initial begin
    we_i = 0;
    raddr_i = 0;
    waddr_i = 0;
    data_i = 0;
    clint_we_i = 0;
    clint_raddr_i = 0;
    clint_waddr_i = 0;
    clint_data_i = 0;
    #10;

    for(i = 0; i < 20; i = i + 1) begin
        #8;
        $display("Period %d", i);
        we_i = $random & 1'd1;
        raddr_i = $random;
        waddr_i = $random;
        data_i = $random;
        clint_we_i = $random & 1'd1;
        clint_raddr_i = $random;
        clint_waddr_i = $random;
        clint_data_i = $random;
        #2;
    end

    $display("Period 20");
    $finish;
end

initial
begin            
    $dumpfile("wave.vcd");        //生成的vcd文件名称
    $dumpvars(0, tb_csr_reg);    //tb模块名称
end 
endmodule

RTL/core/csr_reg/wave.vcd
$date
	Wed Feb 19 15:10:16 2025
$end
$version
	Icarus Verilog
$end
$timescale
	1ps
$end
$scope module tb_csr_reg $end
$var wire 1 ! global_int_en_o $end
$var wire 32 " data_o [31:0] $end
$var wire 32 # clint_data_o [31:0] $end
$var wire 32 $ clint_csr_mtvec [31:0] $end
$var wire 32 % clint_csr_mstatus [31:0] $end
$var wire 32 & clint_csr_mepc [31:0] $end
$var parameter 32 ' PERIOD $end
$var reg 32 ( clint_data_i [31:0] $end
$var reg 32 ) clint_raddr_i [31:0] $end
$var reg 32 * clint_waddr_i [31:0] $end
$var reg 1 + clint_we_i $end
$var reg 1 , clk $end
$var reg 32 - data_i [31:0] $end
$var reg 32 . raddr_i [31:0] $end
$var reg 1 / rst $end
$var reg 32 0 waddr_i [31:0] $end
$var reg 1 1 we_i $end
$var integer 32 2 i [31:0] $end
$scope module u_csr_reg $end
$var wire 32 3 clint_csr_mepc [31:0] $end
$var wire 32 4 clint_csr_mstatus [31:0] $end
$var wire 32 5 clint_csr_mtvec [31:0] $end
$var wire 32 6 clint_data_i [31:0] $end
$var wire 32 7 clint_raddr_i [31:0] $end
$var wire 32 8 clint_waddr_i [31:0] $end
$var wire 1 + clint_we_i $end
$var wire 1 , clk $end
$var wire 32 9 data_i [31:0] $end
$var wire 32 : raddr_i [31:0] $end
$var wire 1 / rst $end
$var wire 32 ; waddr_i [31:0] $end
$var wire 1 1 we_i $end
$var wire 1 ! global_int_en_o $end
$var reg 32 < clint_data_o [31:0] $end
$var reg 64 = cycle [63:0] $end
$var reg 32 > data_o [31:0] $end
$var reg 32 ? mcause [31:0] $end
$var reg 32 @ mepc [31:0] $end
$var reg 32 A mie [31:0] $end
$var reg 32 B mscratch [31:0] $end
$var reg 32 C mstatus [31:0] $end
$var reg 32 D mtvec [31:0] $end
$upscope $end
$upscope $end
$enddefinitions $end
$comment Show the parameter values. $end
$dumpall
b1010 '
$end
#0
$dumpvars
bx D
bx C
bx B
bx A
bx @
bx ?
b0 >
bx =
b0 <
b0 ;
b0 :
b0 9
b0 8
b0 7
b0 6
bx 5
bx 4
bx 3
bx 2
01
b0 0
0/
b0 .
b0 -
0,
0+
b0 *
b0 )
b0 (
bx &
bx %
bx $
b0 #
b0 "
x!
$end
#5000
0!
b0 =
b0 B
b0 %
b0 4
b0 C
b0 A
b0 &
b0 3
b0 @
b0 ?
b0 $
b0 5
b0 D
1,
#10000
0,
b0 2
#15000
1,
#18000
b10001001001101110101001000010010 (
b10001001001101110101001000010010 6
b10110010110000101000010001100101 *
b10110010110000101000010001100101 8
b1000110110111111001100110001101 )
b1000110110111111001100110001101 7
1+
b10110001111100000101011001100011 -
b10110001111100000101011001100011 9
b10000100100001001101011000001001 0
b10000100100001001101011000001001 ;
b11000000100010010101111010000001 .
b11000000100010010101111010000001 :
#20000
b1 2
0,
1/
#25000
b1 =
1,
#28000
b11100011001101110010010011000110 (
b11100011001101110010010011000110 6
b1111100111111011110100111111001 *
b1111100111111011110100111111001 8
b1000110001011011111011110001100 )
b1000110001011011111011110001100 7
b11110100011011100110100111101 -
b11110100011011100110100111101 9
b111011001000111111000101110110 0
b111011001000111111000101110110 ;
b110110101111100110100001101 .
b110110101111100110100001101 :
11
#30000
b10 2
0,
#35000
b10 =
1,
#38000
b11100111011101101001011011001110 (
b11100111011101101001011011001110 6
b1111001001100000110100111110010 *
b1111001001100000110100111110010 8
b1000111111011001101101110001111 )
b1000111111011001101101110001111 7
0+
b10111011110100100111001001110111 -
b10111011110100100111001001110111 9
b1110010101011111111011111100101 0
b1110010101011111111011111100101 ;
b11010101000100111101001010101010 .
b11010101000100111101001010101010 :
#40000
b11 2
0,
#45000
b11 =
1,
#48000
b101011100111000011100001010 (
b101011100111000011100001010 6
b10110001111011110110001001100011 *
b10110001111011110110001001100011 8
b10110010101001110010011001100101 )
b10110010101001110010011001100101 7
1+
b11011110100011100010100010111101 -
b11011110100011100010100010111101 9
b101110010110000100100101011100 0
b101110010110000100100101011100 ;
b11100010110010100100111011000101 .
b11100010110010100100111011000101 :
01
#50000
b100 2
0,
#55000
b100 =
1,
#58000
b10101001101001111101011001010011 (
b10101001101001111101011001010011 6
b10000110101111000011100000001101 *
b10000110101111000011100000001101 8
b10001001100000111011100000010011 )
b10001001100000111011100000010011 7
0+
b11001110110011001100110010011101 -
b11001110110011001100110010011101 9
b1010101011110000100010110101010 0
b1010101011110000100010110101010 ;
b10000011001000010000100100000 .
b10000011001000010000100100000 :
#60000
b101 2
0,
#65000
b101 =
1,
#68000
b101000010010110010100001010 (
b101000010010110010100001010 6
b10001100001000100100100100011 *
b10001100001000100100100100011 8
b11100111110001010111001011001111 )
b11100111110001010111001011001111 7
1+
b11010111010101100011111010101110 -
b11010111010101100011111010101110 9
b10000001000101110100101000000010 0
b10000001000101110100101000000010 ;
b11101010101001100010101011010101 .
b11101010101001100010101011010101 :
11
#70000
b110 2
0,
#75000
b110 =
1,
#78000
b11000100100010100001001010001001 (
b11000100100010100001001010001001 6
b111100001000001111001101111000 *
b111100001000001111001101111000 8
b11101100010010110011010011011000 )
b11101100010010110011010011011000 7
b1000101001011100110000110001010 -
b1000101001011100110000110001010 9
b1111001011010001011110111110010 0
b1111001011010001011110111110010 ;
b10011110001100010100110000111100 .
b10011110001100010100110000111100 :
01
#80000
b111 2
0,
#85000
b111 =
1,
#88000
b10111000100101111011111001110001 (
b10111000100101111011111001110001 6
b10000101110101111001101000001011 *
b10000101110101111001101000001011 8
b10101000011111101110100101010 )
b10101000011111101110100101010 7
0+
b1010111000101010001001110101110 -
b1010111000101010001001110101110 9
b1100011010010111111100111000110 0
b1100011010010111111100111000110 ;
b1011011000000100110010110110110 .
b1011011000000100110010110110110 :
11
#90000
b1000 2
0,
#95000
b1000 =
1,
#98000
b1101100100111000100101111011001 (
b1101100100111000100101111011001 6
b1111000110110011001101111110001 *
b1111000110110011001101111110001 8
b1010101010100100101100010101 )
b1010101010100100101100010101 7
b11101000001100011001100111010 -
b11101000001100011001100111010 9
b10011101110011000110000000111011 0
b10011101110011000110000000111011 ;
b100111111100100101010101001111 .
b100111111100100101010101001111 :
#100000
b1001 2
0,
#105000
b1001 =
1,
#108000
b10101110011111011001010001011100 (
b10101110011111011001010001011100 6
b11001111110001000101011010011111 *
b11001111110001000101011010011111 8
b11011011110011010110000010110111 )
b11011011110011010110000010110111 7
b1000111101110011010000110001111 -
b1000111101110011010000110001111 9
b1001111101000010101010110011111 0
b1001111101000010101010110011111 ;
b100110001101011111101101001100 .
b100110001101011111101101001100 :
01
#110000
b1010 2
0,
#115000
b1010 =
1,
#118000
b110000111010111111100001100 (
b110000111010111111100001100 6
b1001011001000010010111110010110 *
b1001011001000010010111110010110 8
b10101000110001111111110001010001 )
b10101000110001111111110001010001 7
1+
b11101000001000110011111011010000 -
b11101000001000110011111011010000 9
b10100100101011100011001001001001 0
b10100100101011100011001001001001 ;
b1000100110111100011011110001001 .
b1000100110111100011011110001001 :
11
#120000
b1011 2
0,
#125000
b1011 =
1,
#128000
b11100110110011110011100111001 (
b11100110110011110011100111001 6
b110110111001011000000101101101 *
b110110111001011000000101101101 8
b10111111000001010000000001111110 )
b10111111000001010000000001111110 7
0+
b11110111100101110110100111101 -
b11110111100101110110100111101 9
b10111011100000100101101001110111 0
b10111011100000100101101001110111 ;
b1100100010101111110110111001000 .
b1100100010101111110110111001000 :
01
#130000
b1100 2
0,
#135000
b1100 =
1,
#138000
b10101000011001010111100101010 (
b10101000011001010111100101010 6
b10011111111100101010111000111111 *
b10011111111100101010111000111111 8
b100100100010110100101101001001 )
b100100100010110100101101001001 7
1+
b10111100000101001000100001111000 -
b10111100000101001000100001111000 9
b1000010110110010010111110000101 0
b1000010110110010010111110000101 ;
b11101001111010111111011011010011 .
b11101001111010111111011011010011 :
11
#140000
b1101 2
0,
#145000
b1101 =
1,
#148000
b11010001100010111011010010100011 (
b11010001100010111011010010100011 6
b111001100101100001011101110011 *
b111001100101100001011101110011 8
b10010011011111011011110000100110 )
b10010011011111011011110000100110 7
0+
b11001110001011111111001010011100 -
b11001110001011111111001010011100 9
b11000111000110100000110010001110 0
b11000111000110100000110010001110 ;
b11000011001111110011100010000110 .
b11000011001111110011100010000110 :
01
#150000
b1110 2
0,
#155000
b1110 =
1,
#158000
b101101001010001101101101011010 (
b101101001010001101101101011010 6
b11110011000010010001101011100110 *
b11110011000010010001101011100110 8
b11100101100110110011011011001011 )
b11100101100110110011011011001011 7
1+
b100010001010010000110101000100 -
b100010001010010000110101000100 9
b10101111110110000101011001011111 0
b10101111110110000101011001011111 ;
b11011001110100101001001010110011 .
b11011001110100101001001010110011 :
11
#160000
b1111 2
0,
#165000
b1111 =
1,
#168000
b100010001100011111111101000100 (
b100010001100011111111101000100 6
b111100111100010001100101111001 *
b111100111100010001100101111001 8
b11101111101111101001010011011111 )
b11101111101111101001010011011111 7
b10110010100111111011011001100101 -
b10110010100111111011011001100101 9
b11101101010100110110110011011010 0
b11101101010100110110110011011010 ;
b11110110100000101110001011101101 .
b11110110100000101110001011101101 :
#170000
b10000 2
0,
#175000
b10000 =
1,
#178000
b11100001111100010000001011000011 (
b11100001111100010000001011000011 6
b11111110110111110111001011111101 *
b11111110110111110111001011111101 8
b11001101010111101011110010011010 )
b11001101010111101011110010011010 7
0+
b111011011111100111100001110 -
b111011011111100111100001110 9
b1010101111101101010110110101011 0
b1010101111101101010110110101011 ;
b10101000010010000101100101010 .
b10101000010010000101100101010 :
01
#180000
b10001 2
0,
#185000
b10001 =
1,
#188000
b11011100001010111100010010111000 (
b11011100001010111100010010111000 6
b111100110100011000011101111001 *
b111100110100011000011101111001 8
b10011100000011101000101000111000 )
b10011100000011101000101000111000 7
b10000101001100010011010000001010 -
b10000101001100010011010000001010 9
b10110011110110010111011001100111 0
b10110011110110010111011001100111 ;
b100111011110011110100101001110 .
b100111011110011110100101001110 :
#190000
b10010 2
0,
#195000
b10010 =
1,
#198000
b10110110101001000010011001101101 (
b10110110101001000010011001101101 6
b1101100101100001011011111011001 *
b1101100101100001011011111011001 8
b10100110111111001101111001001101 )
b10100110111111001101111001001101 7
1+
b10101100101101111100101001011001 -
b10101100101101111100101001011001 9
b10000010001111110010110000000100 0
b10000010001111110010110000000100 ;
b1001001110001100101110110010011 .
b1001001110001100101110110010011 :
#200000
b10011 2
0,
#205000
b10011 =
1,
#208000
b110100100110000000011101101001 (
b110100100110000000011101101001 6
b1111011110100100110000111110111 *
b1111011110100100110000111110111 8
b10011101001001101100000100 )
b10011101001001101100000100 7
0+
b1001010100100110111000110010101 -
b1001010100100110111000110010101 9
b1011011000101110010110110110110 0
b1011011000101110010110110110110 ;
b1100101001110110100100111001010 .
b1100101001110110100100111001010 :
#210000
b10100 2
0,
