RTL/case3/dut.v
module case3 (    clk,    rst,    input_a,    input_b,    ctr,    ht_out);

 input wire clk;

 input wire rst;

 input wire [31:0] input_a;

 input wire [31:0] input_b;

 input wire [31:0] ctr;

 output reg [31:0] ht_out;

 reg signal1, signal2, signal3;

 reg [31:0] ctr_1;

 reg [31:0] ctr_2;

 wire trigger;

 assign trigger = signal1 & signal2 & signal3;

always @(posedge clk) begin $display("achieve node: 1,1"); if (rst) begin $display("achieve node: 1,1,1"); signal1 <= 1'b0; signal2 <= 1'b0; signal3 <= 1'b0;end else if (input_a == 32'h11223344) begin  $display("achieve node: 1,1,0,1");signal2 <= 1'b1; end else if (input_b == 32'h55667788 && signal1) begin  $display("achieve node: 1,1,0,0,1");signal3 <= 1'b1; end else if (input_a == 32'h99AABBCC && input_b == 32'hDDCCEEFF && signal2) begin  $display("achieve node: 1,1,0,0,0,1");signal1 <= 1'b1; end else begin $display("achieve node: 1,1,0,0,0,0"); signal1 <= 1'b0; signal2 <= 1'b0; signal3 <= 1'b0; end end

always @(posedge clk) begin $display("achieve node: 2,1"); ctr_1 <= ctr; end

always @(posedge clk) begin $display("achieve node: 3,1"); ctr_2 <= ctr_1; end

always @(posedge clk) begin $display("achieve node: 4,1"); if (rst) begin  ht_out <= 32'b0;$display("achieve node: 4,1,1"); end else if (ctr_2 == 32'h12345678) begin $display("achieve node: 4,1,0,1");if (trigger == 1'b1) begin  $display("achieve node: 4,1,0,1,1");ht_out <= {ht_out[30:0], ht_out[31] ^ 1'b1}; end else begin  $display("achieve node: 4,1,0,1,0");ht_out <= {ht_out[30:0], ht_out[31]}; end end else begin  $display("achieve node: 4,1,0,0");ht_out <= ht_out; end  end

endmodule

RTL/case3/case3_tb.v
`timescale  1ns / 1ps

module tb_case3;

// case3 Parameters
parameter PERIOD  = 10;


// case3 Inputs
reg   clk                                  = 0 ;
reg   rst                                  = 0 ;
reg   [31:0]  input_a                      = 0 ;
reg   [31:0]  input_b                      = 0 ;
reg   [31:0]  ctr                          = 0 ;


// case3 Outputs
wire  [31:0]  ht_out                       ;


initial
begin
    forever #(PERIOD/2)  clk=~clk;
end

initial
begin
    #(PERIOD*2) rst  =  0;
end

case3  u_case3 (
    .clk                     ( clk                         ),
    .rst                     ( rst                         ),
    .input_a                 ( input_a              [31:0] ),
    .input_b                 ( input_b              [31:0] ),
    .ctr                     ( ctr                  [31:0] ),
    .ht_out                  ( ht_out               [31:0] )
);

integer i;
initial begin
    clk = 0;
    rst = 1;
    input_a = 0;
    input_b = 0;
    ctr = 0;
    #10;
    for(i = 0; i < 10; i = i + 1) begin
        $display("********Period %d********", i);
        input_a = $random;
        input_b = $random;
        ctr = $random;
        #10;
    end
    input_a = 32'h11223344;
    input_b = $random;
    ctr = $random;
    #10;
    input_a = 32'h99AABBCC;
    input_b = 32'hDDCCEEFF;
    ctr = 32'h12345678;
    #10;
    input_a = 32'h14572219;
    input_b = 32'h55667788;
    ctr = $random;
    #10;      
    input_a = $random;
    input_b = $random;
    ctr = $random;
    #10;
    input_a = $random;
    input_b = $random;
    ctr = $random;
    #10;
    input_a = $random;
    input_b = $random;
    ctr = $random;
    #10;
    $finish;
end
initial
begin            
    $dumpfile("wave.vcd");        //生成的vcd文件名称
    $dumpvars(0, tb_case3);    //tb模块名称
end 
endmodule

RTL/case3/wave.vcd
$date
	Wed Mar 26 09:59:25 2025
$end
$version
	Icarus Verilog
$end
$timescale
	1ps
$end
$scope module tb_case3 $end
$var wire 32 ! ht_out [31:0] $end
$var parameter 32 " PERIOD $end
$var reg 1 # clk $end
$var reg 32 $ ctr [31:0] $end
$var reg 32 % input_a [31:0] $end
$var reg 32 & input_b [31:0] $end
$var reg 1 ' rst $end
$var integer 32 ( i [31:0] $end
$scope module u_case3 $end
$var wire 1 # clk $end
$var wire 32 ) ctr [31:0] $end
$var wire 32 * input_a [31:0] $end
$var wire 32 + input_b [31:0] $end
$var wire 1 ' rst $end
$var wire 1 , trigger $end
$var reg 32 - ctr_1 [31:0] $end
$var reg 32 . ctr_2 [31:0] $end
$var reg 32 / ht_out [31:0] $end
$var reg 1 0 signal1 $end
$var reg 1 1 signal2 $end
$var reg 1 2 signal3 $end
$upscope $end
$upscope $end
$enddefinitions $end
$comment Show the parameter values. $end
$dumpall
b1010 "
$end
#0
$dumpvars
x2
x1
x0
bx /
bx .
bx -
x,
b0 +
b0 *
b0 )
bx (
1'
b0 &
b0 %
b0 $
0#
bx !
$end
#5000
0,
02
01
00
b0 -
b0 !
b0 /
1#
#10000
0#
b10000100100001001101011000001001 $
b10000100100001001101011000001001 )
b11000000100010010101111010000001 &
b11000000100010010101111010000001 +
b10010000101010011010100100100 %
b10010000101010011010100100100 *
b0 (
#15000
b0 .
b10000100100001001101011000001001 -
1#
#20000
0#
b1000110110111111001100110001101 $
b1000110110111111001100110001101 )
b110101110010111101100001101 &
b110101110010111101100001101 +
b10110001111100000101011001100011 %
b10110001111100000101011001100011 *
b1 (
0'
#25000
b1000110110111111001100110001101 -
b10000100100001001101011000001001 .
1#
#30000
0#
b111100111110001100000001 $
b111100111110001100000001 )
b10001001001101110101001000010010 &
b10001001001101110101001000010010 +
b10110010110000101000010001100101 %
b10110010110000101000010001100101 *
b10 (
#35000
b1000110110111111001100110001101 .
b111100111110001100000001 -
1#
#40000
0#
b11110100011011100110100111101 $
b11110100011011100110100111101 )
b111011001000111111000101110110 &
b111011001000111111000101110110 +
b110110101111100110100001101 %
b110110101111100110100001101 *
b11 (
#45000
b11110100011011100110100111101 -
b111100111110001100000001 .
1#
#50000
0#
b1111100111111011110100111111001 $
b1111100111111011110100111111001 )
b1000110001011011111011110001100 &
b1000110001011011111011110001100 +
b1110110110101000101011111101101 %
b1110110110101000101011111101101 *
b100 (
#55000
b11110100011011100110100111101 .
b1111100111111011110100111111001 -
1#
#60000
0#
b11010101000100111101001010101010 $
b11010101000100111101001010101010 )
b11100010111101111000010011000101 &
b11100010111101111000010011000101 +
b11100011001101110010010011000110 %
b11100011001101110010010011000110 *
b101 (
#65000
b11010101000100111101001010101010 -
b1111100111111011110100111111001 .
1#
#70000
0#
b10001001001100101101011000010010 $
b10001001001100101101011000010010 )
b10111011110100100111001001110111 &
b10111011110100100111001001110111 +
b1110010101011111111011111100101 %
b1110010101011111111011111100101 *
b110 (
#75000
b11010101000100111101001010101010 .
b10001001001100101101011000010010 -
1#
#80000
0#
b11100111011101101001011011001110 $
b11100111011101101001011011001110 )
b1111001001100000110100111110010 &
b1111001001100000110100111110010 +
b1000111111011001101101110001111 %
b1000111111011001101101110001111 *
b111 (
#85000
b11100111011101101001011011001110 -
b10001001001100101101011000010010 .
1#
#90000
0#
b101110010110000100100101011100 $
b101110010110000100100101011100 )
b11100010110010100100111011000101 &
b11100010110010100100111011000101 +
b11110100000000000111101011101000 %
b11110100000000000111101011101000 *
b1000 (
#95000
b11100111011101101001011011001110 .
b101110010110000100100101011100 -
1#
#100000
0#
b10110010101001110010011001100101 $
b10110010101001110010011001100101 )
b10010110101010110101100000101101 &
b10010110101010110101100000101101 +
b11011110100011100010100010111101 %
b11011110100011100010100010111101 *
b1001 (
#105000
b10110010101001110010011001100101 -
b101110010110000100100101011100 .
1#
#110000
0#
b101011100111000011100001010 $
b101011100111000011100001010 )
b10110001111011110110001001100011 &
b10110001111011110110001001100011 +
b10001001000100011001101000100 %
b10001001000100011001101000100 *
b1010 (
#115000
b10110010101001110010011001100101 .
b101011100111000011100001010 -
11
1#
#120000
0#
b10010001101000101011001111000 $
b10010001101000101011001111000 )
b11011101110011001110111011111111 &
b11011101110011001110111011111111 +
b10011001101010101011101111001100 %
b10011001101010101011101111001100 *
#125000
10
b10010001101000101011001111000 -
b101011100111000011100001010 .
1#
#130000
0#
b11000000001110110010001010000000 $
b11000000001110110010001010000000 )
b1010101011001100111011110001000 &
b1010101011001100111011110001000 +
b10100010101110010001000011001 %
b10100010101110010001000011001 *
#135000
1,
b10010001101000101011001111000 .
b11000000001110110010001010000000 -
12
1#
#140000
0#
b11001110110011001100110010011101 $
b11001110110011001100110010011101 )
b1010101011110000100010110101010 &
b1010101011110000100010110101010 +
b10000011001000010000100100000 %
b10000011001000010000100100000 *
#145000
0,
02
01
00
b11001110110011001100110010011101 -
b11000000001110110010001010000000 .
b1 !
b1 /
1#
#150000
0#
b10000110101111000011100000001101 $
b10000110101111000011100000001101 )
b10001001100000111011100000010011 &
b10001001100000111011100000010011 +
b11001011001000000011111010010110 %
b11001011001000000011111010010110 *
#155000
b11001110110011001100110010011101 .
b10000110101111000011100000001101 -
1#
#160000
0#
b11101010101001100010101011010101 $
b11101010101001100010101011010101 )
b110101100111111101110101101011 &
b110101100111111101110101101011 +
b10101001101001111101011001010011 %
b10101001101001111101011001010011 *
#165000
b11101010101001100010101011010101 -
b10000110101111000011100000001101 .
1#
