RTL/or1200_ICache/or1200_ic_fsm_1.v
//////////////////////////////////////////////////////////////////////
////                                                              ////
////  OR1200's IC FSM                                             ////
////                                                              ////
////  This file is part of the OpenRISC 1200 project              ////
////  http://opencores.org/project,or1k                           ////
////                                                              ////
////  Description                                                 ////
////  Insn cache state machine                                    ////
////                                                              ////
////  To Do:                                                      ////
////   - make it smaller and faster                               ////
////                                                              ////
////  Author(s):                                                  ////
////      - Damjan Lampret, lampret@opencores.org                 ////
////                                                              ////
//////////////////////////////////////////////////////////////////////
////                                                              ////
//// Copyright (C) 2000 Authors and OPENCORES.ORG                 ////
////                                                              ////
//// This source file may be used and distributed without         ////
//// restriction provided that this copyright statement is not    ////
//// removed from the file and that any derivative work contains  ////
//// the original copyright notice and the associated disclaimer. ////
////                                                              ////
//// This source file is free software; you can redistribute it   ////
//// and/or modify it under the terms of the GNU Lesser General   ////
//// Public License as published by the Free Software Foundation; ////
//// either version 2.1 of the License, or (at your option) any   ////
//// later version.                                               ////
////                                                              ////
//// This source is distributed in the hope that it will be       ////
//// useful, but WITHOUT ANY WARRANTY; without even the implied   ////
//// warranty of MERCHANTABILITY or FITNESS FOR A PARTICULAR      ////
//// PURPOSE.  See the GNU Lesser General Public License for more ////
//// details.                                                     ////
////                                                              ////
//// You should have received a copy of the GNU Lesser General    ////
//// Public License along with this source; if not, download it   ////
//// from http://www.opencores.org/lgpl.shtml                     ////
////                                                              ////
//////////////////////////////////////////////////////////////////////

module or1200_ic_fsm (

    clk,
    rst,

    ic_en,
    icqmem_cycstb_i,
    icqmem_ci_i,
    tagcomp_miss,
    biudata_valid,
    biudata_error,
    start_addr,
    saved_addr,
    icram_we,
    tag_we,
    biu_read,
    first_hit_ack,
    first_miss_ack,
    first_miss_err,
    burst
);

  //
  // I/O
  //
  input wire clk;
  input wire rst;
  input wire ic_en;
  input wire icqmem_cycstb_i;
  input wire icqmem_ci_i;
  input wire tagcomp_miss;
  input wire biudata_valid;
  input wire biudata_error;
  input wire [31:0] start_addr;
  output wire [31:0] saved_addr;
  output wire [3:0] icram_we;
  output wire biu_read;
  output wire first_hit_ack;
  output wire first_miss_ack;
  output wire first_miss_err;
  output wire burst;
  output wire tag_we;


  reg [31:0] saved_addr_r;
  reg [1:0] state;
  reg [3:0] cnt;
  reg        hitmiss_eval;
  reg        load;
  reg        cache_inhibit;
  reg        last_eval_miss;  // JPB
  reg [31:0] temp_addr;

  //
  // Generate of ICRAM write enables
  //
  assign icram_we = {4{biu_read & biudata_valid & !cache_inhibit}};
  assign tag_we = biu_read & biudata_valid & !cache_inhibit;

  //
  // BIU read and write
  //
  assign biu_read = (hitmiss_eval & tagcomp_miss) | (!hitmiss_eval & load);

  //assign saved_addr = hitmiss_eval ? start_addr : saved_addr_r;
  assign saved_addr = saved_addr_r;

  // Asserted when a cache hit occurs and the first word is ready/valid
  assign first_hit_ack = (state == 2'd1) & hitmiss_eval & !tagcomp_miss & !cache_inhibit;

  // Asserted when a cache miss occurs, but the first word of the new
  // cache line is ready (on the bus)
  // Cache hits overpower bus data
  assign first_miss_ack = (state == 2'd1) & biudata_valid & ~first_hit_ack;

  // Asserted when a cache occurs, but there was a bus error with handling
  // the old line or fetching the new line
  assign first_miss_err = (state == 2'd1) & biudata_error;

  //
  // Assert burst when doing reload of complete cache line
  //
  assign burst = (state == 2'd1) & tagcomp_miss & !cache_inhibit | (state == 2'd2);

  //
  // Main IC FSM
  //
  always @(posedge clk or posedge rst) begin
    if (rst == (1'b1)) begin
      state <= 2'd0;
      saved_addr_r <= 32'b0;
      hitmiss_eval <= 1'b0;
      load <= 1'b0;
      cnt <= 4'd0;
      
      last_eval_miss <= 0;  // JPB

    end else
      case (state)  // synopsys parallel_case
        2'd0: begin
          if (ic_en & icqmem_cycstb_i) begin  // fetch
			state <= 2'd1;
			saved_addr_r <= start_addr;
			hitmiss_eval <= 1'b1;
			load <= 1'b1;
			cache_inhibit <= icqmem_ci_i;
			last_eval_miss <= 0;  // JPB
          end else begin  // idle
			hitmiss_eval <= 1'b0;
			load <= 1'b0;
			cache_inhibit <= 1'b0;
        end
		end
        2'd1: begin  // fetch
		temp_addr = saved_addr_r;
		if (icqmem_cycstb_i & icqmem_ci_i) cache_inhibit <=  1'b1;

          if (hitmiss_eval) begin
            temp_addr = {start_addr[31:13], temp_addr[12:0]};
          end

          if ((!ic_en) || (hitmiss_eval & !icqmem_cycstb_i) || (biudata_error) || (cache_inhibit & biudata_valid)) begin
            state <= 2'd0;
            hitmiss_eval <= 1'b0;
            load <= 1'b0;
            cache_inhibit <= 1'b0;
          end else if (tagcomp_miss & biudata_valid) begin
            state <= 2'd2;
            temp_addr = {temp_addr[31:4], saved_addr_r[3:2] + 2'b1, temp_addr[1:0]};
            hitmiss_eval <= 1'b0;
            cnt <= ((1 << 4) - (2 * 4));
            cache_inhibit <= 1'b0;
          end else if (!icqmem_cycstb_i & !last_eval_miss) begin
            state <= 2'd0;
            hitmiss_eval <= 1'b0;
            load <= 1'b0;
            cache_inhibit <= 1'b0;
          end else if (!tagcomp_miss & !icqmem_ci_i) begin
            temp_addr = start_addr;
            cache_inhibit <= 1'b0;
          end else
            hitmiss_eval <= 1'b0;

          if (hitmiss_eval & !tagcomp_miss)  // JPB
            last_eval_miss <= 1;  // JPB

          saved_addr_r <= temp_addr;
        end
        2'd2: begin
          // abort because IC has just been turned off
          if (!ic_en) begin
            // invalidate before IC can be turned on
            state <= 2'd0;
            saved_addr_r <= start_addr;
            hitmiss_eval <= 1'b0;
            load <= 1'b0;
          end else if (biudata_valid && (|cnt)) begin
            cnt <= cnt - 4'd4;
            saved_addr_r <= {saved_addr_r[31:4], saved_addr_r[4-1:2] + 2'b1, saved_addr_r[1:0]};
            //saved_addr_r[4-1:2] 
            // <= saved_addr_r[4-1:2] + 1;
          end else if (biudata_valid) begin
            state <= 2'd0;
            saved_addr_r <= start_addr;
            hitmiss_eval <= 1'b0;
            load <= 1'b0;
          end
        end
        default: state <= 2'd0;
      endcase
  end


endmodule

RTL/or1200_ic_fsm/tb_or1200_ic_fsm.v
//~ `New testbench
`timescale  1ns / 1ps

module tb_or1200_ic_fsm;

// or1200_ic_fsm Parameters
parameter PERIOD  = 10;


// or1200_ic_fsm Inputs
reg   clk                                  = 0 ;
reg   rst                                  = 0 ;
reg   ic_en                                = 0 ;
reg   icqmem_cycstb_i                      = 0 ;
reg   icqmem_ci_i                          = 0 ;
reg   tagcomp_miss                         = 0 ;
reg   biudata_valid                        = 0 ;
reg   biudata_error                        = 0 ;
reg   [31:0]  start_addr                   = 0 ;

// or1200_ic_fsm Outputs
wire  [31:0]  saved_addr                   ;
wire  [3:0]  icram_we                      ;
wire  biu_read                             ;
wire  first_hit_ack                        ;
wire  first_miss_ack                       ;
wire  first_miss_err                       ;
wire  burst                                ;
wire  tag_we                               ;


initial
begin
    forever #(PERIOD/2)  clk=~clk;
end

initial
begin
    #(PERIOD*2) rst  =  0;
end

or1200_ic_fsm  u_or1200_ic_fsm (
    .clk                     ( clk                     ),
    .rst                     ( rst                     ),
    .ic_en                   ( ic_en                   ),
    .icqmem_cycstb_i         ( icqmem_cycstb_i         ),
    .icqmem_ci_i             ( icqmem_ci_i             ),
    .tagcomp_miss            ( tagcomp_miss            ),
    .biudata_valid           ( biudata_valid           ),
    .biudata_error           ( biudata_error           ),
    .start_addr              ( start_addr       [31:0] ),

    .saved_addr              ( saved_addr       [31:0] ),
    .icram_we                ( icram_we         [3:0]  ),
    .biu_read                ( biu_read                ),
    .first_hit_ack           ( first_hit_ack           ),
    .first_miss_ack          ( first_miss_ack          ),
    .first_miss_err          ( first_miss_err          ),
    .burst                   ( burst                   ),
    .tag_we                  ( tag_we                  )
);

integer i;
initial begin
    ic_en = 0;
    icqmem_cycstb_i = 0;
    icqmem_ci_i = 0;
    tagcomp_miss = 0;
    biudata_valid = 0;
    biudata_error = 0;
    start_addr = 0;
    clk = 0;
    rst = 1;
    #10;
    for(i = 0; i < 2000; i = i + 1) begin
        $display("********Period %d********", i);
        ic_en = $random & 1'd1;
        icqmem_cycstb_i = $random & 1'd1;
        icqmem_ci_i = $random & 1'd1;
        tagcomp_miss = $random & 1'd1;
        biudata_valid = $random & 1'd1;
        biudata_error = $random & 1'd1;
        start_addr = $random;
        #10;
    end
    $finish;
end
initial begin
    $dumpfile("d:/mylife_yanjiu/project/concolic_on_RTL/RTL/or1200_ICache/wave.vcd");
    $dumpvars(0, tb_or1200_ic_fsm);
end

endmodule

RTL/or1200_ICache/wave.vcd
$date
	Tue Mar 18 15:31:18 2025
$end
$version
	Icarus Verilog
$end
$timescale
	1ps
$end
$scope module tb_or1200_ic_fsm $end
$var wire 1 ! tag_we $end
$var wire 32 " saved_addr [31:0] $end
$var wire 4 # icram_we [3:0] $end
$var wire 1 $ first_miss_err $end
$var wire 1 % first_miss_ack $end
$var wire 1 & first_hit_ack $end
$var wire 1 ' burst $end
$var wire 1 ( biu_read $end
$var parameter 32 ) PERIOD $end
$var reg 1 * biudata_error $end
$var reg 1 + biudata_valid $end
$var reg 1 , clk $end
$var reg 1 - ic_en $end
$var reg 1 . icqmem_ci_i $end
$var reg 1 / icqmem_cycstb_i $end
$var reg 1 0 rst $end
$var reg 32 1 start_addr [31:0] $end
$var reg 1 2 tagcomp_miss $end
$var integer 32 3 i [31:0] $end
$scope module u_or1200_ic_fsm $end
$var wire 1 ( biu_read $end
$var wire 1 * biudata_error $end
$var wire 1 + biudata_valid $end
$var wire 1 ' burst $end
$var wire 1 , clk $end
$var wire 1 & first_hit_ack $end
$var wire 1 % first_miss_ack $end
$var wire 1 $ first_miss_err $end
$var wire 1 - ic_en $end
$var wire 1 . icqmem_ci_i $end
$var wire 1 / icqmem_cycstb_i $end
$var wire 1 0 rst $end
$var wire 32 4 saved_addr [31:0] $end
$var wire 32 5 start_addr [31:0] $end
$var wire 1 ! tag_we $end
$var wire 1 2 tagcomp_miss $end
$var wire 4 6 icram_we [3:0] $end
$var reg 1 7 cache_inhibit $end
$var reg 4 8 cnt [3:0] $end
$var reg 1 9 hitmiss_eval $end
$var reg 1 : last_eval_miss $end
$var reg 1 ; load $end
$var reg 32 < saved_addr_r [31:0] $end
$var reg 2 = state [1:0] $end
$var reg 32 > temp_addr [31:0] $end
$upscope $end
$upscope $end
$enddefinitions $end
$comment Show the parameter values. $end
$dumpall
b1010 )
$end
#0
$dumpvars
bx >
b0 =
b0 <
0;
0:
09
b0 8
x7
b0 6
b0 5
b0 4
bx 3
02
b0 1
10
0/
0.
0-
0,
0+
0*
0(
0'
0&
0%
0$
b0 #
b0 "
0!
$end
#5000
1,
#10000
0,
b10110010110000101000010001100101 1
b10110010110000101000010001100101 5
1*
1+
12
1.
1/
b0 3
#15000
1,
#20000
0,
b1000110001011011111011110001100 1
b1000110001011011111011110001100 5
02
b1 3
00
#25000
07
1,
#30000
0,
b10001001001100101101011000010010 1
b10001001001100101101011000010010 5
0/
1-
b10 3
#35000
1,
#40000
0,
b11011110100011100010100010111101 1
b11011110100011100010100010111101 5
0*
0.
b11 3
#45000
1,
#50000
0,
b1010101011110000100010110101010 1
b1010101011110000100010110101010 5
0+
1.
1/
b100 3
#55000
17
1;
19
b1010101011110000100010110101010 "
b1010101011110000100010110101010 4
b1010101011110000100010110101010 <
b1 =
1,
#60000
1%
1(
1$
0,
b11101010101001100010101011010101 1
b11101010101001100010101011010101 5
1*
1+
12
0/
b101 3
#65000
0(
0%
b0 #
b0 6
0!
0$
b11101010101001100010010110101010 "
b11101010101001100010010110101010 4
b11101010101001100010010110101010 <
07
0;
09
b0 =
b11101010101001100010010110101010 >
1,
#70000
0,
b11100101011100110000101011001010 1
b11100101011100110000101011001010 5
0*
0-
b110 3
#75000
1,
#80000
0,
b11000100100010100001001010001001 1
b11000100100010100001001010001001 5
0+
0.
b111 3
#85000
1,
#90000
0,
b10000101110101111001101000001011 1
b10000101110101111001101000001011 5
02
1-
b1000 3
#95000
1,
#100000
0,
b1010101010100100101100010101 1
b1010101010100100101100010101 5
12
1.
1/
b1001 3
#105000
1(
17
1;
19
b1010101010100100101100010101 "
b1010101010100100101100010101 4
b1010101010100100101100010101 <
b1 =
1,
#110000
1%
0(
1$
0,
b1111100011011011010100111111000 1
b1111100011011011010100111111000 5
1*
1+
02
0.
b1010 3
#115000
0%
0&
0$
b1111100011011011010101100010101 "
b1111100011011011010101100010101 4
b1111100011011011010101100010101 <
1:
07
0;
09
b0 =
b1111100011011011010101100010101 >
1,
#120000
0,
b11101000001000110011111011010000 1
b11101000001000110011111011010000 5
12
b1011 3
#125000
1!
b1111 #
b1111 6
1'
1(
1%
1$
0:
1;
19
b11101000001000110011111011010000 "
b11101000001000110011111011010000 4
b11101000001000110011111011010000 <
b1 =
1,
#130000
0'
b0 #
b0 6
0!
0%
0(
1&
0$
0,
b10111011100000100101101001110111 1
b10111011100000100101101001110111 5
0*
0+
02
b1100 3
#135000
b10111011100000100101101001110111 "
b10111011100000100101101001110111 4
b10111011100000100101101001110111 <
1:
b10111011100000100101101001110111 >
1,
#140000
1!
b1111 #
b1111 6
1%
1'
1(
0&
1$
0,
b11101001111010111111011011010011 1
b11101001111010111111011011010011 5
1*
1+
12
0/
b1101 3
#145000
0!
b0 #
b0 6
0'
0(
0%
0$
b11101001111010111111101001110111 "
b11101001111010111111101001110111 4
b11101001111010111111101001110111 <
0;
09
b0 =
b11101001111010111111101001110111 >
1,
#150000
0,
b101100000101010110001101011000 1
b101100000101010110001101011000 5
0*
1.
b1110 3
#155000
1,
#160000
0,
b11010001100010111011010010100011 1
b11010001100010111011010010100011 5
1*
0+
02
0.
0-
b1111 3
#165000
1,
#170000
0,
b11110011000010010001101011100110 1
b11110011000010010001101011100110 5
1+
1.
1/
1-
b10000 3
#175000
1%
1$
0:
17
1;
19
b11110011000010010001101011100110 "
b11110011000010010001101011100110 4
b11110011000010010001101011100110 <
b1 =
1,
#180000
0,
b11101111101111101001010011011111 1
b11101111101111101001010011011111 5
0-
b10001 3
#185000
0%
0&
0$
b11101111101111101001101011100110 "
b11101111101111101001101011100110 4
b11101111101111101001101011100110 <
1:
07
0;
09
b0 =
b11101111101111101001101011100110 >
1,
#190000
0,
b1101110010111011010110111011100 1
b1101110010111011010110111011100 5
0*
0.
0/
1-
b10010 3
#195000
1,
#200000
0,
b10000101001100010011010000001010 1
b10000101001100010011010000001010 5
1*
0+
1.
1/
0-
b10011 3
#205000
1,
#210000
0,
b10000010001111110010110000000100 1
b10000010001111110010110000000100 5
0/
b10100 3
#215000
1,
#220000
0,
b1100101001110110100100111001010 1
b1100101001110110100100111001010 5
0*
1+
12
1/
1-
b10101 3
#225000
1(
1%
0:
17
1;
19
b1100101001110110100100111001010 "
b1100101001110110100100111001010 4
b1100101001110110100100111001010 <
b1 =
1,
#230000
0(
1$
0,
b11011010011011101011101010110100 1
b11011010011011101011101010110100 5
1*
02
0.
0-
b10110 3
#235000
0%
0&
0$
b11011010011011101010100111001010 "
b11011010011011101010100111001010 4
b11011010011011101010100111001010 <
1:
07
0;
09
b0 =
b11011010011011101010100111001010 >
1,
#240000
0,
b1110010000010100010100011100 1
b1110010000010100010100011100 5
0*
0+
12
1.
0/
b10111 3
#245000
1,
#250000
0,
b110011010011101010011101100110 1
b110011010011101010011101100110 5
1*
02
0.
1/
1-
b11000 3
#255000
1&
1$
0:
1;
19
b110011010011101010011101100110 "
b110011010011101010011101100110 4
b110011010011101010011101100110 <
b1 =
1,
#260000
0,
b10001101001001001111011000011010 1
b10001101001001001111011000011010 5
0-
b11001 3
#265000
0&
0$
b10001101001001001110011101100110 "
b10001101001001001110011101100110 4
b10001101001001001110011101100110 <
1:
0;
09
b0 =
b10001101001001001110011101100110 >
1,
#270000
0,
b111110100110011000001101111101 1
b111110100110011000001101111101 5
0*
1-
b11010 3
#275000
1&
0:
1;
19
b111110100110011000001101111101 "
b111110100110011000001101111101 4
b111110100110011000001101111101 <
b1 =
1,
#280000
1$
0,
b111100111011010010101101111001 1
b111100111011010010101101111001 5
1*
1+
0/
0-
b11011 3
#285000
0&
0$
b111100111011010010001101111101 "
b111100111011010010001101111101 4
b111100111011010010001101111101 <
1:
0;
09
b0 =
b111100111011010010001101111101 >
1,
#290000
0,
b1111010100011000101100111110101 1
b1111010100011000101100111110101 5
0*
0+
12
1.
1/
b11100 3
#295000
1,
#300000
0,
b10111001100011000100001001110011 1
b10111001100011000100001001110011 5
1*
1-
b11101 3
#305000
1(
1$
0:
17
1;
19
b10111001100011000100001001110011 "
b10111001100011000100001001110011 4
b10111001100011000100001001110011 <
b1 =
1,
#310000
1%
0(
0,
b111000010111011100100001110 1
b111000010111011100100001110 5
1+
02
0.
0/
0-
b11110 3
#315000
0%
0&
0$
b111000010111010001001110011 "
b111000010111010001001110011 4
b111000010111010001001110011 <
1:
07
0;
09
b0 =
b111000010111010001001110011 >
1,
#320000
0,
b10011100011011011110011000111000 1
b10011100011011011110011000111000 5
0*
1/
b11111 3
#325000
1,
#330000
0,
b1011011000010111101110110110110 1
b1011011000010111101110110110110 5
1*
12
0/
1-
b100000 3
#335000
1,
#340000
0,
b11000011001100111001000010000110 1
b11000011001100111001000010000110 5
0+
02
1.
0-
b100001 3
#345000
1,
#350000
0,
b1100101010000111100111111001010 1
b1100101010000111100111111001010 5
0*
12
0.
b100010 3
#355000
1,
#360000
0,
b1100100110010000011110111001001 1
b1100100110010000011110111001001 5
1*
1+
1/
1-
b100011 3
#365000
1!
b1111 #
b1111 6
1'
1(
1%
1$
0:
1;
19
b1100100110010000011110111001001 "
b1100100110010000011110111001001 4
b1100100110010000011110111001001 <
b1 =
1,
#370000
b0 #
b0 6
0!
0%
0$
0,
b1001101111100111000000110011011 1
b1001101111100111000000110011011 5
0*
0+
1.
0-
b100100 3
#375000
0'
0(
b1001101111100111001110111001001 "
b1001101111100111001110111001001 4
b1001101111100111001110111001001 <
0;
09
b0 =
07
b1001101111100111001110111001001 >
1,
#380000
0,
b110101100110000010100001101 1
b110101100110000010100001101 5
0/
b100101 3
#385000
1,
#390000
0,
b1101100010001001111100111011000 1
b1101100010001001111100111011000 5
1*
1+
02
b100110 3
#395000
1,
#400000
0,
b11101100010100001011010011011000 1
b11101100010100001011010011011000 5
0+
1-
b100111 3
#405000
1,
#410000
0,
b1000000100100000101110110000001 1
b1000000100100000101110110000001 5
1+
12
0-
b101000 3
#415000
1,
#420000
0,
b11001011010111001000000010010110 1
b11001011010111001000000010010110 5
0*
0+
1/
b101001 3
#425000
1,
#430000
0,
b10101100010110010101100101011 1
b10101100010110010101100101011 5
1*
1+
0.
0/
b101010 3
#435000
1,
#440000
0,
b11011100111011111001000010111001 1
b11011100111011111001000010111001 5
02
1.
1/
1-
b101011 3
#445000
1%
1$
17
1;
19
b11011100111011111001000010111001 "
b11011100111011111001000010111001 4
b11011100111011111001000010111001 <
b1 =
1,
#450000
1(
0$
0,
b1111101001010100100010111111010 1
b1111101001010100100010111111010 5
0*
12
b101100 3
#455000
0(
0%
b0 #
b0 6
0!
b1111101001010100101000010111001 "
b1111101001010100101000010111001 4
b1111101001010100101000010111001 <
07
0;
09
b0 =
b1111101001010100101000010111001 >
1,
#460000
0,
b10110111110111111010101001101111 1
b10110111110111111010101001101111 5
0+
02
0.
b101101 3
#465000
1&
1;
19
b10110111110111111010101001101111 "
b10110111110111111010101001101111 4
b10110111110111111010101001101111 <
b1 =
1,
#470000
0,
b11100010101111110001101011000101 1
b11100010101111110001101011000101 5
0/
0-
b101110 3
#475000
0&
b11100010101111110000101001101111 "
b11100010101111110000101001101111 4
b11100010101111110000101001101111 <
1:
0;
09
b0 =
b11100010101111110000101001101111 >
1,
#480000
0,
b110001001001001101001101100010 1
b110001001001001101001101100010 5
1.
b101111 3
#485000
1,
#490000
0,
b10010100101111100101100100101 1
b10010100101111100101100100101 5
1+
12
1/
1-
b110000 3
#495000
1(
1%
0:
17
1;
19
b10010100101111100101100100101 "
b10010100101111100101100100101 4
b10010100101111100101100100101 <
b1 =
1,
#500000
0%
0,
b10111000101011011110011001110001 1
b10111000101011011110011001110001 5
0+
0.
b110001 3
#505000
b10111000101011011110101100100101 "
b10111000101011011110101100100101 4
b10111000101011011110101100100101 <
09
b10111000101011011110101100100101 >
1,
#510000
1$
0,
b10010000001010100011101000100000 1
b10010000001010100011101000100000 5
1*
02
1.
0/
b110010 3
#515000
0(
0$
07
0;
b0 =
1,
#520000
0,
b10111100110011000100001001111001 1
b10111100110011000100001001111001 5
1+
12
0.
0-
b110011 3
#525000
1,
#530000
0,
b1110100100100100001100011101 1
b1110100100100100001100011101 5
1.
1/
b110100 3
#535000
1,
#540000
0,
b1111100000111100101101111111000 1
b1111100000111100101101111111000 5
0*
02
0/
1-
b110101 3
#545000
1,
#550000
0,
b1011111010101100000100010111 1
b1011111010101100000100010111 5
0+
0.
b110110 3
#555000
1,
#560000
0,
b11000101101000010110000010001011 1
b11000101101000010110000010001011 5
0-
b110111 3
#565000
1,
#570000
0,
b10011110110010011100000000111101 1
b10011110110010011100000000111101 5
1+
1/
b111000 3
#575000
1,
#580000
0,
b1101000010100011110010111010000 1
b1101000010100011110010111010000 5
1.
0/
1-
b111001 3
#585000
1,
#590000
0,
b10100101111001111001111001001011 1
b10100101111001111001111001001011 5
0-
b111010 3
#595000
1,
#600000
0,
b11101111100000110111001011011111 1
b11101111100000110111001011011111 5
1*
1-
b111011 3
#605000
1,
#610000
0,
b11101100101110010001101011011001 1
b11101100101110010001101011011001 5
0+
1/
0-
b111100 3
#615000
1,
#620000
0,
b10101110110101110010111001011101 1
b10101110110101110010111001011101 5
0*
12
0/
b111101 3
#625000
1,
#630000
0,
b101100100001001000100101011001 1
b101100100001001000100101011001 5
b111110 3
#635000
1,
#640000
0,
b10000000011110010111110000000000 1
b10000000011110010111110000000000 5
1*
b111111 3
#645000
1,
#650000
0,
b1001000001110011110010110010000 1
b1001000001110011110010110010000 5
1+
0.
1/
1-
b1000000 3
#655000
1!
b1111 #
b1111 6
1'
1(
1%
1$
1;
19
b1001000001110011110010110010000 "
b1001000001110011110010110010000 4
b1001000001110011110010110010000 <
b1 =
1,
#660000
0'
b0 #
b0 6
0!
0%
0(
1&
0,
b11100010000011101001101011000100 1
b11100010000011101001101011000100 5
0+
02
1.
b1000001 3
#665000
0&
0$
b11100010000011101000010110010000 "
b11100010000011101000010110010000 4
b11100010000011101000010110010000 <
1:
0;
09
b0 =
07
b11100010000011101000010110010000 >
1,
#670000
0,
b1101010000101011111010111010100 1
b1101010000101011111010111010100 5
1+
0.
0-
b1000010 3
#675000
1,
#680000
0,
b11000000011101100100001010000000 1
b11000000011101100100001010000000 5
12
1.
0/
1-
b1000011 3
#685000
1,
#690000
0,
b11110100110110000110111011101001 1
b11110100110110000110111011101001 5
0+
0.
1/
0-
b1000100 3
#695000
1,
#700000
0,
b110000010011100100110101100000 1
b110000010011100100110101100000 5
0*
1+
1.
0/
b1000101 3
#705000
1,
#710000
0,
b110111000101010001010101101110 1
b110111000101010001010101101110 5
1*
0.
1-
b1000110 3
#715000
1,
#720000
0,
b11111000110111000100100011110001 1
b11111000110111000100100011110001 5
0+
02
1/
b1000111 3
#725000
1&
1$
0:
1;
19
b11111000110111000100100011110001 "
b11111000110111000100100011110001 4
b11111000110111000100100011110001 <
b1 =
1,
#730000
0,
b10101101111001111101000001011011 1
b10101101111001111101000001011011 5
1+
0/
b1001000 3
#735000
0&
0$
b10101101111001111100100011110001 "
b10101101111001111100100011110001 4
b10101101111001111100100011110001 <
1:
0;
09
b0 =
b10101101111001111100100011110001 >
1,
#740000
0,
b101000110001100010011101010001 1
b101000110001100010011101010001 5
12
1.
b1001001 3
#745000
1,
#750000
0,
b10101000100111101110100101010 1
b10101000100111101110100101010 5
0*
0+
0.
1/
b1001010 3
#755000
1'
1(
0:
1;
19
b10101000100111101110100101010 "
b10101000100111101110100101010 4
b10101000100111101110100101010 <
b1 =
1,
#760000
b1111 #
b1111 6
1!
1%
1$
0,
b1010111110000011101000110101111 1
b1010111110000011101000110101111 5
1*
1+
1.
b1001011 3
#765000
0!
b0 #
b0 6
0'
0(
0%
0$
b1010111110000011101110100101010 "
b1010111110000011101110100101010 4
b1010111110000011101110100101010 <
0;
09
b0 =
07
b1010111110000011101110100101010 >
1,
#770000
0,
b10110101010101011101111001101010 1
b10110101010101011101111001101010 5
0+
02
0.
b1001100 3
#775000
1&
1$
1;
19
b10110101010101011101111001101010 "
b10110101010101011101111001101010 4
b10110101010101011101111001101010 <
b1 =
1,
#780000
1'
1(
0&
0$
0,
b10101110001000111100111001011100 1
b10101110001000111100111001011100 5
0*
12
1.
0/
0-
b1001101 3
#785000
0'
0(
b10101110001000111101111001101010 "
b10101110001000111101111001101010 4
b10101110001000111101111001101010 <
0;
09
b0 =
b10101110001000111101111001101010 >
1,
#790000
0,
b110011100010000001100001100 1
b110011100010000001100001100 5
1*
0.
1/
1-
b1001110 3
#795000
1'
1(
1$
1;
19
b110011100010000001100001100 "
b110011100010000001100001100 4
b110011100010000001100001100 <
b1 =
1,
#800000
b1111 #
b1111 6
1!
1%
0$
0,
b10111010111101001110001001110101 1
b10111010111101001110001001110101 5
0*
1+
1.
0/
0-
b1001111 3
#805000
0!
b0 #
b0 6
0'
0(
0%
b10111010111101001110001100001100 "
b10111010111101001110001100001100 4
b10111010111101001110001100001100 <
0;
09
b0 =
b10111010111101001110001100001100 >
1,
#810000
0,
b1001111110010100100000010 1
b1001111110010100100000010 5
0.
1/
b1010000 3
#815000
1,
#820000
0,
b1111010111101101010101111110101 1
b1111010111101101010101111110101 5
0+
1.
0/
b1010001 3
#825000
1,
#830000
0,
b10110110010111111100100101101 1
b10110110010111111100100101101 5
1+
0.
1/
b1010010 3
#835000
1,
#840000
0,
b100110101111110011111101001101 1
b100110101111110011111101001101 5
1*
0+
02
0/
1-
b1010011 3
#845000
1,
#850000
0,
b11011100010000110000100010111000 1
b11011100010000110000100010111000 5
0*
1.
1/
b1010100 3
#855000
17
1;
19
b11011100010000110000100010111000 "
b11011100010000110000100010111000 4
b11011100010000110000100010111000 <
b1 =
1,
#860000
1%
1(
1$
0,
b1011011110100111101101110110111 1
b1011011110100111101101110110111 5
1*
1+
12
0.
0/
0-
b1010101 3
#865000
0(
0%
b0 #
b0 6
0!
0$
b1011011110100111100100010111000 "
b1011011110100111100100010111000 4
b1011011110100111100100010111000 <
07
0;
09
b0 =
b1011011110100111100100010111000 >
1,
#870000
0,
b11001000001110001111010010010000 1
b11001000001110001111010010010000 5
0*
0+
02
1.
1/
1-
b1010110 3
#875000
17
1;
19
b11001000001110001111010010010000 "
b11001000001110001111010010010000 4
b11001000001110001111010010010000 <
b1 =
1,
#880000
1(
1$
0,
b1101100011010100110110111011000 1
b1101100011010100110110111011000 5
1*
12
0/
0-
b1010111 3
#885000
0(
0$
b1101100011010100111010010010000 "
b1101100011010100111010010010000 4
b1101100011010100111010010010000 <
07
0;
09
b0 =
b1101100011010100111010010010000 >
1,
#890000
0,
b1100100101111000110100011001 1
b1100100101111000110100011001 5
0*
02
1/
1-
b1011000 3
#895000
17
1;
19
b1100100101111000110100011001 "
b1100100101111000110100011001 4
b1100100101111000110100011001 <
b1 =
1,
#900000
0,
b11001110100100010100000110 1
b11001110100100010100000110 5
0/
b1011001 3
#905000
0&
b11001110100100110100011001 "
b11001110100100110100011001 4
b11001110100100110100011001 <
1:
07
0;
09
b0 =
b11001110100100110100011001 >
1,
#910000
0,
b1011001001101001110100110110010 1
b1011001001101001110100110110010 5
1*
0-
b1011010 3
#915000
1,
#920000
0,
b1000100100000111010110110001001 1
b1000100100000111010110110001001 5
0*
12
1/
b1011011 3
#925000
1,
#930000
0,
b1010101110111011000110110101011 1
b1010101110111011000110110101011 5
1*
1+
02
1-
b1011100 3
#935000
1%
1$
0:
17
1;
19
b1010101110111011000110110101011 "
b1010101110111011000110110101011 4
b1010101110111011000110110101011 <
b1 =
1,
#940000
0%
0,
b11011001101101000101100110110 1
b11011001101101000101100110110 5
0+
0/
b1011101 3
#945000
0&
0$
b11011001101101000110110101011 "
b11011001101101000110110101011 4
b11011001101101000110110101011 <
1:
07
0;
09
b0 =
b11011001101101000110110101011 >
1,
#950000
0,
b10010111010110011000100000101110 1
b10010111010110011000100000101110 5
0*
0.
1/
0-
b1011110 3
#955000
1,
#960000
0,
b11100000111000000000010011000001 1
b11100000111000000000010011000001 5
1*
1.
b1011111 3
#965000
1,
#970000
0,
b11101001101101001001101011010011 1
b11101001101101001001101011010011 5
0*
1+
12
1-
b1100000 3
#975000
1(
1%
0:
17
1;
19
b11101001101101001001101011010011 "
b11101001101101001001101011010011 4
b11101001101101001001101011010011 <
b1 =
1,
#980000
0,
b11111000110001110001010011110001 1
b11111000110001110001010011110001 5
0.
0/
0-
b1100001 3
#985000
0(
0%
b0 #
b0 6
0!
b11111000110001110001101011010011 "
b11111000110001110001101011010011 4
b11111000110001110001101011010011 <
07
0;
09
b0 =
b11111000110001110001101011010011 >
1,
#990000
0,
b10110010110100010100101001100101 1
b10110010110100010100101001100101 5
0+
02
1/
1-
b1100010 3
#995000
1&
1;
19
b10110010110100010100101001100101 "
b10110010110100010100101001100101 4
b10110010110100010100101001100101 <
b1 =
1,
#1000000
1'
1(
0&
0,
b10111010011000000011100001110100 1
b10111010011000000011100001110100 5
12
b1100011 3
#1005000
b10111010011000000010101001100101 "
b10111010011000000010101001100101 4
b10111010011000000010101001100101 <
09
b10111010011000000010101001100101 >
1,
#1010000
0'
b1111 #
b1111 6
1!
1%
0,
b11011000011110000110100110110 1
b11011000011110000110100110110 5
1+
02
0/
0-
b1100100 3
#1015000
0!
b0 #
b0 6
0(
0%
0;
b0 =
1,
