RTL/AES-T1100/dut.v
module top ( input wire clk, input wire rst, input wire [127:0] state, input wire [127:0] key, output [63:0] Capacitance );

 reg Tj_Trig;

 reg State0;

 reg State1;

 reg State2;

 reg State3;

always @(rst, state) begin $display("achieve node: 0,0"); if (rst == 1'b1) begin $display("achieve node: 0,0,1"); State0 <= 1'b0; State1 <= 1'b0; State2 <= 1'b0; State3 <= 1'b0; end else if (state == 128'h3243f6a8_885a308d_313198a2_e0370734) begin $display("achieve node: 0,0,0,1"); State0 <= 1'b1; end else if ((state == 128'h00112233_44556677_8899aabb_ccddeeff) && (State0 == 1'b1)) begin $display("achieve node: 0,0,0,0,1"); State1 <= 1'b1; end else if ((state == 128'h0) && (State1 == 1'b1)) begin $display("achieve node: 0,0,0,0,0,1"); State2 <= 1'b1; end else if ((state == 128'h1) && (State2 == 1'b1)) begin $display("achieve node: 0,0,0,0,0,0,1"); State3 <= 1'b1; end end

always @(State0, State1, State2, State3) begin $display("achieve node: 1,0"); Tj_Trig <= State0 & State1 & State2 & State3; end

 reg [19:0] lfsr_stream;

 wire [19:0] lfsr;

 wire d0;

 wire [127:0] data;

 assign data = state;

 assign lfsr = lfsr_stream;

 assign d0 = lfsr_stream[15] ^ lfsr_stream[11] ^ lfsr_stream[7] ^ lfsr_stream[0];

always @(posedge clk) begin $display("achieve node: 5,1"); if (rst == 1'b1) begin $display("achieve node: 5,1,1"); lfsr_stream <= data[19:0]; end else begin $display("achieve node: 5,1,0");  if (Tj_Trig == 1'b1) begin $display("achieve node: 5,1,0,1"); lfsr_stream <= {d0, lfsr_stream[19:1]}; end else begin $display("achieve node: 5,1,0,0");  lfsr_stream <= lfsr_stream; end end end

 wire [19:0] counter;

 assign counter = lfsr_stream;

 reg [63:0] load;

 wire [63:0] Capacitance;

 assign Capacitance = load;

always @(posedge clk) begin $display("achieve node: 8,1"); load[0] <= key[0] ^ counter[0]; load[1] <= key[0] ^ counter[0]; load[2] <= key[0] ^ counter[0]; load[3] <= key[0] ^ counter[0]; load[4] <= key[0] ^ counter[0]; load[5] <= key[0] ^ counter[0]; load[6] <= key[0] ^ counter[0]; load[7] <= key[0] ^ counter[0]; load[8] <= key[1] ^ counter[1]; load[9] <= key[1] ^ counter[1]; load[10] <= key[1] ^ counter[1]; load[11] <= key[1] ^ counter[1]; load[12] <= key[1] ^ counter[1]; load[13] <= key[1] ^ counter[1]; load[14] <= key[1] ^ counter[1]; load[15] <= key[1] ^ counter[1]; load[16] <= key[2] ^ counter[2]; load[17] <= key[2] ^ counter[2]; load[18] <= key[2] ^ counter[2]; load[19] <= key[2] ^ counter[2]; load[20] <= key[2] ^ counter[2]; load[21] <= key[2] ^ counter[2]; load[22] <= key[2] ^ counter[2]; load[23] <= key[2] ^ counter[2]; load[24] <= key[3] ^ counter[3]; load[25] <= key[3] ^ counter[3]; load[26] <= key[3] ^ counter[3]; load[27] <= key[3] ^ counter[3]; load[28] <= key[3] ^ counter[3]; load[29] <= key[3] ^ counter[3]; load[30] <= key[3] ^ counter[3]; load[31] <= key[3] ^ counter[3]; load[32] <= key[4] ^ counter[4]; load[33] <= key[4] ^ counter[4]; load[34] <= key[4] ^ counter[4]; load[35] <= key[4] ^ counter[4]; load[36] <= key[4] ^ counter[4]; load[37] <= key[4] ^ counter[4]; load[38] <= key[4] ^ counter[4]; load[39] <= key[4] ^ counter[4]; load[40] <= key[5] ^ counter[5]; load[41] <= key[5] ^ counter[5]; load[42] <= key[5] ^ counter[5]; load[43] <= key[5] ^ counter[5]; load[44] <= key[5] ^ counter[5]; load[45] <= key[5] ^ counter[5]; load[46] <= key[5] ^ counter[5]; load[47] <= key[5] ^ counter[5]; load[48] <= key[6] ^ counter[6]; load[49] <= key[6] ^ counter[6]; load[50] <= key[6] ^ counter[6]; load[51] <= key[6] ^ counter[6]; load[52] <= key[6] ^ counter[6]; load[53] <= key[6] ^ counter[6]; load[54] <= key[6] ^ counter[6]; load[55] <= key[6] ^ counter[6]; load[56] <= key[7] ^ counter[7]; load[57] <= key[7] ^ counter[7]; load[58] <= key[7] ^ counter[7]; load[59] <= key[7] ^ counter[7]; load[60] <= key[7] ^ counter[7]; load[61] <= key[7] ^ counter[7]; load[62] <= key[7] ^ counter[7]; load[63] <= key[7] ^ counter[7]; end

endmodule

RTL/AES-T1100/AES-T1100_tb.v
`timescale 1ns/1ps
module AES_T1100_tb();
reg clk;
reg rst;
reg [127:0] state;
reg [127:0] key;
wire [63:0] Capacitance;

// 实例化待测模块
top uut (
    .clk(clk),
    .rst(rst),
    .state(state),
    .key(key),
    .Capacitance(Capacitance)
    );

// 时钟激励
initial begin
    clk = 0;
    forever #5 clk = ~clk;
end

// 复位激励
initial begin
    rst = 1;
    #10;
    rst = 0;
end

integer i;
initial begin
    state = 0;
    key = 0;
    #10;
    for(i = 0; i < 4000; i = i + 1) begin
        $display("********Period %d********", i);
        state = $random;
        key = $random;
        #10;
    end
    $finish;
end
initial begin
    $dumpfile("wave.vcd");
    $dumpvars(0, AES_T1100_tb);
end

endmodule

RTL/AES-T1100/wave.vcd
$date
	Thu Apr 10 10:14:11 2025
$end
$version
	Icarus Verilog
$end
$timescale
	1ps
$end
$scope module AES_T1100_tb $end
$var wire 64 ! Capacitance [63:0] $end
$var reg 1 " clk $end
$var reg 128 # key [127:0] $end
$var reg 1 $ rst $end
$var reg 128 % state [127:0] $end
$var integer 32 & i [31:0] $end
$scope module uut $end
$var wire 64 ' Capacitance [63:0] $end
$var wire 1 " clk $end
$var wire 20 ( counter [19:0] $end
$var wire 1 ) d0 $end
$var wire 128 * data [127:0] $end
$var wire 128 + key [127:0] $end
$var wire 20 , lfsr [19:0] $end
$var wire 1 $ rst $end
$var wire 128 - state [127:0] $end
$var reg 1 . State0 $end
$var reg 1 / State1 $end
$var reg 1 0 State2 $end
$var reg 1 1 State3 $end
$var reg 1 2 Tj_Trig $end
$var reg 20 3 lfsr_stream [19:0] $end
$var reg 64 4 load [63:0] $end
$upscope $end
$upscope $end
$enddefinitions $end
$comment Show the parameter values. $end
$dumpall
$end
#0
$dumpvars
bx 4
bx 3
02
01
00
0/
0.
b0 -
bx ,
b0 +
b0 *
x)
bx (
bx '
bx &
b0 %
1$
b0 #
0"
bx !
$end
#5000
0)
b0 (
b0 ,
b0 3
1"
#10000
0"
b11111111111111111111111111111111111111111111111111111111111111111111111111111111111111111111111111000000100010010101111010000001 #
b11111111111111111111111111111111111111111111111111111111111111111111111111111111111111111111111111000000100010010101111010000001 +
b10010000101010011010100100100 *
b10010000101010011010100100100 %
b10010000101010011010100100100 -
b0 &
0$
#15000
b1111111100000000000000000000000000000000000000000000000011111111 !
b1111111100000000000000000000000000000000000000000000000011111111 '
b1111111100000000000000000000000000000000000000000000000011111111 4
1"
#20000
0"
b11111111111111111111111111111111111111111111111111111111111111111111111111111111111111111111111110110001111100000101011001100011 #
b11111111111111111111111111111111111111111111111111111111111111111111111111111111111111111111111110110001111100000101011001100011 +
b11111111111111111111111111111111111111111111111111111111111111111111111111111111111111111111111110000100100001001101011000001001 *
b11111111111111111111111111111111111111111111111111111111111111111111111111111111111111111111111110000100100001001101011000001001 %
b11111111111111111111111111111111111111111111111111111111111111111111111111111111111111111111111110000100100001001101011000001001 -
b1 &
#25000
b11111111111111110000000000000000000000001111111111111111 !
b11111111111111110000000000000000000000001111111111111111 '
b11111111111111110000000000000000000000001111111111111111 4
1"
#30000
0"
b1000110110111111001100110001101 #
b1000110110111111001100110001101 +
b110101110010111101100001101 *
b110101110010111101100001101 %
b110101110010111101100001101 -
b10 &
#35000
b1111111100000000000000000000000011111111111111110000000011111111 !
b1111111100000000000000000000000011111111111111110000000011111111 '
b1111111100000000000000000000000011111111111111110000000011111111 4
1"
#40000
0"
b11111111111111111111111111111111111111111111111111111111111111111111111111111111111111111111111110001001001101110101001000010010 #
b11111111111111111111111111111111111111111111111111111111111111111111111111111111111111111111111110001001001101110101001000010010 +
b11111111111111111111111111111111111111111111111111111111111111111111111111111111111111111111111110110010110000101000010001100101 *
b11111111111111111111111111111111111111111111111111111111111111111111111111111111111111111111111110110010110000101000010001100101 %
b11111111111111111111111111111111111111111111111111111111111111111111111111111111111111111111111110110010110000101000010001100101 -
b11 &
#45000
b1111111100000000000000001111111100000000 !
b1111111100000000000000001111111100000000 '
b1111111100000000000000001111111100000000 4
1"
#50000
0"
b110110101111100110100001101 #
b110110101111100110100001101 +
b111100111110001100000001 *
b111100111110001100000001 %
b111100111110001100000001 -
b100 &
#55000
b11111111111111110000000011111111 !
b11111111111111110000000011111111 '
b11111111111111110000000011111111 4
1"
#60000
0"
b11110100011011100110100111101 #
b11110100011011100110100111101 +
b111011001000111111000101110110 *
b111011001000111111000101110110 %
b111011001000111111000101110110 -
b101 &
#65000
b111111111111111111111111111111110000000011111111 !
b111111111111111111111111111111110000000011111111 '
b111111111111111111111111111111110000000011111111 4
1"
#70000
0"
b1000110001011011111011110001100 #
b1000110001011011111011110001100 +
b1110110110101000101011111101101 *
b1110110110101000101011111101101 %
b1110110110101000101011111101101 -
b110 &
#75000
b1111111100000000000000000000000011111111111111110000000000000000 !
b1111111100000000000000000000000011111111111111110000000000000000 '
b1111111100000000000000000000000011111111111111110000000000000000 4
1"
#80000
0"
b11111111111111111111111111111111111111111111111111111111111111111111111111111111111111111111111111100011001101110010010011000110 #
b11111111111111111111111111111111111111111111111111111111111111111111111111111111111111111111111111100011001101110010010011000110 +
b1111100111111011110100111111001 *
b1111100111111011110100111111001 %
b1111100111111011110100111111001 -
b111 &
#85000
b1111111111111111000000000000000000000000111111111111111100000000 !
b1111111111111111000000000000000000000000111111111111111100000000 '
b1111111111111111000000000000000000000000111111111111111100000000 4
1"
#90000
0"
b11111111111111111111111111111111111111111111111111111111111111111111111111111111111111111111111111010101000100111101001010101010 #
b11111111111111111111111111111111111111111111111111111111111111111111111111111111111111111111111111010101000100111101001010101010 +
b11111111111111111111111111111111111111111111111111111111111111111111111111111111111111111111111111100010111101111000010011000101 *
b11111111111111111111111111111111111111111111111111111111111111111111111111111111111111111111111111100010111101111000010011000101 %
b11111111111111111111111111111111111111111111111111111111111111111111111111111111111111111111111111100010111101111000010011000101 -
b1000 &
#95000
b1111111100000000111111110000000011111111000000001111111100000000 !
b1111111100000000111111110000000011111111000000001111111100000000 '
b1111111100000000111111110000000011111111000000001111111100000000 4
1"
#100000
0"
b11111111111111111111111111111111111111111111111111111111111111111111111111111111111111111111111110111011110100100111001001110111 #
b11111111111111111111111111111111111111111111111111111111111111111111111111111111111111111111111110111011110100100111001001110111 +
b1110010101011111111011111100101 *
b1110010101011111111011111100101 %
b1110010101011111111011111100101 -
b1001 &
#105000
b11111111111111111111111100000000111111111111111111111111 !
b11111111111111111111111100000000111111111111111111111111 '
b11111111111111111111111100000000111111111111111111111111 4
1"
#110000
0"
b1000111111011001101101110001111 #
b1000111111011001101101110001111 +
b11111111111111111111111111111111111111111111111111111111111111111111111111111111111111111111111110001001001100101101011000010010 *
b11111111111111111111111111111111111111111111111111111111111111111111111111111111111111111111111110001001001100101101011000010010 %
b11111111111111111111111111111111111111111111111111111111111111111111111111111111111111111111111110001001001100101101011000010010 -
b1010 &
#115000
b1111111100000000000000000000000011111111111111111111111111111111 !
b1111111100000000000000000000000011111111111111111111111111111111 '
b1111111100000000000000000000000011111111111111111111111111111111 4
1"
#120000
0"
b11111111111111111111111111111111111111111111111111111111111111111111111111111111111111111111111111100111011101101001011011001110 #
b11111111111111111111111111111111111111111111111111111111111111111111111111111111111111111111111111100111011101101001011011001110 +
b1111001001100000110100111110010 *
b1111001001100000110100111110010 %
b1111001001100000110100111110010 -
b1011 &
#125000
b1111111111111111000000000000000011111111111111111111111100000000 !
b1111111111111111000000000000000011111111111111111111111100000000 '
b1111111111111111000000000000000011111111111111111111111100000000 4
1"
#130000
0"
b11111111111111111111111111111111111111111111111111111111111111111111111111111111111111111111111111100010110010100100111011000101 #
b11111111111111111111111111111111111111111111111111111111111111111111111111111111111111111111111111100010110010100100111011000101 +
b11111111111111111111111111111111111111111111111111111111111111111111111111111111111111111111111111110100000000000111101011101000 *
b11111111111111111111111111111111111111111111111111111111111111111111111111111111111111111111111111110100000000000111101011101000 %
b11111111111111111111111111111111111111111111111111111111111111111111111111111111111111111111111111110100000000000111101011101000 -
b1100 &
#135000
b1111111111111111000000000000000000000000111111110000000011111111 !
b1111111111111111000000000000000000000000111111110000000011111111 '
b1111111111111111000000000000000000000000111111110000000011111111 4
1"
#140000
0"
b11111111111111111111111111111111111111111111111111111111111111111111111111111111111111111111111111011110100011100010100010111101 #
b11111111111111111111111111111111111111111111111111111111111111111111111111111111111111111111111111011110100011100010100010111101 +
b101110010110000100100101011100 *
b101110010110000100100101011100 %
b101110010110000100100101011100 -
b1101 &
#145000
b1111111100000000111111111111111111111111111111110000000011111111 !
b1111111100000000111111111111111111111111111111110000000011111111 '
b1111111100000000111111111111111111111111111111110000000011111111 4
1"
#150000
0"
b11111111111111111111111111111111111111111111111111111111111111111111111111111111111111111111111110110010101001110010011001100101 #
b11111111111111111111111111111111111111111111111111111111111111111111111111111111111111111111111110110010101001110010011001100101 +
b11111111111111111111111111111111111111111111111111111111111111111111111111111111111111111111111110010110101010110101100000101101 *
b11111111111111111111111111111111111111111111111111111111111111111111111111111111111111111111111110010110101010110101100000101101 %
b11111111111111111111111111111111111111111111111111111111111111111111111111111111111111111111111110010110101010110101100000101101 -
b1110 &
#155000
b11111111111111110000000000000000111111110000000011111111 !
b11111111111111110000000000000000111111110000000011111111 '
b11111111111111110000000000000000111111110000000011111111 4
1"
#160000
0"
b101011100111000011100001010 #
b101011100111000011100001010 +
b11111111111111111111111111111111111111111111111111111111111111111111111111111111111111111111111110110001111011110110001001100011 *
b11111111111111111111111111111111111111111111111111111111111111111111111111111111111111111111111110110001111011110110001001100011 %
b11111111111111111111111111111111111111111111111111111111111111111111111111111111111111111111111110110001111011110110001001100011 -
b1111 &
#165000
b11111111000000001111111100000000 !
b11111111000000001111111100000000 '
b11111111000000001111111100000000 4
1"
#170000
0"
b10000011001000010000100100000 #
b10000011001000010000100100000 +
b11111111111111111111111111111111111111111111111111111111111111111111111111111111111111111111111111000000001110110010001010000000 *
b11111111111111111111111111111111111111111111111111111111111111111111111111111111111111111111111111000000001110110010001010000000 %
b11111111111111111111111111111111111111111111111111111111111111111111111111111111111111111111111111000000001110110010001010000000 -
b10000 &
#175000
b111111110000000000000000000000000000000000000000 !
b111111110000000000000000000000000000000000000000 '
b111111110000000000000000000000000000000000000000 4
1"
#180000
0"
b11111111111111111111111111111111111111111111111111111111111111111111111111111111111111111111111111001110110011001100110010011101 #
b11111111111111111111111111111111111111111111111111111111111111111111111111111111111111111111111111001110110011001100110010011101 +
b1010101011110000100010110101010 *
b1010101011110000100010110101010 %
b1010101011110000100010110101010 -
b10001 &
#185000
b1111111100000000000000001111111111111111111111110000000011111111 !
b1111111100000000000000001111111111111111111111110000000011111111 '
b1111111100000000000000001111111111111111111111110000000011111111 4
1"
#190000
0"
b11111111111111111111111111111111111111111111111111111111111111111111111111111111111111111111111110001001100000111011100000010011 #
b11111111111111111111111111111111111111111111111111111111111111111111111111111111111111111111111110001001100000111011100000010011 +
b11111111111111111111111111111111111111111111111111111111111111111111111111111111111111111111111111001011001000000011111010010110 *
b11111111111111111111111111111111111111111111111111111111111111111111111111111111111111111111111111001011001000000011111010010110 %
b11111111111111111111111111111111111111111111111111111111111111111111111111111111111111111111111111001011001000000011111010010110 -
b10010 &
#195000
b1111111100000000000000001111111111111111 !
b1111111100000000000000001111111111111111 '
b1111111100000000000000001111111111111111 4
1"
#200000
0"
b11111111111111111111111111111111111111111111111111111111111111111111111111111111111111111111111110101001101001111101011001010011 #
b11111111111111111111111111111111111111111111111111111111111111111111111111111111111111111111111110101001101001111101011001010011 +
b11111111111111111111111111111111111111111111111111111111111111111111111111111111111111111111111110000110101111000011100000001101 *
b11111111111111111111111111111111111111111111111111111111111111111111111111111111111111111111111110000110101111000011100000001101 %
b11111111111111111111111111111111111111111111111111111111111111111111111111111111111111111111111110000110101111000011100000001101 -
b10011 &
#205000
b11111111000000001111111100000000000000001111111111111111 !
b11111111000000001111111100000000000000001111111111111111 '
b11111111000000001111111100000000000000001111111111111111 4
1"
#210000
0"
b11111111111111111111111111111111111111111111111111111111111111111111111111111111111111111111111111101010101001100010101011010101 #
b11111111111111111111111111111111111111111111111111111111111111111111111111111111111111111111111111101010101001100010101011010101 +
b110101100111111101110101101011 *
b110101100111111101110101101011 %
b110101100111111101110101101011 -
b10100 &
#215000
b1111111111111111000000001111111100000000111111110000000011111111 !
b1111111111111111000000001111111100000000111111110000000011111111 '
b1111111111111111000000001111111100000000111111110000000011111111 4
1"
#220000
0"
b11111111111111111111111111111111111111111111111111111111111111111111111111111111111111111111111111010111010101100011111010101110 #
b11111111111111111111111111111111111111111111111111111111111111111111111111111111111111111111111111010111010101100011111010101110 +
b11111111111111111111111111111111111111111111111111111111111111111111111111111111111111111111111110000001000101110100101000000010 *
b11111111111111111111111111111111111111111111111111111111111111111111111111111111111111111111111110000001000101110100101000000010 %
b11111111111111111111111111111111111111111111111111111111111111111111111111111111111111111111111110000001000101110100101000000010 -
b10101 &
#225000
b1111111100000000111111110000000011111111111111111111111100000000 !
b1111111100000000111111110000000011111111111111111111111100000000 '
b1111111100000000111111110000000011111111111111111111111100000000 4
1"
#230000
0"
b11111111111111111111111111111111111111111111111111111111111111111111111111111111111111111111111111100111110001010111001011001111 #
b11111111111111111111111111111111111111111111111111111111111111111111111111111111111111111111111111100111110001010111001011001111 +
b1110111111111110100100011101 *
b1110111111111110100100011101 %
b1110111111111110100100011101 -
b10110 &
#235000
b1111111111111111000000000000000011111111111111111111111111111111 !
b1111111111111111000000000000000011111111111111111111111111111111 '
b1111111111111111000000000000000011111111111111111111111111111111 4
1"
#240000
0"
b101000010010110010100001010 #
b101000010010110010100001010 +
b10001100001000100100100100011 *
b10001100001000100100100100011 %
b10001100001000100100100100011 -
b10111 &
#245000
b11111111000000001111111100000000 !
b11111111000000001111111100000000 '
b11111111000000001111111100000000 4
1"
#250000
0"
b11111111111111111111111111111111111111111111111111111111111111111111111111111111111111111111111110011110001100010100110000111100 #
b11111111111111111111111111111111111111111111111111111111111111111111111111111111111111111111111110011110001100010100110000111100 +
b11111111111111111111111111111111111111111111111111111111111111111111111111111111111111111111111111100101011100110000101011001010 *
b11111111111111111111111111111111111111111111111111111111111111111111111111111111111111111111111111100101011100110000101011001010 %
b11111111111111111111111111111111111111111111111111111111111111111111111111111111111111111111111111100101011100110000101011001010 -
b11000 &
#255000
b111111111111111111111111111111110000000000000000 !
b111111111111111111111111111111110000000000000000 '
b111111111111111111111111111111110000000000000000 4
1"
#260000
0"
b1000101001011100110000110001010 #
b1000101001011100110000110001010 +
b1111001011010001011110111110010 *
b1111001011010001011110111110010 %
b1111001011010001011110111110010 -
b11001 &
#265000
b1111111100000000000000000000000011111111000000001111111100000000 !
b1111111100000000000000000000000011111111000000001111111100000000 '
b1111111100000000000000000000000011111111000000001111111100000000 4
1"
#270000
0"
b11111111111111111111111111111111111111111111111111111111111111111111111111111111111111111111111111101100010010110011010011011000 #
b11111111111111111111111111111111111111111111111111111111111111111111111111111111111111111111111111101100010010110011010011011000 +
b100000110001001011001101000001 *
b100000110001001011001101000001 %
b100000110001001011001101000001 -
b11010 &
#275000
b1111111111111111000000001111111111111111000000000000000000000000 !
b1111111111111111000000001111111111111111000000000000000000000000 '
b1111111111111111000000001111111111111111000000000000000000000000 4
1"
#280000
0"
b11111111111111111111111111111111111111111111111111111111111111111111111111111111111111111111111111000100100010100001001010001001 #
b11111111111111111111111111111111111111111111111111111111111111111111111111111111111111111111111111000100100010100001001010001001 +
b111100001000001111001101111000 *
b111100001000001111001101111000 %
b111100001000001111001101111000 -
b11011 &
#285000
b1111111100000000000000000000000011111111000000000000000011111111 !
b1111111100000000000000000000000011111111000000000000000011111111 '
b1111111100000000000000000000000011111111000000000000000011111111 4
1"
#290000
0"
b1011011000000100110010110110110 #
b1011011000000100110010110110110 +
b1110101110001010000110111101011 *
b1110101110001010000110111101011 %
b1110101110001010000110111101011 -
b11100 &
#295000
b1111111100000000111111111111111100000000111111111111111100000000 !
b1111111100000000111111111111111100000000111111111111111100000000 '
b1111111100000000111111111111111100000000111111111111111100000000 4
1"
#300000
0"
b1010111000101010001001110101110 #
b1010111000101010001001110101110 +
b1100011010010111111100111000110 *
b1100011010010111111100111000110 %
b1100011010010111111100111000110 -
b11101 &
#305000
b1111111100000000111111110000000011111111111111111111111100000000 !
b1111111100000000111111110000000011111111111111111111111100000000 '
b1111111100000000111111110000000011111111111111111111111100000000 4
1"
#310000
0"
b10101000011111101110100101010 #
b10101000011111101110100101010 +
b11111111111111111111111111111111111111111111111111111111111111111111111111111111111111111111111111011110011101010000001010111100 *
b11111111111111111111111111111111111111111111111111111111111111111111111111111111111111111111111111011110011101010000001010111100 %
b11111111111111111111111111111111111111111111111111111111111111111111111111111111111111111111111111011110011101010000001010111100 -
b11110 &
#315000
b111111110000000011111111000000001111111100000000 !
b111111110000000011111111000000001111111100000000 '
b111111110000000011111111000000001111111100000000 4
1"
#320000
0"
b11111111111111111111111111111111111111111111111111111111111111111111111111111111111111111111111110111000100101111011111001110001 #
b11111111111111111111111111111111111111111111111111111111111111111111111111111111111111111111111110111000100101111011111001110001 +
b11111111111111111111111111111111111111111111111111111111111111111111111111111111111111111111111110000101110101111001101000001011 *
b11111111111111111111111111111111111111111111111111111111111111111111111111111111111111111111111110000101110101111001101000001011 %
b11111111111111111111111111111111111111111111111111111111111111111111111111111111111111111111111110000101110101111001101000001011 -
b11111 &
#325000
b11111111111111111111111100000000000000000000000011111111 !
b11111111111111111111111100000000000000000000000011111111 '
b11111111111111111111111100000000000000000000000011111111 4
1"
#330000
0"
b100111111100100101010101001111 #
b100111111100100101010101001111 +
b1000010111100100100000110000101 *
b1000010111100100100000110000101 %
b1000010111100100100000110000101 -
b100000 &
#335000
b11111111000000000000000011111111111111111111111111111111 !
b11111111000000000000000011111111111111111111111111111111 '
b11111111000000000000000011111111111111111111111111111111 4
1"
#340000
0"
b11101000001100011001100111010 #
b11101000001100011001100111010 +
b11111111111111111111111111111111111111111111111111111111111111111111111111111111111111111111111110011101110011000110000000111011 *
b11111111111111111111111111111111111111111111111111111111111111111111111111111111111111111111111110011101110011000110000000111011 %
b11111111111111111111111111111111111111111111111111111111111111111111111111111111111111111111111110011101110011000110000000111011 -
b100001 &
#345000
b111111111111111111111111000000001111111100000000 !
b111111111111111111111111000000001111111100000000 '
b111111111111111111111111000000001111111100000000 4
1"
#350000
0"
b1010101010100100101100010101 #
b1010101010100100101100010101 +
b11111111111111111111111111111111111111111111111111111111111111111111111111111111111111111111111110111111001000110011001001111110 *
b11111111111111111111111111111111111111111111111111111111111111111111111111111111111111111111111110111111001000110011001001111110 %
b11111111111111111111111111111111111111111111111111111111111111111111111111111111111111111111111110111111001000110011001001111110 -
b100010 &
#355000
b1111111100000000111111110000000011111111 !
b1111111100000000111111110000000011111111 '
b1111111100000000111111110000000011111111 4
1"
#360000
0"
b1101100100111000100101111011001 #
b1101100100111000100101111011001 +
b1111000110110011001101111110001 *
b1111000110110011001101111110001 %
b1111000110110011001101111110001 -
b100011 &
#365000
b1111111111111111000000001111111111111111000000000000000011111111 !
b1111111111111111000000001111111111111111000000000000000011111111 '
b1111111111111111000000001111111111111111000000000000000011111111 4
1"
#370000
0"
b100110001101011111101101001100 #
b100110001101011111101101001100 +
b110001001000110000011101100010 *
b110001001000110000011101100010 %
b110001001000110000011101100010 -
b100100 &
#375000
b11111111000000000000000011111111111111110000000000000000 !
b11111111000000000000000011111111111111110000000000000000 '
b11111111000000000000000011111111111111110000000000000000 4
1"
#380000
0"
b1000111101110011010000110001111 #
b1000111101110011010000110001111 +
b1001111101000010101010110011111 *
b1001111101000010101010110011111 %
b1001111101000010101010110011111 -
b100101 &
#385000
b1111111100000000000000000000000011111111111111111111111111111111 !
b1111111100000000000000000000000011111111111111111111111111111111 '
b1111111100000000000000000000000011111111111111111111111111111111 4
1"
#390000
0"
b11111111111111111111111111111111111111111111111111111111111111111111111111111111111111111111111111011011110011010110000010110111 #
b11111111111111111111111111111111111111111111111111111111111111111111111111111111111111111111111111011011110011010110000010110111 +
b1111100011011011010100111111000 *
b1111100011011011010100111111000 %
b1111100011011011010100111111000 -
b100110 &
#395000
b1111111100000000111111111111111100000000111111111111111111111111 !
b1111111100000000111111111111111100000000111111111111111111111111 '
b1111111100000000111111111111111100000000111111111111111111111111 4
1"
#400000
0"
b11111111111111111111111111111111111111111111111111111111111111111111111111111111111111111111111110101110011111011001010001011100 #
b11111111111111111111111111111111111111111111111111111111111111111111111111111111111111111111111110101110011111011001010001011100 +
b11111111111111111111111111111111111111111111111111111111111111111111111111111111111111111111111111001111110001000101011010011111 *
b11111111111111111111111111111111111111111111111111111111111111111111111111111111111111111111111111001111110001000101011010011111 %
b11111111111111111111111111111111111111111111111111111111111111111111111111111111111111111111111111001111110001000101011010011111 -
b100111 &
#405000
b11111111000000001111111111111111111111110000000000000000 !
b11111111000000001111111111111111111111110000000000000000 '
b11111111000000001111111111111111111111110000000000000000 4
1"
#410000
0"
b1000100110111100011011110001001 #
b1000100110111100011011110001001 +
b11111111111111111111111111111111111111111111111111111111111111111111111111111111111111111111111110101101110010111100000001011011 *
b11111111111111111111111111111111111111111111111111111111111111111111111111111111111111111111111110101101110010111100000001011011 %
b11111111111111111111111111111111111111111111111111111111111111111111111111111111111111111111111110101101110010111100000001011011 -
b101000 &
#415000
b1111111100000000000000000000000011111111000000000000000011111111 !
b1111111100000000000000000000000011111111000000000000000011111111 '
b1111111100000000000000000000000011111111000000000000000011111111 4
1"
#420000
0"
b11111111111111111111111111111111111111111111111111111111111111111111111111111111111111111111111111101000001000110011111011010000 #
b11111111111111111111111111111111111111111111111111111111111111111111111111111111111111111111111111101000001000110011111011010000 +
b11111111111111111111111111111111111111111111111111111111111111111111111111111111111111111111111110100100101011100011001001001001 *
b11111111111111111111111111111111111111111111111111111111111111111111111111111111111111111111111110100100101011100011001001001001 %
b11111111111111111111111111111111111111111111111111111111111111111111111111111111111111111111111110100100101011100011001001001001 -
b101001 &
#425000
b1111111111111111000000001111111100000000000000000000000000000000 !
b1111111111111111000000001111111100000000000000000000000000000000 '
b1111111111111111000000001111111100000000000000000000000000000000 4
1"
#430000
0"
b11111111111111111111111111111111111111111111111111111111111111111111111111111111111111111111111110101000110001111111110001010001 #
b11111111111111111111111111111111111111111111111111111111111111111111111111111111111111111111111110101000110001111111110001010001 +
b11111111111111111111111111111111111111111111111111111111111111111111111111111111111111111111111111101011111111101100000011010111 *
b11111111111111111111111111111111111111111111111111111111111111111111111111111111111111111111111111101011111111101100000011010111 %
b11111111111111111111111111111111111111111111111111111111111111111111111111111111111111111111111111101011111111101100000011010111 -
b101010 &
#435000
b11111111000000001111111100000000000000000000000011111111 !
b11111111000000001111111100000000000000000000000011111111 '
b11111111000000001111111100000000000000000000000011111111 4
1"
#440000
0"
b110000111010111111100001100 #
b110000111010111111100001100 +
b1001011001000010010111110010110 *
b1001011001000010010111110010110 %
b1001011001000010010111110010110 -
b101011 &
#445000
b11111111111111110000000000000000 !
b11111111111111110000000000000000 '
b11111111111111110000000000000000 4
1"
#450000
0"
b1100100010101111110110111001000 #
b1100100010101111110110111001000 +
b11111111111111111111111111111111111111111111111111111111111111111111111111111111111111111111111111100001001011001100111011000010 *
b11111111111111111111111111111111111111111111111111111111111111111111111111111111111111111111111111100001001011001100111011000010 %
b11111111111111111111111111111111111111111111111111111111111111111111111111111111111111111111111111100001001011001100111011000010 -
b101100 &
#455000
b1111111111111111000000000000000011111111000000000000000000000000 !
b1111111111111111000000000000000011111111000000000000000000000000 '
b1111111111111111000000000000000011111111000000000000000000000000 4
1"
#460000
0"
b11110111100101110110100111101 #
b11110111100101110110100111101 +
b11111111111111111111111111111111111111111111111111111111111111111111111111111111111111111111111110111011100000100101101001110111 *
b11111111111111111111111111111111111111111111111111111111111111111111111111111111111111111111111110111011100000100101101001110111 %
b11111111111111111111111111111111111111111111111111111111111111111111111111111111111111111111111110111011100000100101101001110111 -
b101101 &
#465000
b111111111111111111111111111111110000000011111111 !
b111111111111111111111111111111110000000011111111 '
b111111111111111111111111111111110000000011111111 4
1"
#470000
0"
b11111111111111111111111111111111111111111111111111111111111111111111111111111111111111111111111110111111000001010000000001111110 #
b11111111111111111111111111111111111111111111111111111111111111111111111111111111111111111111111110111111000001010000000001111110 +
b1001000011001101101100010010 *
b1001000011001101101100010010 %
b1001000011001101101100010010 -
b101110 &
#475000
b11111111111111111111111111111111111111111111111100000000 !
b11111111111111111111111111111111111111111111111100000000 '
b11111111111111111111111111111111111111111111111100000000 4
1"
#480000
0"
b11100110110011110011100111001 #
b11100110110011110011100111001 +
b110110111001011000000101101101 *
b110110111001011000000101101101 %
b110110111001011000000101101101 -
b101111 &
#485000
b111111111111111111111111000000000000000011111111 !
b111111111111111111111111000000000000000011111111 '
b111111111111111111111111000000000000000011111111 4
1"
#490000
0"
b11111111111111111111111111111111111111111111111111111111111111111111111111111111111111111111111111101001111010111111011011010011 #
b11111111111111111111111111111111111111111111111111111111111111111111111111111111111111111111111111101001111010111111011011010011 +
b1111110100101000111100011111 *
b1111110100101000111100011111 %
b1111110100101000111100011111 -
b110000 &
#495000
b1111111111111111000000001111111100000000000000001111111111111111 !
b1111111111111111000000001111111100000000000000001111111111111111 '
b1111111111111111000000001111111100000000000000001111111111111111 4
1"
