RTL/or1200_ic_fsm/or1200_ic_fsm_1.v
//////////////////////////////////////////////////////////////////////
////                                                              ////
////  OR1200's IC FSM                                             ////
////                                                              ////
////  This file is part of the OpenRISC 1200 project              ////
////  http://opencores.org/project,or1k                           ////
////                                                              ////
////  Description                                                 ////
////  Insn cache state machine                                    ////
////                                                              ////
////  To Do:                                                      ////
////   - make it smaller and faster                               ////
////                                                              ////
////  Author(s):                                                  ////
////      - Damjan Lampret, lampret@opencores.org                 ////
////                                                              ////
//////////////////////////////////////////////////////////////////////
////                                                              ////
//// Copyright (C) 2000 Authors and OPENCORES.ORG                 ////
////                                                              ////
//// This source file may be used and distributed without         ////
//// restriction provided that this copyright statement is not    ////
//// removed from the file and that any derivative work contains  ////
//// the original copyright notice and the associated disclaimer. ////
////                                                              ////
//// This source file is free software; you can redistribute it   ////
//// and/or modify it under the terms of the GNU Lesser General   ////
//// Public License as published by the Free Software Foundation; ////
//// either version 2.1 of the License, or (at your option) any   ////
//// later version.                                               ////
////                                                              ////
//// This source is distributed in the hope that it will be       ////
//// useful, but WITHOUT ANY WARRANTY; without even the implied   ////
//// warranty of MERCHANTABILITY or FITNESS FOR A PARTICULAR      ////
//// PURPOSE.  See the GNU Lesser General Public License for more ////
//// details.                                                     ////
////                                                              ////
//// You should have received a copy of the GNU Lesser General    ////
//// Public License along with this source; if not, download it   ////
//// from http://www.opencores.org/lgpl.shtml                     ////
////                                                              ////
//////////////////////////////////////////////////////////////////////
//
// $Log: or1200_ic_fsm.v,v $
// Revision 2.0  2010/06/30 11:00:00  ORSoC
// Minor update: 
// Bugs fixed. 
//


// `define OR1200_ICFSM_IDLE	2'd0
// `define OR1200_ICFSM_CFETCH	2'd1
// `define OR1200_ICFSM_LREFILL3	2'd2
// `define OR1200_ICFSM_IFETCH	2'd3

//
// Instruction cache FSM
//

module or1200_ic_fsm (
    // Clock and reset
    clk,
    rst,

    // Internal i/f to top level IC
    ic_en,
    icqmem_cycstb_i,
    icqmem_ci_i,
    tagcomp_miss,
    biudata_valid,
    biudata_error,
    start_addr,
    saved_addr,
    icram_we,
    tag_we,
    biu_read,
    first_hit_ack,
    first_miss_ack,
    first_miss_err,
    burst
);

  //
  // I/O
  //
  input wire clk;
  input wire rst;
  input wire ic_en;
  input wire icqmem_cycstb_i;
  input wire icqmem_ci_i;
  input wire tagcomp_miss;
  input wire biudata_valid;
  input wire biudata_error;
  input wire [31:0] start_addr;
  output wire [31:0] saved_addr;
  output wire [3:0] icram_we;
  output wire biu_read;
  output wire first_hit_ack;
  output wire first_miss_ack;
  output wire first_miss_err;
  output wire burst;
  output wire tag_we;

  //
  // Internal wires and regs
  //
  reg [31:0] saved_addr_r;
  reg [ 1:0] state;
  reg [ 3:0] cnt;
  reg        hitmiss_eval;
  reg        load;
  reg        cache_inhibit;
  reg        last_eval_miss;  // JPB
  reg [31:0] temp_addr;

  //
  // Generate of ICRAM write enables
  //
  assign icram_we = {4{biu_read & biudata_valid & !cache_inhibit}};
  assign tag_we = biu_read & biudata_valid & !cache_inhibit;

  //
  // BIU read and write
  //
  assign biu_read = (hitmiss_eval & tagcomp_miss) | (!hitmiss_eval & load);

  //assign saved_addr = hitmiss_eval ? start_addr : saved_addr_r;
  assign saved_addr = saved_addr_r;

  // Asserted when a cache hit occurs and the first word is ready/valid
  assign first_hit_ack = (state == 2'd1) & hitmiss_eval & !tagcomp_miss & !cache_inhibit;

  // Asserted when a cache miss occurs, but the first word of the new
  // cache line is ready (on the bus)
  // Cache hits overpower bus data
  assign first_miss_ack = (state == 2'd1) & biudata_valid & ~first_hit_ack;

  // Asserted when a cache occurs, but there was a bus error with handling
  // the old line or fetching the new line
  assign first_miss_err = (state == 2'd1) & biudata_error;

  //
  // Assert burst when doing reload of complete cache line
  //
  assign burst = (state == 2'd1) & tagcomp_miss & !cache_inhibit | (state == 2'd2);

  //
  // Main IC FSM
  //
  always @(posedge clk or posedge rst) begin
    if (rst == 1'b1) begin
      state <= 2'd0;
      saved_addr_r <= 32'b0;
      hitmiss_eval <= 1'b0;
      load <= 1'b0;
      cnt <= 4'd0;
      cache_inhibit <= 1'b0;
      last_eval_miss <= 0;  // JPB

    end else
      case (state)  // synopsys parallel_case
        2'd0:
        if (ic_en & icqmem_cycstb_i) begin  // fetch
          state <= 2'd1;
          saved_addr_r <= start_addr;
          hitmiss_eval <= 1'b1;
          load <= 1'b1;
          cache_inhibit <= icqmem_ci_i;
          last_eval_miss <= 0;  // JPB
        end else begin  // idle
          hitmiss_eval <= 1'b0;
          load <= 1'b0;
          cache_inhibit <= 1'b0;
        end
        2'd1: begin  // fetch
          temp_addr = saved_addr_r;
          if (icqmem_cycstb_i & icqmem_ci_i) cache_inhibit <= 1'b1;

          if (hitmiss_eval) begin
            temp_addr = {start_addr[31:13], temp_addr[12:0]};
            //saved_addr_r[31:`OR1200_ICTAGL] <= start_addr[31:`OR1200_ICTAGL];
          end

          // Check for stopped cache loads
          // instruction cache turned-off
          if ((!ic_en) || (hitmiss_eval & !icqmem_cycstb_i) || (biudata_error) || (cache_inhibit & biudata_valid)) begin
            state <= 2'd0;
            hitmiss_eval <= 1'b0;
            load <= 1'b0;
            cache_inhibit <= 1'b0;
          end // if ((!ic_en) ||...	     
	     // fetch missed, wait for first fetch and continue filling line
          else if (tagcomp_miss & biudata_valid) begin
            state <= 2'd2;
            temp_addr = {temp_addr[31:4], saved_addr_r[3:2] + 2'b1, temp_addr[1:0]};
            //saved_addr_r[3:2] 
            //  <= saved_addr_r[3:2] + 1;
            hitmiss_eval <= 1'b0;
            cnt <= 4'd8;
            cache_inhibit <= 1'b0;
          end  // fetch aborted (usually caused by exception)
          else if (!icqmem_cycstb_i & !last_eval_miss) begin
            state <= 2'd0;
            hitmiss_eval <= 1'b0;
            load <= 1'b0;
            cache_inhibit <= 1'b0;
          end  // fetch hit, wait in this state for now
          else if (!tagcomp_miss & !icqmem_ci_i) begin
            temp_addr = start_addr;
            cache_inhibit <= 1'b0;
          end else  // fetch in-progress
            hitmiss_eval <= 1'b0;

          if (hitmiss_eval & !tagcomp_miss)  // JPB
            last_eval_miss <= 1;  // JPB

          saved_addr_r <= temp_addr;
        end
        2'd2: begin
          // abort because IC has just been turned off
          if (!ic_en) begin
            // invalidate before IC can be turned on
            state <= 2'd0;
            saved_addr_r <= start_addr;
            hitmiss_eval <= 1'b0;
            load <= 1'b0;
          end  // refill ack, more fetchs to come
          else if (biudata_valid && (|cnt)) begin
            cnt <= cnt - 4'd4;
            saved_addr_r <= {saved_addr_r[31:4], saved_addr_r[3:2] + 2'b1, saved_addr_r[1:0]};
          end else if (biudata_valid) begin
            state <= 2'd0;
            saved_addr_r <= start_addr;
            hitmiss_eval <= 1'b0;
            load <= 1'b0;
          end
        end
        default: state <= 2'd0;
      endcase
  end

endmodule

RTL/or1200_ic_fsm/or1200_ic_fsm_tb.v
`timescale 1ns/1ps
module or1200_ic_fsm_tb();
reg clk;
reg rst;
reg ic_en;
reg icqmem_cycstb_i;
reg icqmem_ci_i;
reg tagcomp_miss;
reg biudata_valid;
reg biudata_error;
reg [31:0] start_addr;
wire [31:0] saved_addr;
wire [3:0] icram_we;
wire biu_read;
wire first_hit_ack;
wire first_miss_ack;
wire first_miss_err;
wire burst;
wire tag_we;

// 实例化待测模块
or1200_ic_fsm uut (
    .clk(clk),
    .rst(rst),
    .ic_en(ic_en),
    .icqmem_cycstb_i(icqmem_cycstb_i),
    .icqmem_ci_i(icqmem_ci_i),
    .tagcomp_miss(tagcomp_miss),
    .biudata_valid(biudata_valid),
    .biudata_error(biudata_error),
    .start_addr(start_addr),
    .saved_addr(saved_addr),
    .icram_we(icram_we),
    .biu_read(biu_read),
    .first_hit_ack(first_hit_ack),
    .first_miss_ack(first_miss_ack),
    .first_miss_err(first_miss_err),
    .burst(burst),
    .tag_we(tag_we)
    );

// 时钟激励
initial begin
    clk = 0;
    forever #5 clk = ~clk;
end

// 复位激励
initial begin
    rst = 1;
    #10;
    rst = 0;
end

integer i;
initial begin
    ic_en = 0;
    icqmem_cycstb_i = 0;
    icqmem_ci_i = 0;
    tagcomp_miss = 0;
    biudata_valid = 0;
    biudata_error = 0;
    start_addr = 0;
    #10;
    for(i = 0; i < 100; i = i + 1) begin
        $display("********Period %d********", i);
        ic_en = $random & 1'd1;
        icqmem_cycstb_i = $random & 1'd1;
        icqmem_ci_i = $random & 1'd1;
        tagcomp_miss = $random & 1'd1;
        biudata_valid = $random & 1'd1;
        biudata_error = $random & 1'd1;
        start_addr = $random;
        if(i == 13) begin ic_en = 1; tagcomp_miss = 1; biudata_valid = 1; biudata_error = 0; icqmem_cycstb_i = 1; icqmem_ci_i = 0; end

        if(i == 15) begin ic_en = 1; biudata_valid = 1; end
        if(i == 16) begin ic_en = 1; biudata_valid = 1; end

        // if(i == 50) begin ic_en = 1; icqmem_cycstb_i = 0; tagcomp_miss = 0; biudata_error = 0; biudata_valid = 0; end

        #10;        
    end
    $finish;
end
initial begin
    $dumpfile("wave.vcd");
    $dumpvars(0, or1200_ic_fsm_tb);
end

endmodule

RTL/or1200_ic_fsm/wave.vcd
$date
	Fri Apr 18 15:08:37 2025
$end
$version
	Icarus Verilog
$end
$timescale
	1ps
$end
$scope module or1200_ic_fsm_tb $end
$var wire 1 ! tag_we $end
$var wire 32 " saved_addr [31:0] $end
$var wire 4 # icram_we [3:0] $end
$var wire 1 $ first_miss_err $end
$var wire 1 % first_miss_ack $end
$var wire 1 & first_hit_ack $end
$var wire 1 ' burst $end
$var wire 1 ( biu_read $end
$var reg 1 ) biudata_error $end
$var reg 1 * biudata_valid $end
$var reg 1 + clk $end
$var reg 1 , ic_en $end
$var reg 1 - icqmem_ci_i $end
$var reg 1 . icqmem_cycstb_i $end
$var reg 1 / rst $end
$var reg 32 0 start_addr [31:0] $end
$var reg 1 1 tagcomp_miss $end
$var integer 32 2 i [31:0] $end
$scope module uut $end
$var wire 1 ( biu_read $end
$var wire 1 ) biudata_error $end
$var wire 1 * biudata_valid $end
$var wire 1 ' burst $end
$var wire 1 + clk $end
$var wire 1 & first_hit_ack $end
$var wire 1 % first_miss_ack $end
$var wire 1 $ first_miss_err $end
$var wire 1 , ic_en $end
$var wire 1 - icqmem_ci_i $end
$var wire 1 . icqmem_cycstb_i $end
$var wire 1 / rst $end
$var wire 32 3 saved_addr [31:0] $end
$var wire 32 4 start_addr [31:0] $end
$var wire 1 ! tag_we $end
$var wire 1 1 tagcomp_miss $end
$var wire 4 5 icram_we [3:0] $end
$var reg 1 6 cache_inhibit $end
$var reg 4 7 cnt [3:0] $end
$var reg 1 8 hitmiss_eval $end
$var reg 1 9 last_eval_miss $end
$var reg 1 : load $end
$var reg 32 ; saved_addr_r [31:0] $end
$var reg 2 < state [1:0] $end
$var reg 32 = temp_addr [31:0] $end
$upscope $end
$upscope $end
$enddefinitions $end
$comment Show the parameter values. $end
$dumpall
$end
#0
$dumpvars
bx =
b0 <
b0 ;
0:
09
08
b0 7
x6
b0 5
b0 4
b0 3
bx 2
01
b0 0
1/
0.
0-
0,
0+
0*
0)
0(
0'
0&
0%
0$
b0 #
b0 "
0!
$end
#5000
1+
#10000
0+
b10110010110000101000010001100101 0
b10110010110000101000010001100101 4
1)
1*
11
1-
1.
b0 2
0/
#15000
06
1+
#20000
0+
b1000110001011011111011110001100 0
b1000110001011011111011110001100 4
01
b1 2
#25000
1+
#30000
0+
b10001001001100101101011000010010 0
b10001001001100101101011000010010 4
0.
1,
b10 2
#35000
1+
#40000
0+
b11011110100011100010100010111101 0
b11011110100011100010100010111101 4
0)
0-
b11 2
#45000
1+
#50000
0+
b1010101011110000100010110101010 0
b1010101011110000100010110101010 4
0*
1-
1.
b100 2
#55000
16
1:
18
b1010101011110000100010110101010 "
b1010101011110000100010110101010 3
b1010101011110000100010110101010 ;
b1 <
1+
#60000
1%
1(
1$
0+
b11101010101001100010101011010101 0
b11101010101001100010101011010101 4
1)
1*
11
0.
b101 2
#65000
0(
0%
b0 #
b0 5
0!
0$
b11101010101001100010010110101010 "
b11101010101001100010010110101010 3
b11101010101001100010010110101010 ;
06
0:
08
b0 <
b11101010101001100010010110101010 =
1+
#70000
0+
b11100101011100110000101011001010 0
b11100101011100110000101011001010 4
0)
0,
b110 2
#75000
1+
#80000
0+
b11000100100010100001001010001001 0
b11000100100010100001001010001001 4
0*
0-
b111 2
#85000
1+
#90000
0+
b10000101110101111001101000001011 0
b10000101110101111001101000001011 4
01
1,
b1000 2
#95000
1+
#100000
0+
b1010101010100100101100010101 0
b1010101010100100101100010101 4
11
1-
1.
b1001 2
#105000
1(
16
1:
18
b1010101010100100101100010101 "
b1010101010100100101100010101 3
b1010101010100100101100010101 ;
b1 <
1+
#110000
1%
0(
1$
0+
b1111100011011011010100111111000 0
b1111100011011011010100111111000 4
1)
1*
01
0-
b1010 2
#115000
0%
0&
0$
b1111100011011011010101100010101 "
b1111100011011011010101100010101 3
b1111100011011011010101100010101 ;
19
06
0:
08
b0 <
b1111100011011011010101100010101 =
1+
#120000
0+
b11101000001000110011111011010000 0
b11101000001000110011111011010000 4
11
b1011 2
#125000
1!
b1111 #
b1111 5
1'
1(
1%
1$
09
1:
18
b11101000001000110011111011010000 "
b11101000001000110011111011010000 3
b11101000001000110011111011010000 ;
b1 <
1+
#130000
0'
b0 #
b0 5
0!
0%
0(
1&
0$
0+
b10111011100000100101101001110111 0
b10111011100000100101101001110111 4
0)
0*
01
b1100 2
#135000
b10111011100000100101101001110111 "
b10111011100000100101101001110111 3
b10111011100000100101101001110111 ;
19
b10111011100000100101101001110111 =
1+
#140000
1!
b1111 #
b1111 5
1%
1'
1(
0&
0+
b11101001111010111111011011010011 0
b11101001111010111111011011010011 4
0)
1*
11
1.
b1101 2
#145000
0%
b11101001111010111111101001111011 "
b11101001111010111111101001111011 3
b11101001111010111111101001111011 ;
b1000 7
08
b10 <
b11101001111010111111101001111011 =
1+
#150000
0+
b101100000101010110001101011000 0
b101100000101010110001101011000 4
1-
0.
b1110 2
#155000
b11101001111010111111101001111111 "
b11101001111010111111101001111111 3
b11101001111010111111101001111111 ;
b100 7
1+
#160000
0+
b11010001100010111011010010100011 0
b11010001100010111011010010100011 4
1)
1*
01
0-
1,
b1111 2
#165000
b11101001111010111111101001110011 "
b11101001111010111111101001110011 3
b11101001111010111111101001110011 ;
b0 7
1+
#170000
0+
b11110011000010010001101011100110 0
b11110011000010010001101011100110 4
1-
1.
b10000 2
#175000
0!
b0 #
b0 5
0(
0'
0:
b11110011000010010001101011100110 "
b11110011000010010001101011100110 3
b11110011000010010001101011100110 ;
b0 <
1+
#180000
0+
b11101111101111101001010011011111 0
b11101111101111101001010011011111 4
0,
b10001 2
#185000
1+
#190000
0+
b1101110010111011010110111011100 0
b1101110010111011010110111011100 4
0)
0-
0.
1,
b10010 2
#195000
1+
#200000
0+
b10000101001100010011010000001010 0
b10000101001100010011010000001010 4
1)
0*
1-
1.
0,
b10011 2
#205000
1+
#210000
0+
b10000010001111110010110000000100 0
b10000010001111110010110000000100 4
0.
b10100 2
#215000
1+
#220000
0+
b1100101001110110100100111001010 0
b1100101001110110100100111001010 4
0)
1*
11
1.
1,
b10101 2
#225000
1(
1%
09
16
1:
18
b1100101001110110100100111001010 "
b1100101001110110100100111001010 3
b1100101001110110100100111001010 ;
b1 <
1+
#230000
0(
1$
0+
b11011010011011101011101010110100 0
b11011010011011101011101010110100 4
1)
01
0-
0,
b10110 2
#235000
0%
0&
0$
b11011010011011101010100111001010 "
b11011010011011101010100111001010 3
b11011010011011101010100111001010 ;
19
06
0:
08
b0 <
b11011010011011101010100111001010 =
1+
#240000
0+
b1110010000010100010100011100 0
b1110010000010100010100011100 4
0)
0*
11
1-
0.
b10111 2
#245000
1+
#250000
0+
b110011010011101010011101100110 0
b110011010011101010011101100110 4
1)
01
0-
1.
1,
b11000 2
#255000
1&
1$
09
1:
18
b110011010011101010011101100110 "
b110011010011101010011101100110 3
b110011010011101010011101100110 ;
b1 <
1+
#260000
0+
b10001101001001001111011000011010 0
b10001101001001001111011000011010 4
0,
b11001 2
#265000
0&
0$
b10001101001001001110011101100110 "
b10001101001001001110011101100110 3
b10001101001001001110011101100110 ;
19
0:
08
b0 <
b10001101001001001110011101100110 =
1+
#270000
0+
b111110100110011000001101111101 0
b111110100110011000001101111101 4
0)
1,
b11010 2
#275000
1&
09
1:
18
b111110100110011000001101111101 "
b111110100110011000001101111101 3
b111110100110011000001101111101 ;
b1 <
1+
#280000
1$
0+
b111100111011010010101101111001 0
b111100111011010010101101111001 4
1)
1*
0.
0,
b11011 2
#285000
0&
0$
b111100111011010010001101111101 "
b111100111011010010001101111101 3
b111100111011010010001101111101 ;
19
0:
08
b0 <
b111100111011010010001101111101 =
1+
#290000
0+
b1111010100011000101100111110101 0
b1111010100011000101100111110101 4
0)
0*
11
1-
1.
b11100 2
#295000
1+
#300000
0+
b10111001100011000100001001110011 0
b10111001100011000100001001110011 4
1)
1,
b11101 2
#305000
1(
1$
09
16
1:
18
b10111001100011000100001001110011 "
b10111001100011000100001001110011 3
b10111001100011000100001001110011 ;
b1 <
1+
#310000
1%
0(
0+
b111000010111011100100001110 0
b111000010111011100100001110 4
1*
01
0-
0.
0,
b11110 2
#315000
0%
0&
0$
b111000010111010001001110011 "
b111000010111010001001110011 3
b111000010111010001001110011 ;
19
06
0:
08
b0 <
b111000010111010001001110011 =
1+
#320000
0+
b10011100011011011110011000111000 0
b10011100011011011110011000111000 4
0)
1.
b11111 2
#325000
1+
#330000
0+
b1011011000010111101110110110110 0
b1011011000010111101110110110110 4
1)
11
0.
1,
b100000 2
#335000
1+
#340000
0+
b11000011001100111001000010000110 0
b11000011001100111001000010000110 4
0*
01
1-
0,
b100001 2
#345000
1+
#350000
0+
b1100101010000111100111111001010 0
b1100101010000111100111111001010 4
0)
11
0-
b100010 2
#355000
1+
#360000
0+
b1100100110010000011110111001001 0
b1100100110010000011110111001001 4
1)
1*
1.
1,
b100011 2
#365000
1!
b1111 #
b1111 5
1'
1(
1%
1$
09
1:
18
b1100100110010000011110111001001 "
b1100100110010000011110111001001 3
b1100100110010000011110111001001 ;
b1 <
1+
#370000
b0 #
b0 5
0!
0%
0$
0+
b1001101111100111000000110011011 0
b1001101111100111000000110011011 4
0)
0*
1-
0,
b100100 2
#375000
0'
0(
b1001101111100111001110111001001 "
b1001101111100111001110111001001 3
b1001101111100111001110111001001 ;
0:
08
b0 <
06
b1001101111100111001110111001001 =
1+
#380000
0+
b110101100110000010100001101 0
b110101100110000010100001101 4
0.
b100101 2
#385000
1+
#390000
0+
b1101100010001001111100111011000 0
b1101100010001001111100111011000 4
1)
1*
01
b100110 2
#395000
1+
#400000
0+
b11101100010100001011010011011000 0
b11101100010100001011010011011000 4
0*
1,
b100111 2
#405000
1+
#410000
0+
b1000000100100000101110110000001 0
b1000000100100000101110110000001 4
1*
11
0,
b101000 2
#415000
1+
#420000
0+
b11001011010111001000000010010110 0
b11001011010111001000000010010110 4
0)
0*
1.
b101001 2
#425000
1+
#430000
0+
b10101100010110010101100101011 0
b10101100010110010101100101011 4
1)
1*
0-
0.
b101010 2
#435000
1+
#440000
0+
b11011100111011111001000010111001 0
b11011100111011111001000010111001 4
01
1-
1.
1,
b101011 2
#445000
1%
1$
16
1:
18
b11011100111011111001000010111001 "
b11011100111011111001000010111001 3
b11011100111011111001000010111001 ;
b1 <
1+
#450000
1(
0$
0+
b1111101001010100100010111111010 0
b1111101001010100100010111111010 4
0)
11
b101100 2
#455000
0(
0%
b0 #
b0 5
0!
b1111101001010100101000010111001 "
b1111101001010100101000010111001 3
b1111101001010100101000010111001 ;
06
0:
08
b0 <
b1111101001010100101000010111001 =
1+
#460000
0+
b10110111110111111010101001101111 0
b10110111110111111010101001101111 4
0*
01
0-
b101101 2
#465000
1&
1:
18
b10110111110111111010101001101111 "
b10110111110111111010101001101111 3
b10110111110111111010101001101111 ;
b1 <
1+
#470000
0+
b11100010101111110001101011000101 0
b11100010101111110001101011000101 4
0.
0,
b101110 2
#475000
0&
b11100010101111110000101001101111 "
b11100010101111110000101001101111 3
b11100010101111110000101001101111 ;
19
0:
08
b0 <
b11100010101111110000101001101111 =
1+
#480000
0+
b110001001001001101001101100010 0
b110001001001001101001101100010 4
1-
b101111 2
#485000
1+
#490000
0+
b10010100101111100101100100101 0
b10010100101111100101100100101 4
1*
11
1.
1,
b110000 2
#495000
1(
1%
09
16
1:
18
b10010100101111100101100100101 "
b10010100101111100101100100101 3
b10010100101111100101100100101 ;
b1 <
1+
#500000
0%
0+
b10111000101011011110011001110001 0
b10111000101011011110011001110001 4
0*
0-
b110001 2
#505000
b10111000101011011110101100100101 "
b10111000101011011110101100100101 3
b10111000101011011110101100100101 ;
08
b10111000101011011110101100100101 =
1+
#510000
1$
0+
b10010000001010100011101000100000 0
b10010000001010100011101000100000 4
1)
01
1-
0.
b110010 2
#515000
0(
0$
06
0:
b0 <
1+
#520000
0+
b10111100110011000100001001111001 0
b10111100110011000100001001111001 4
1*
11
0-
0,
b110011 2
#525000
1+
#530000
0+
b1110100100100100001100011101 0
b1110100100100100001100011101 4
1-
1.
b110100 2
#535000
1+
#540000
0+
b1111100000111100101101111111000 0
b1111100000111100101101111111000 4
0)
01
0.
1,
b110101 2
#545000
1+
#550000
0+
b1011111010101100000100010111 0
b1011111010101100000100010111 4
0*
0-
b110110 2
#555000
1+
#560000
0+
b11000101101000010110000010001011 0
b11000101101000010110000010001011 4
0,
b110111 2
#565000
1+
#570000
0+
b10011110110010011100000000111101 0
b10011110110010011100000000111101 4
1*
1.
b111000 2
#575000
1+
#580000
0+
b1101000010100011110010111010000 0
b1101000010100011110010111010000 4
1-
0.
1,
b111001 2
#585000
1+
#590000
0+
b10100101111001111001111001001011 0
b10100101111001111001111001001011 4
0,
b111010 2
#595000
1+
#600000
0+
b11101111100000110111001011011111 0
b11101111100000110111001011011111 4
1)
1,
b111011 2
#605000
1+
#610000
0+
b11101100101110010001101011011001 0
b11101100101110010001101011011001 4
0*
1.
0,
b111100 2
#615000
1+
#620000
0+
b10101110110101110010111001011101 0
b10101110110101110010111001011101 4
0)
11
0.
b111101 2
#625000
1+
#630000
0+
b101100100001001000100101011001 0
b101100100001001000100101011001 4
b111110 2
#635000
1+
#640000
0+
b10000000011110010111110000000000 0
b10000000011110010111110000000000 4
1)
b111111 2
#645000
1+
#650000
0+
b1001000001110011110010110010000 0
b1001000001110011110010110010000 4
1*
0-
1.
1,
b1000000 2
#655000
1!
b1111 #
b1111 5
1'
1(
1%
1$
1:
18
b1001000001110011110010110010000 "
b1001000001110011110010110010000 3
b1001000001110011110010110010000 ;
b1 <
1+
#660000
0'
b0 #
b0 5
0!
0%
0(
1&
0+
b11100010000011101001101011000100 0
b11100010000011101001101011000100 4
0*
01
1-
b1000001 2
#665000
0&
0$
b11100010000011101000010110010000 "
b11100010000011101000010110010000 3
b11100010000011101000010110010000 ;
19
0:
08
b0 <
06
b11100010000011101000010110010000 =
1+
#670000
0+
b1101010000101011111010111010100 0
b1101010000101011111010111010100 4
1*
0-
0,
b1000010 2
#675000
1+
#680000
0+
b11000000011101100100001010000000 0
b11000000011101100100001010000000 4
11
1-
0.
1,
b1000011 2
#685000
1+
#690000
0+
b11110100110110000110111011101001 0
b11110100110110000110111011101001 4
0*
0-
1.
0,
b1000100 2
#695000
1+
#700000
0+
b110000010011100100110101100000 0
b110000010011100100110101100000 4
0)
1*
1-
0.
b1000101 2
#705000
1+
#710000
0+
b110111000101010001010101101110 0
b110111000101010001010101101110 4
1)
0-
1,
b1000110 2
#715000
1+
#720000
0+
b11111000110111000100100011110001 0
b11111000110111000100100011110001 4
0*
01
1.
b1000111 2
#725000
1&
1$
09
1:
18
b11111000110111000100100011110001 "
b11111000110111000100100011110001 3
b11111000110111000100100011110001 ;
b1 <
1+
#730000
0+
b10101101111001111101000001011011 0
b10101101111001111101000001011011 4
1*
0.
b1001000 2
#735000
0&
0$
b10101101111001111100100011110001 "
b10101101111001111100100011110001 3
b10101101111001111100100011110001 ;
19
0:
08
b0 <
b10101101111001111100100011110001 =
1+
#740000
0+
b101000110001100010011101010001 0
b101000110001100010011101010001 4
11
1-
b1001001 2
#745000
1+
#750000
0+
b10101000100111101110100101010 0
b10101000100111101110100101010 4
0)
0*
0-
1.
b1001010 2
#755000
1'
1(
09
1:
18
b10101000100111101110100101010 "
b10101000100111101110100101010 3
b10101000100111101110100101010 ;
b1 <
1+
#760000
b1111 #
b1111 5
1!
1%
1$
0+
b1010111110000011101000110101111 0
b1010111110000011101000110101111 4
1)
1*
1-
b1001011 2
#765000
0!
b0 #
b0 5
0'
0(
0%
0$
b1010111110000011101110100101010 "
b1010111110000011101110100101010 3
b1010111110000011101110100101010 ;
0:
08
b0 <
06
b1010111110000011101110100101010 =
1+
#770000
0+
b10110101010101011101111001101010 0
b10110101010101011101111001101010 4
0*
01
0-
b1001100 2
#775000
1&
1$
1:
18
b10110101010101011101111001101010 "
b10110101010101011101111001101010 3
b10110101010101011101111001101010 ;
b1 <
1+
#780000
1'
1(
0&
0$
0+
b10101110001000111100111001011100 0
b10101110001000111100111001011100 4
0)
11
1-
0.
0,
b1001101 2
#785000
0'
0(
b10101110001000111101111001101010 "
b10101110001000111101111001101010 3
b10101110001000111101111001101010 ;
0:
08
b0 <
b10101110001000111101111001101010 =
1+
#790000
0+
b110011100010000001100001100 0
b110011100010000001100001100 4
1)
0-
1.
1,
b1001110 2
#795000
1'
1(
1$
1:
18
b110011100010000001100001100 "
b110011100010000001100001100 3
b110011100010000001100001100 ;
b1 <
1+
#800000
b1111 #
b1111 5
1!
1%
0$
0+
b10111010111101001110001001110101 0
b10111010111101001110001001110101 4
0)
1*
1-
0.
0,
b1001111 2
#805000
0!
b0 #
b0 5
0'
0(
0%
b10111010111101001110001100001100 "
b10111010111101001110001100001100 3
b10111010111101001110001100001100 ;
0:
08
b0 <
b10111010111101001110001100001100 =
1+
#810000
0+
b1001111110010100100000010 0
b1001111110010100100000010 4
0-
1.
b1010000 2
#815000
1+
#820000
0+
b1111010111101101010101111110101 0
b1111010111101101010101111110101 4
0*
1-
0.
b1010001 2
#825000
1+
#830000
0+
b10110110010111111100100101101 0
b10110110010111111100100101101 4
1*
0-
1.
b1010010 2
#835000
1+
#840000
0+
b100110101111110011111101001101 0
b100110101111110011111101001101 4
1)
0*
01
0.
1,
b1010011 2
#845000
1+
#850000
0+
b11011100010000110000100010111000 0
b11011100010000110000100010111000 4
0)
1-
1.
b1010100 2
#855000
16
1:
18
b11011100010000110000100010111000 "
b11011100010000110000100010111000 3
b11011100010000110000100010111000 ;
b1 <
1+
#860000
1%
1(
1$
0+
b1011011110100111101101110110111 0
b1011011110100111101101110110111 4
1)
1*
11
0-
0.
0,
b1010101 2
#865000
0(
0%
b0 #
b0 5
0!
0$
b1011011110100111100100010111000 "
b1011011110100111100100010111000 3
b1011011110100111100100010111000 ;
06
0:
08
b0 <
b1011011110100111100100010111000 =
1+
#870000
0+
b11001000001110001111010010010000 0
b11001000001110001111010010010000 4
0)
0*
01
1-
1.
1,
b1010110 2
#875000
16
1:
18
b11001000001110001111010010010000 "
b11001000001110001111010010010000 3
b11001000001110001111010010010000 ;
b1 <
1+
#880000
1(
1$
0+
b1101100011010100110110111011000 0
b1101100011010100110110111011000 4
1)
11
0.
0,
b1010111 2
#885000
0(
0$
b1101100011010100111010010010000 "
b1101100011010100111010010010000 3
b1101100011010100111010010010000 ;
06
0:
08
b0 <
b1101100011010100111010010010000 =
1+
#890000
0+
b1100100101111000110100011001 0
b1100100101111000110100011001 4
0)
01
1.
1,
b1011000 2
#895000
16
1:
18
b1100100101111000110100011001 "
b1100100101111000110100011001 3
b1100100101111000110100011001 ;
b1 <
1+
#900000
0+
b11001110100100010100000110 0
b11001110100100010100000110 4
0.
b1011001 2
#905000
0&
b11001110100100110100011001 "
b11001110100100110100011001 3
b11001110100100110100011001 ;
19
06
0:
08
b0 <
b11001110100100110100011001 =
1+
#910000
0+
b1011001001101001110100110110010 0
b1011001001101001110100110110010 4
1)
0,
b1011010 2
#915000
1+
#920000
0+
b1000100100000111010110110001001 0
b1000100100000111010110110001001 4
0)
11
1.
b1011011 2
#925000
1+
#930000
0+
b1010101110111011000110110101011 0
b1010101110111011000110110101011 4
1)
1*
01
1,
b1011100 2
#935000
1%
1$
09
16
1:
18
b1010101110111011000110110101011 "
b1010101110111011000110110101011 3
b1010101110111011000110110101011 ;
b1 <
1+
#940000
0%
0+
b11011001101101000101100110110 0
b11011001101101000101100110110 4
0*
0.
b1011101 2
#945000
0&
0$
b11011001101101000110110101011 "
b11011001101101000110110101011 3
b11011001101101000110110101011 ;
19
06
0:
08
b0 <
b11011001101101000110110101011 =
1+
#950000
0+
b10010111010110011000100000101110 0
b10010111010110011000100000101110 4
0)
0-
1.
0,
b1011110 2
#955000
1+
#960000
0+
b11100000111000000000010011000001 0
b11100000111000000000010011000001 4
1)
1-
b1011111 2
#965000
1+
#970000
0+
b11101001101101001001101011010011 0
b11101001101101001001101011010011 4
0)
1*
11
1,
b1100000 2
#975000
1(
1%
09
16
1:
18
b11101001101101001001101011010011 "
b11101001101101001001101011010011 3
b11101001101101001001101011010011 ;
b1 <
1+
#980000
0+
b11111000110001110001010011110001 0
b11111000110001110001010011110001 4
0-
0.
0,
b1100001 2
#985000
0(
0%
b0 #
b0 5
0!
b11111000110001110001101011010011 "
b11111000110001110001101011010011 3
b11111000110001110001101011010011 ;
06
0:
08
b0 <
b11111000110001110001101011010011 =
1+
#990000
0+
b10110010110100010100101001100101 0
b10110010110100010100101001100101 4
0*
01
1.
1,
b1100010 2
