RTL/b11/dut.v
module b11 ( x_in, stbi, clock, reset, x_out );

 input wire [5:0] x_in;

 input wire stbi;

 input wire clock;

 input wire reset;

 output reg [5:0] x_out;

 reg [5:0] r_in;

 reg [3:0] stato;

 reg [5:0] cont;

 wire signed [8:0] cont1_inv;

 reg signed [8:0] cont1;

 assign cont1_inv = -cont1;

always @(posedge clock) begin 
    $display("achieve node: 1,1"); 
    if (reset == 1'b1) begin $display("achieve node: 1,1,1"); stato = 4'b0000; r_in = 6'b0; cont = 6'b0; cont1 = 9'b0; x_out = 6'b0; end else begin $display("achieve node: 1,1,0");  
    case (stato) 
    4'b0000: begin  cont = 6'b0; $display("achieve node: 1,1,0,1");  r_in = x_in; x_out <= 6'b0; stato = 4'b0001; end 
    4'b0001: begin  r_in = x_in; $display("achieve node: 1,1,0,2");  if (stbi == 1'b1) begin $display("achieve node: 1,1,0,2,1"); stato = 4'b0001; end else begin $display("achieve node: 1,1,0,2,0");  stato = 4'b0010; end end 
    4'b0010:  if (r_in == 6'b0 || r_in == 6'b111111) begin $display("achieve node: 1,1,0,3");  $display("achieve node: 1,1,0,3,1"); cont1 = {3'b0, r_in}; stato = 4'b1000; if (cont < 6'b11001) begin $display("achieve node: 1,1,0,3,1,1"); cont = cont + 1'b1; end else begin $display("achieve node: 1,1,0,3,1,0");  cont = 6'b0; end end else if (r_in <= 6'b011010) begin $display("achieve node: 1,1,0,3,0,1"); stato = 4'b0011; end else begin $display("achieve node: 1,1,0,3,0,0");  stato = 4'b0001; end 
    4'b0011: begin  stato = 4'b0100; $display("achieve node: 1,1,0,4");  if (r_in[0] == 1'b1) begin $display("achieve node: 1,1,0,4,1"); cont1 = {2'b0, cont, 1'b0}; end else begin $display("achieve node: 1,1,0,4,0");  cont1 = {3'b0, cont}; end end 
    4'b0100:  if (r_in[1] == 1'b1) begin $display("achieve node: 1,1,0,5");  $display("achieve node: 1,1,0,5,1"); cont1 = {3'b0, r_in} + cont1; stato = 4'b0101; end else begin $display("achieve node: 1,1,0,5,0");  cont1 = {3'b0, r_in} - cont1; stato = 4'b0110; end 
    4'b0101:  if (cont1 > 9'b011010 && cont1 < 9'b100000000) begin $display("achieve node: 1,1,0,6");  $display("achieve node: 1,1,0,6,1"); cont1 = cont1 - 9'b011010; stato = 4'b0101; end else begin $display("achieve node: 1,1,0,6,0");  stato = 4'b0111; end 
    4'b0110:  if (cont1 > 9'b000111111 && cont1 < 9'b100000000) begin $display("achieve node: 1,1,0,7");  $display("achieve node: 1,1,0,7,1"); cont1 = cont1 + 9'b011010; stato = 4'b0110; end else begin $display("achieve node: 1,1,0,7,0");  stato = 4'b0111; end 
    4'b0111: begin  stato = 4'b1000; $display("achieve node: 1,1,0,8");  if (r_in[3:2] == 2'b00) begin $display("achieve node: 1,1,0,8,1"); cont1 = cont1 - 9'b010101; end else if (r_in[3:2] == 2'b01) begin $display("achieve node: 1,1,0,8,0,1"); cont1 = cont1 - 9'b101010; end else if (r_in[3:2] == 2'b10) begin $display("achieve node: 1,1,0,8,0,0,1"); cont1 = cont1 + 9'b010101; end else begin $display("achieve node: 1,1,0,8,0,0,0");  cont1 = cont1 + 9'b011100; end end 
    4'b1000: begin  stato = 4'b0001; $display("achieve node: 1,1,0,9");  if (cont1 > 9'b100000000) begin $display("achieve node: 1,1,0,9,1"); x_out <= cont1_inv[5:0]; end else begin $display("achieve node: 1,1,0,9,0");  x_out <= cont1[5:0]; end end endcase end end

endmodule

RTL/b11/b11_tb.v
`timescale 1ns/1ps
module b11_tb();
reg [5:0] x_in;
reg stbi;
reg clock;
reg reset;
wire [5:0] x_out;

// 实例化待测模块
b11 uut (
    .x_in(x_in),
    .stbi(stbi),
    .clock(clock),
    .reset(reset),
    .x_out(x_out)
    );

// 时钟激励
initial begin
    clock = 0;
    forever #5 clock = ~clock;
end

// 复位激励
initial begin
    reset = 1;
    #10;
    reset = 0;
end
 
integer i;
initial begin
    x_in = 0;
    stbi = 0;
    #10;
    for(i = 0; i < 100; i = i + 1) begin
        $display("********Period %d********", i);
        x_in = $random & 6'd63;
        stbi = $random & 1'd1;
        if(i == 3) begin x_in = 6'b0; stbi = 0; end
        if(i == 8) begin x_in[3:2] = 2'b11; end
        #10;
    end
    $finish;
end
initial begin
    $dumpfile("wave.vcd");
    $dumpvars(0, b11_tb);
end

endmodule

RTL/b11/wave.vcd
$date
	Wed Apr 16 21:14:20 2025
$end
$version
	Icarus Verilog
$end
$timescale
	1ps
$end
$scope module b11_tb $end
$var wire 6 ! x_out [5:0] $end
$var reg 1 " clock $end
$var reg 1 # reset $end
$var reg 1 $ stbi $end
$var reg 6 % x_in [5:0] $end
$var integer 32 & i [31:0] $end
$scope module uut $end
$var wire 1 " clock $end
$var wire 1 # reset $end
$var wire 1 $ stbi $end
$var wire 6 ' x_in [5:0] $end
$var wire 9 ( cont1_inv [8:0] $end
$var reg 6 ) cont [5:0] $end
$var reg 9 * cont1 [8:0] $end
$var reg 6 + r_in [5:0] $end
$var reg 4 , stato [3:0] $end
$var reg 6 - x_out [5:0] $end
$upscope $end
$upscope $end
$enddefinitions $end
$comment Show the parameter values. $end
$dumpall
$end
#0
$dumpvars
bx -
bx ,
bx +
bx *
bx )
bx (
b0 '
bx &
b0 %
0$
1#
0"
bx !
$end
#5000
b0 !
b0 -
b0 (
b0 *
b0 )
b0 +
b0 ,
1"
#10000
0"
1$
b100100 %
b100100 '
b0 &
0#
#15000
b1 ,
b100100 +
1"
#20000
0"
b1001 %
b1001 '
b1 &
#25000
b1001 +
1"
#30000
0"
b1101 %
b1101 '
b10 &
#35000
b1101 +
1"
#40000
0"
0$
b0 %
b0 '
b11 &
#45000
b10 ,
b0 +
1"
#50000
0"
1$
b1 %
b1 '
b100 &
#55000
b1 )
b1000 ,
1"
#60000
0"
b110110 %
b110110 '
b101 &
#65000
b1 ,
1"
#70000
0"
0$
b101101 %
b101101 '
b110 &
#75000
b10 ,
b101101 +
1"
#80000
0"
b111001 %
b111001 '
b111 &
#85000
b1 ,
1"
#90000
0"
b1101 %
b1101 '
b1000 &
#95000
b10 ,
b1101 +
1"
#100000
0"
1$
b100101 %
b100101 '
b1001 &
#105000
b11 ,
1"
#110000
0"
b10010 %
b10010 '
b1010 &
#115000
b111111110 (
b10 *
b100 ,
1"
#120000
0"
0$
b110010 %
b110010 '
b1011 &
#125000
b110 ,
b111110101 (
b1011 *
1"
#130000
0"
1$
b101000 %
b101000 '
b1100 &
#135000
b111 ,
1"
#140000
0"
b11100 %
b11100 '
b1101 &
#145000
b111011001 (
b100111 *
b1000 ,
1"
#150000
0"
b101101 %
b101101 '
b1110 &
#155000
b100111 !
b100111 -
b1 ,
1"
#160000
0"
0$
b100011 %
b100011 '
b1111 &
#165000
b10 ,
b100011 +
1"
#170000
0"
b0 %
b0 '
b10000 &
#175000
b1 ,
1"
#180000
0"
1$
b101010 %
b101010 '
b10001 &
#185000
b101010 +
1"
#190000
0"
b10110 %
b10110 '
b10010 &
#195000
b10110 +
1"
#200000
0"
b1101 %
b1101 '
b10011 &
#205000
b1101 +
1"
#210000
0"
b101011 %
b101011 '
b10100 &
#215000
b101011 +
1"
#220000
0"
0$
b10 %
b10 '
b10101 &
#225000
b10 ,
b10 +
1"
#230000
0"
1$
b11101 %
b11101 '
b10110 &
#235000
b11 ,
1"
#240000
0"
0$
b100011 %
b100011 '
b10111 &
#245000
b111111111 (
b1 *
b100 ,
1"
#250000
0"
b1010 %
b1010 '
b11000 &
#255000
b101 ,
b111111101 (
b11 *
1"
#260000
0"
b110010 %
b110010 '
b11001 &
#265000
b111 ,
1"
#270000
0"
b1 %
b1 '
b11010 &
#275000
b10010 (
b111101110 *
b1000 ,
1"
#280000
0"
1$
b111000 %
b111000 '
b11011 &
#285000
b10010 !
b10010 -
b1 ,
1"
#290000
0"
0$
b101011 %
b101011 '
b11100 &
#295000
b10 ,
b101011 +
1"
#300000
0"
b110 %
b110 '
b11101 &
#305000
b1 ,
1"
#310000
0"
b111100 %
b111100 '
b11110 &
#315000
b10 ,
b111100 +
1"
#320000
0"
1$
b1011 %
b1011 '
b11111 &
#325000
b1 ,
1"
#330000
0"
b101 %
b101 '
b100000 &
#335000
b101 +
1"
#340000
0"
0$
b111011 %
b111011 '
b100001 &
#345000
b10 ,
b111011 +
1"
#350000
0"
1$
b111110 %
b111110 '
b100010 &
#355000
b1 ,
1"
#360000
0"
b110001 %
b110001 '
b100011 &
#365000
b110001 +
1"
#370000
0"
0$
b100010 %
b100010 '
b100100 &
#375000
b10 ,
b100010 +
1"
#380000
0"
1$
b11111 %
b11111 '
b100101 &
#385000
b1 ,
1"
#390000
0"
b111000 %
b111000 '
b100110 &
#395000
b111000 +
1"
#400000
0"
0$
b11111 %
b11111 '
b100111 &
#405000
b10 ,
b11111 +
1"
#410000
0"
1$
b11011 %
b11011 '
b101000 &
#415000
b1 ,
1"
#420000
0"
0$
b1001 %
b1001 '
b101001 &
#425000
b10 ,
b1001 +
1"
#430000
0"
1$
b10111 %
b10111 '
b101010 &
#435000
b11 ,
1"
#440000
0"
0$
b10110 %
b10110 '
b101011 &
#445000
b111111110 (
b10 *
b100 ,
1"
#450000
0"
b10 %
b10 '
b101100 &
#455000
b110 ,
b111111001 (
b111 *
1"
#460000
0"
1$
b110111 %
b110111 '
b101101 &
#465000
b111 ,
1"
#470000
0"
0$
b10010 %
b10010 '
b101110 &
#475000
b111100100 (
b11100 *
b1000 ,
1"
#480000
0"
1$
b101101 %
b101101 '
b101111 &
#485000
b11100 !
b11100 -
b1 ,
1"
#490000
0"
b11111 %
b11111 '
b110000 &
#495000
b11111 +
1"
#500000
0"
0$
b101 %
b101 '
b110001 &
#505000
b10 ,
b101 +
1"
#510000
0"
1$
b11011 %
b11011 '
b110010 &
#515000
b11 ,
1"
#520000
0"
0$
b111111 %
b111111 '
b110011 &
#525000
b111111110 (
b10 *
b100 ,
1"
#530000
0"
b11000 %
b11000 '
b110100 &
#535000
b110 ,
b111111101 (
b11 *
1"
#540000
0"
b1110 %
b1110 '
b110101 &
#545000
b111 ,
1"
#550000
0"
b111010 %
b111010 '
b110110 &
#555000
b100111 (
b111011001 *
b1000 ,
1"
#560000
0"
1$
b110011 %
b110011 '
b110111 &
#565000
b100111 !
b100111 -
b1 ,
1"
#570000
0"
b101111 %
b101111 '
b111000 &
#575000
b101111 +
1"
#580000
0"
0$
b11111 %
b11111 '
b111001 &
#585000
b10 ,
b11111 +
1"
#590000
0"
1$
b110111 %
b110111 '
b111010 &
#595000
b1 ,
1"
#600000
0"
0$
b100110 %
b100110 '
b111011 &
#605000
b10 ,
b100110 +
1"
#610000
0"
1$
b101001 %
b101001 '
b111100 &
#615000
b1 ,
1"
#620000
0"
b11010 %
b11010 '
b111101 &
#625000
b11010 +
1"
#630000
0"
b110101 %
b110101 '
b111110 &
#635000
b110101 +
1"
#640000
0"
0$
b111001 %
b111001 '
b111111 &
#645000
b10 ,
b111001 +
1"
#650000
0"
b10000 %
b10000 '
b1000000 &
#655000
b1 ,
1"
#660000
0"
b101011 %
b101011 '
b1000001 &
#665000
b10 ,
b101011 +
1"
#670000
0"
b11100 %
b11100 '
b1000010 &
#675000
b1 ,
1"
#680000
0"
1$
b111101 %
b111101 '
b1000011 &
#685000
b111101 +
1"
#690000
0"
0$
b10110 %
b10110 '
b1000100 &
#695000
b10 ,
b10110 +
1"
#700000
0"
b100111 %
b100111 '
b1000101 &
#705000
b11 ,
1"
#710000
0"
b110110 %
b110110 '
b1000110 &
#715000
b111111111 (
b1 *
b100 ,
1"
#720000
0"
b111001 %
b111001 '
b1000111 &
#725000
b101 ,
b111101001 (
b10111 *
1"
#730000
0"
1$
b10100 %
b10100 '
b1001000 &
#735000
b111 ,
1"
#740000
0"
b100 %
b100 '
b1001001 &
#745000
b10011 (
b111101101 *
b1000 ,
1"
#750000
0"
b11011 %
b11011 '
b1001010 &
#755000
b10011 !
b10011 -
b1 ,
1"
#760000
0"
b11001 %
b11001 '
b1001011 &
#765000
b11001 +
1"
#770000
0"
0$
b110110 %
b110110 '
b1001100 &
#775000
b10 ,
b110110 +
1"
#780000
0"
1$
b1001101 &
#785000
b1 ,
1"
#790000
0"
0$
b110 %
b110 '
b1001110 &
#795000
b10 ,
b110 +
1"
#800000
0"
1$
b110111 %
b110111 '
b1001111 &
#805000
b11 ,
1"
#810000
0"
0$
b110100 %
b110100 '
b1010000 &
#815000
b111111111 (
b1 *
b100 ,
1"
#820000
0"
1$
b101000 %
b101000 '
b1010001 &
#825000
b101 ,
b111111001 (
b111 *
1"
#830000
0"
0$
b111 %
b111 '
b1010010 &
#835000
b111 ,
1"
#840000
0"
b1000 %
b1000 '
b1010011 &
#845000
b100011 (
b111011101 *
b1000 ,
1"
#850000
0"
1$
b111101 %
b111101 '
b1010100 &
#855000
b100011 !
b100011 -
b1 ,
1"
#860000
0"
0$
b11100 %
b11100 '
b1010101 &
#865000
b10 ,
b11100 +
1"
#870000
0"
1$
b11010 %
b11010 '
b1010110 &
#875000
b1 ,
1"
#880000
0"
0$
b100110 %
b100110 '
b1010111 &
#885000
b10 ,
b100110 +
1"
#890000
0"
b110011 %
b110011 '
b1011000 &
#895000
b1 ,
1"
#900000
0"
b11110 %
b11110 '
b1011001 &
#905000
b10 ,
b11110 +
1"
#910000
0"
b10101 %
b10101 '
b1011010 &
#915000
b1 ,
1"
#920000
0"
1$
b111001 %
b111001 '
b1011011 &
#925000
b111001 +
1"
#930000
0"
0$
b10110 %
b10110 '
b1011100 &
#935000
b10 ,
b10110 +
1"
#940000
0"
b100110 %
b100110 '
b1011101 &
#945000
b11 ,
1"
#950000
0"
b111101 %
b111101 '
b1011110 &
#955000
b111111111 (
b1 *
b100 ,
1"
#960000
0"
b110 %
b110 '
b1011111 &
#965000
b101 ,
b111101001 (
b10111 *
1"
#970000
0"
1$
b111110 %
b111110 '
b1100000 &
#975000
b111 ,
1"
#980000
0"
b1111 %
b1111 '
b1100001 &
#985000
b10011 (
b111101101 *
b1000 ,
1"
#990000
0"
b111010 %
b111010 '
b1100010 &
#995000
b10011 !
b10011 -
b1 ,
1"
#1000000
0"
b10111 %
b10111 '
b1100011 &
#1005000
b10111 +
1"
#1010000
0"
b1100100 &
