RTL/b11/b11 copy.v
module b11 (
    x_in,
    stbi,
    clock,
    reset,
    x_out
);
  input [5:0] x_in;
  input stbi;
  input clock;
  input reset;
  output reg [5:0] x_out;

  reg [5:0] r_in;
  reg [3:0] stato;
  reg [5:0] cont;
  wire signed [8:0] cont1_inv;

  reg signed [8:0] cont1;

  parameter s_reset = 4'b0000;
  parameter s_datain = 4'b0001;
  parameter s_spazio = 4'b0010;
  parameter s_mul = 4'b0011;
  parameter s_somma = 4'b0100;
  parameter s_rsum = 4'b0101;
  parameter s_rsot = 4'b0110;
  parameter s_compl = 4'b0111;
  parameter s_dataout = 4'b1000;

  assign cont1_inv = -cont1;

  always @(posedge clock) begin
    if (reset == 1'b1) begin
      stato = s_reset;
      r_in  = 6'b0;
      cont  = 6'b0;
      cont1 = 9'b0;
      x_out = 6'b0;
    end else
      case (stato)
        s_reset: begin
          cont = 6'b0;
          r_in = x_in;
          x_out <= 6'b0;
          stato = s_datain;
        end
        s_datain: begin
          r_in = x_in;
          
          if (stbi == 1'b1) begin
            stato = s_datain;
          end
          else begin
            stato = s_spazio;
          end
        end
        
        s_spazio:
        if (r_in == 6'b0 || r_in == 6'b111111) begin
          cont1 = {3'b0, r_in};
          stato = s_dataout;
	
          if (cont < 6'b11001) begin
            cont = cont + 1'b1;
          end
          else begin
            cont = 6'b0;
          end
        end else if (r_in <= 6'b011010) begin
          stato = s_mul;
        end
        else begin
          stato = s_datain;
        end

        s_mul: begin
          stato = s_somma;
          	
          if (r_in[0] == 1'b1)  begin  
            cont1 = {2'b0, cont, 1'b0};
          end
          else begin
            cont1 = {3'b0, cont};
          end
        end

        s_somma:
        if (r_in[1] == 1'b1) begin
          cont1 = {3'b0, r_in} + cont1;
          stato = s_rsum;
        end else begin
          cont1 = {3'b0, r_in} - cont1;
          stato = s_rsot;
        end

        s_rsum:
        if (cont1 > 9'b011010 && cont1 < 9'b100000000) begin
          cont1 = cont1 - 9'b011010;
          stato = s_rsum;
        end else begin
          stato = s_compl;
        end

        s_rsot:
        if (cont1 > 9'b000111111 && cont1 < 9'b100000000) begin
          cont1 = cont1 + 9'b011010;
          stato = s_rsot;
        end else begin
          stato = s_compl;
        end

        s_compl: begin
		      stato = s_dataout;
          
          if (r_in[3:2] == 2'b00) begin
            cont1 = cont1 - 9'b010101;
          end
          else if (r_in[3:2] == 2'b01) begin
            cont1 = cont1 - 9'b101010;
          end
          else if (r_in[3:2] == 2'b10) begin
            cont1 = cont1 + 9'b010101;
          end
          else begin
            cont1 = cont1 + 9'b011100;
          end
        end

        s_dataout: begin
          stato = s_datain;

          if (cont1 > 9'b100000000) begin
            x_out <= cont1_inv[5:0];  //cont1[5:0];target;
          end
          else begin
            x_out <= cont1[5:0];
          end
        end
      endcase
  end
endmodule

RTL/b11/b11_tb.v
module b11_tb();

    // Generated top module signals
    reg  clock;
    reg  reset;
    reg  [5:0]x_in = 6'b0;
    reg  stbi = 1'b0;

    wire [5:0]x_out;
    wire [8:0]s_xout;
    // assign s_xout = 9'sb111111;
    // Generated top module instance
    b11 _conc_top_inst(
            .clock     ( clock ),
            .reset     ( reset ),
            .x_in     ( x_in ),
            .stbi     ( stbi ),
            .x_out     ( x_out ));

    // Generated clock pulse
    always begin
        #5 clock = ~clock;
    end
    integer i, seed;
    // Generated initial block
    initial begin
        clock = 1'b0;
        reset = 1'b0;
        x_in = 6'b0;
        stbi = 1'b0;

        #2 clock = 1'b1;
        reset = 1'b1;
        #5 reset = 1'b0;

        for(i= 0; i<1; i++) begin
            #1;
            x_in = $random(seed);
            stbi = $random(seed);
            #9;
            $display("Period %d: x_in = %b, stbi = %b, x_out = %b", i, x_in, stbi, x_out);
        end

        #1;
        x_in = 6'b000010;
        stbi = 1'b0;
        #9;
        $display("x_in = %b, stbi = %b, x_out = %b", x_in, stbi, x_out);

        seed = $time;
        for(i= 2; i<12; i++) begin
            #1;
            x_in = $random(seed);
            stbi = $random(seed);
            #9;
            $display("Period %d: x_in = %b, stbi = %b, x_out = %b", i, x_in, stbi, x_out);
        end        

        $finish;
    end

    initial
    begin            
        $dumpfile("wave.vcd");        //生成的vcd文件名称
        $dumpvars(0, b11_tb);    //tb模块名称
    end 
endmodule

RTL/b11/wave.vcd
$date
	Fri Dec 13 13:50:07 2024
$end
$version
	Icarus Verilog
$end
$timescale
	1s
$end
$scope module b11_tb $end
$var wire 6 ! x_out [5:0] $end
$var reg 1 " clock $end
$var reg 1 # reset $end
$var reg 1 $ stbi $end
$var reg 6 % x_in [5:0] $end
$var integer 32 & i [31:0] $end
$var integer 32 ' seed [31:0] $end
$scope module _conc_top_inst $end
$var wire 1 " clock $end
$var wire 1 # reset $end
$var wire 1 $ stbi $end
$var wire 6 ( x_in [5:0] $end
$var wire 9 ) cont1_inv [8:0] $end
$var parameter 4 * s_compl $end
$var parameter 4 + s_datain $end
$var parameter 4 , s_dataout $end
$var parameter 4 - s_mul $end
$var parameter 4 . s_reset $end
$var parameter 4 / s_rsot $end
$var parameter 4 0 s_rsum $end
$var parameter 4 1 s_somma $end
$var parameter 4 2 s_spazio $end
$var reg 6 3 cont [5:0] $end
$var reg 9 4 cont1 [8:0] $end
$var reg 6 5 r_in [5:0] $end
$var reg 4 6 stato [3:0] $end
$var reg 6 7 x_out [5:0] $end
$upscope $end
$upscope $end
$enddefinitions $end
$comment Show the parameter values. $end
$dumpall
b10 2
b100 1
b101 0
b110 /
b0 .
b11 -
b1000 ,
b1 +
b111 *
$end
#0
$dumpvars
bx 7
bx 6
bx 5
bx 4
bx 3
bx )
b0 (
bx '
bx &
b0 %
0$
0#
0"
bx !
$end
#2
b0 !
b0 7
b0 )
b0 4
b0 3
b0 5
b0 6
1#
1"
#5
0"
#7
b0 &
0#
#8
1$
b100100 %
b100100 (
b1000000100010010101110011001111 '
#10
b1 6
b100100 5
1"
#15
0"
#17
b1 &
#18
0$
b10 %
b10 (
#20
b10 6
b10 5
1"
#25
0"
#27
b10 &
b11011 '
#28
b0 %
b0 (
b11111101010101011000010000100001 '
#30
b11 6
1"
#35
0"
#37
b11 &
#38
1$
b110010 %
b110010 (
b100111100100110110100010111 '
#40
b100 6
1"
#45
0"
#47
b100 &
#48
0$
b100101 %
b100101 (
b10001101000001010010000001111101 '
#50
b101 6
b111111110 )
b10 4
1"
#55
0"
#57
b101 &
#58
1$
b100000 %
b100000 (
b11001001110001001101111111010011 '
#60
b111 6
1"
#65
0"
#67
b110 &
#68
0$
b100011 %
b100011 (
b10100001111000010100010011001 '
#70
b10011 )
b111101101 4
b1000 6
1"
#75
0"
#77
b111 &
#78
1$
b10101 %
b10101 (
b10101000111100100001010001001111 '
#80
b10011 !
b10011 7
b1 6
1"
#85
0"
#87
b1000 &
#88
0$
b10010 %
b10010 (
b1000011010010101011100001110101 '
#90
b10 6
b10010 5
1"
#95
0"
#97
b1001 &
#98
b1101 %
b1101 (
b1101100001101101000011010001011 '
#100
b11 6
1"
#105
0"
#107
b1010 &
#108
1$
b100110 %
b100110 (
b11101010100010001010110000010001 '
#110
b0 )
b0 4
b100 6
1"
#115
0"
#117
b1011 &
#118
0$
b11000 %
b11000 (
b10010001000011000111001010000111 '
#120
b101 6
b111101110 )
b10010 4
1"
#125
0"
#127
b1100 &
