RTL/rtc_clock/rtc_clock.sv

module	rtc_clock(
	input  logic        clk_i,
	input  logic        rstn_i,

	input  logic        clock_update_i,
	output logic [21:0] clock_o,
	input  logic [21:0] clock_i,

	input  logic  [14:0] init_sec_cnt_i,

	output logic        update_day_o
);

	logic [7:0] r_seconds;
	logic [7:0] r_minutes;
	logic [6:0] r_hours;

	logic [7:0] s_seconds;
	logic [7:0] s_minutes;
	logic [6:0] s_hours;

	logic [14:0] r_sec_counter;

	logic s_update_seconds;
	logic s_update_minutes;
	logic s_update_hours;

	assign s_seconds = clock_i[7:0];
	assign s_minutes = clock_i[15:8];
	assign s_hours   = clock_i[21:16];

	assign s_update_seconds = r_sec_counter == 15'h7FFF;
	assign s_update_minutes = s_update_seconds & (r_seconds == 8'h59);
	assign s_update_hours   = s_update_minutes & (r_minutes == 8'h59);

	assign update_day_o   = s_update_hours & (r_hours == 6'h23);
	assign clock_o        = {r_hours,r_minutes,r_seconds};


    always @ (posedge clk_i or negedge rstn_i)
    begin
        if(~rstn_i)
            r_sec_counter <= 'h0;
        else
        begin
        	if (clock_update_i)
        		r_sec_counter <= init_sec_cnt_i;
        	else
            	r_sec_counter <= r_sec_counter + 1;
        end
    end

	always @(posedge clk_i or negedge rstn_i) begin
		if(~rstn_i)
			r_seconds <= 0;
		else begin
			if (clock_update_i)
				r_seconds <= s_seconds;
			else if (s_update_seconds) begin // advance the seconds
					if (r_seconds[7:4] <= 4'h4 && r_seconds[3:0] == 4'h9) begin
						r_seconds[7:4] <= r_seconds[7:4] + 4'h1;
						r_seconds[3:0] <= 4'h0;
					end	else if (r_seconds[7:4] ==4'h5 && r_seconds[3:0] == 4'h9) begin
						r_seconds[7:4] <= 4'h0;
						r_seconds[3:0] <= 4'h0;
					end else
						r_seconds <= r_seconds + 8'h1;
				end
		end
	end

	always @(posedge clk_i or negedge rstn_i) begin
		if(~rstn_i)
			r_minutes <= 0;
		else begin
			if (clock_update_i)
				r_minutes <= s_minutes;
			else if (s_update_minutes) begin // advance the minutes
					if (r_minutes[7:4] <= 4'h4 && r_minutes[3:0] == 4'h9) begin
						r_minutes[7:4] <= r_minutes[7:4] + 4'h1;
						r_minutes[3:0] <= 4'h0;
					end	else if (r_minutes[7:4] ==4'h5 && r_minutes[3:0] == 4'h9) begin
						r_minutes[7:4] <= 4'h0;
						r_minutes[3:0] <= 4'h0;
					end else
						r_minutes <= r_minutes + 8'h1;
				end
		end
	end

	always @(posedge clk_i or negedge rstn_i) begin
		if(~rstn_i)
			r_hours <= 0;
		else begin
			if (clock_update_i)
				r_hours <= s_hours;
			else if (s_update_hours) begin // advance the hours
					if (r_hours[5:4] <= 2'h1 && r_hours[3:0] == 4'h9) begin
						r_hours[5:4] <= r_hours[5:4] + 2'h1;
						r_hours[3:0] <= 4'h0;
					end else if (r_hours[5:0] == 6'h24) begin
						r_hours <= 6'h00;
					end else
						r_hours <= r_hours + 6'h1;
				end
		end
	end

// property clock_max;
// 	@(posedge clk_i) disable iff (!rstn_i) (clock_o <= 22'h235959);
// endproperty

// property update_day_flag;
// 	@(posedge clk_i) disable iff (!rstn_i) (clock_o == 22'h235959 && s_update_seconds && ~clock_update_i)|-> update_day_o;
// endproperty

// assert property (clock_max);
// assert property (update_day_flag);
endmodule

RTL/rtc_clock/rtc_clock_tb.v
//~ `New testbench
`timescale  1ns / 1ps

module tb_rtc_clock;

// rtc_clock Parameters
parameter PERIOD  = 10;


// rtc_clock Inputs
reg           clk_i                   = 0 ;
reg           rstn_i                  = 0 ;
reg           clock_update_i          = 0 ;
reg    [21:0] clock_i                 = 0 ;
reg    [14:0] init_sec_cnt_i          = 0 ;

// rtc_clock Outputs
wire   [21:0] clock_o                 ;
wire          update_day_o            ;


initial
begin
    forever #(PERIOD/2)  clk_i=~clk_i;
end

initial
begin
    #(PERIOD*2) rstn_i  =  1;
end

rtc_clock  u_rtc_clock (
    .        clk_i           (         clk_i            ),
    .        rstn_i          (         rstn_i           ),
    .        clock_update_i  (         clock_update_i   ),
    . clock_i         (  clock_i          ),
    . init_sec_cnt_i  (  init_sec_cnt_i   ),

    . clock_o         (  clock_o          ),
    .        update_day_o    (         update_day_o     )
);

initial
begin
    # (PERIOD*2);
    clock_i = 22'h235859;
    init_sec_cnt_i = 15'h7ffe;
    clock_update_i = 1;
    # PERIOD clock_update_i = 0;
    # (PERIOD*4);

    clock_i = 22'h225959;
    init_sec_cnt_i = 15'h7ffe;
    clock_update_i = 1;
    # PERIOD clock_update_i = 0;
    # (PERIOD*4);

    clock_i = 22'h235959;
    init_sec_cnt_i = 15'h7ffe;
    clock_update_i = 1;
    # PERIOD clock_update_i = 0;
    # (PERIOD*4);

    $finish;
end

initial
begin            
    $dumpfile("wave.vcd");        //生成的vcd文件名称
    $dumpvars(0, tb_rtc_clock);    //tb模块名称
end 

endmodule

RTL/rtc_clock/wave.vcd
$date
	Fri Dec 27 09:43:05 2024
$end
$version
	Icarus Verilog
$end
$timescale
	1ps
$end
$scope module tb_rtc_clock $end
$var wire 1 ! update_day_o $end
$var wire 22 " clock_o [21:0] $end
$var parameter 32 # PERIOD $end
$var reg 1 $ clk_i $end
$var reg 22 % clock_i [21:0] $end
$var reg 1 & clock_update_i $end
$var reg 15 ' init_sec_cnt_i [14:0] $end
$var reg 1 ( rstn_i $end
$scope module u_rtc_clock $end
$var wire 1 $ clk_i $end
$var wire 22 ) clock_i [21:0] $end
$var wire 1 & clock_update_i $end
$var wire 15 * init_sec_cnt_i [14:0] $end
$var wire 1 ( rstn_i $end
$var wire 1 + s_update_hours $end
$var wire 1 , s_update_minutes $end
$var wire 1 ! update_day_o $end
$var wire 1 - s_update_seconds $end
$var wire 8 . s_seconds [7:0] $end
$var wire 8 / s_minutes [7:0] $end
$var wire 7 0 s_hours [6:0] $end
$var wire 22 1 clock_o [21:0] $end
$var reg 7 2 r_hours [6:0] $end
$var reg 8 3 r_minutes [7:0] $end
$var reg 15 4 r_sec_counter [14:0] $end
$var reg 8 5 r_seconds [7:0] $end
$upscope $end
$upscope $end
$enddefinitions $end
$comment Show the parameter values. $end
$dumpall
b1010 #
$end
#0
$dumpvars
bx 5
bx 4
bx 3
bx 2
bx 1
b0 0
b0 /
b0 .
x-
x,
x+
b0 *
b0 )
0(
b0 '
0&
b0 %
0$
bx "
x!
$end
#5000
0,
0+
0!
b0 "
b0 1
0-
b0 4
b0 5
b0 3
b0 2
1$
#10000
0$
#15000
1$
#20000
b1011001 .
b1011000 /
b100011 0
0$
1&
b111111111111110 '
b111111111111110 *
b1000110101100001011001 %
b1000110101100001011001 )
1(
#25000
b1000110101100001011001 "
b1000110101100001011001 1
b111111111111110 4
b1011001 5
b1011000 3
b100011 2
1$
#30000
0$
0&
#35000
1,
1-
b111111111111111 4
1$
#40000
0$
#45000
0!
0,
0+
b1000110101100100000000 "
b1000110101100100000000 1
0-
b0 4
b0 5
b1011001 3
1$
#50000
0$
#55000
b1 4
1$
#60000
0$
#65000
b10 4
1$
#70000
b1011001 /
b100010 0
0$
1&
b1000100101100101011001 %
b1000100101100101011001 )
#75000
b1000100101100101011001 "
b1000100101100101011001 1
b100010 2
b1011001 5
b111111111111110 4
1$
#80000
0$
0&
#85000
1+
1,
1-
b111111111111111 4
1$
#90000
0$
#95000
0+
b1000110000000000000000 "
b1000110000000000000000 1
0,
b100011 2
b0 3
b0 5
0-
b0 4
1$
#100000
0$
#105000
b1 4
1$
#110000
0$
#115000
b10 4
1$
#120000
b100011 0
0$
1&
b1000110101100101011001 %
b1000110101100101011001 )
#125000
b1000110101100101011001 "
b1000110101100101011001 1
b111111111111110 4
b1011001 5
b1011001 3
1$
#130000
0$
0&
#135000
1!
1+
1,
1-
b111111111111111 4
1$
#140000
0$
#145000
0,
0+
0!
b1001000000000000000000 "
b1001000000000000000000 1
0-
b0 4
b0 5
b0 3
b100100 2
1$
#150000
0$
#155000
b1 4
1$
#160000
0$
#165000
b10 4
1$
